Workbook

Sheet 資產表
Q3: =R19 -> 現金比例 | R3: {=index(R20:R1012,Counta(R20:R1012))} -> 0.13325509
Q4: =W19 -> 基金比例 | R4: {=index(W20:W1012,Counta(W20:W1012))} -> 0.11281632
Q5: =AE19 -> 證券比例 | R5: {=index(AE20:AE1012,Counta(AE20:AE1012))} -> 0.64426912
Q6: TW Stock | R6: =R5-R7 -> 0.44669768
Q7: US Stock | R7: {=index(AF20:AF1012,Counta(AF20:AF1012))*R5} -> 0.19757144
Q8: TW Fund | R8: =R4-R9 -> 0.078191656
Q9: US Fund | R9: {=index(X20:X1012,Counta(X20:X1012))*R4} -> 0.034624662
Q10: Cash | R10: =R3 -> 0.13325509
Q11: Real Estate | R11: {=(index(AN42:AN1012,Counta(AN42:AN1012))-index(AV42:AV1012,Counta(AV42:AV1012)))/index(F42:F1012,Counta(F42:F1012))} -> 0.083637776
Q12: Crypto | R12: {=index(AJ20:AJ1012,Counta(AJ20:AJ1012))} -> 0.026021698
F14: 資產 | AV14: 負債
AR17: 即時匯率(USD) | AS17: =IFERROR(__xludf.DUMMYFUNCTION("GOOGLEFINANCE(""Currency:USDTWD"")"),31.426800000000004) -> 31.4268
C18: 收入 | E18: 月總收入(薪資+業外) | F18: 淨資產 (不含斜槓) | G18: 資產mom | H18: 資產yoy | I18: 銀行存款 | S18: 基金現值 | Y18: 證券現值 | AG18: 加密貨幣現值 | AK18: 斜槓資本 | AN18: 房屋累積投入資金 | AV18: 貸款餘額
A19: 統計日期 | B19: 月份 | C19: 薪資 | D19: 利息/回饋/投資 | I19: 國泰世華 | J19: 台新Richart | K19: 永豐DAWHO | L19: 郵局 | M19: 富邦網銀 | N19: 臺企銀 | O19: 國泰世華(美金) | P19: 富邦網銀(美金) | Q19: 總現金存款 | R19: 現金比例 | S19: 統一投信 | T19: 台新Richart | U19: 國泰投信(美金) | V19: 總基金現值 | W19: 基金比例 | X19: 美元基金比例 | Y19: 臺企銀證券 | Z19: 國泰證券 | AA19: 富邦證券(美金) | AB19: 國泰證券(美金) | AC19: 嘉信 (美金) | AD19: 總證券現值 | AE19: 證券比例 | AF19: 美股占證券比例 | AG19: 台灣交易所(MaicoinMax/ Hoyabit) | AH19: 海外交易所/錢包 | AI19: 總加密貨幣現值 | AJ19: 加密貨幣比例 | AK19: MoleculeX | AL19: Relifetek | AM19: 總斜槓資本額 | AO19: 睿來股權 | AP19: 聚動股權 | AQ19: 聚動股價 元/股 | AR19: 聚動股權現值 | AS19: 匯率 TWD/USD | AU19: Richart卡費 | AV19: 三信房貸
A20: 44766 | B20: 44766 | C20: 162321 | D20: 4319.21 | E20: =SUM(C20:D20) -> 166640.21 | F20: =SUM(Q20,V20,AD20,AN20)-AV20 -> 1592820.6 | G20: - | H20: - | I20: 317657 | J20: 5538 | K20: - | L20: 9023 | M20: 51239 | N20: 111823 | O20: 700.53 | P20: 125.58 | Q20: =SUM(I20:N20)+SUM(O20:P20)*$AS20 -> 519907.41 | R20: =Q20/F20 -> 0.32640677 | S20: 168939 | T20: 5658 | U20: 889.69 | V20: =SUM(S20:T20)+U20*$AS20 -> 201119.82 | W20: =V20/F20 -> 0.12626646 | X20: =sum(T20,U20*AS20)/V20 -> 0.16000818 | Y20: 651576 | Z20: 187740 | AA20: =272.7+816.73 -> 1089.43 | AC20: - | AD20: =SUM(Y20:Z20)+AA20*$AS20 -> 871793.32 | AE20: =AD20/F20 -> 0.54732677 | AF20: =SUM(AA20:AC20)*AS20/AD20 -> 0.037253468 | AG20: - | AH20: - | AJ20: - | AK20: 250000 | AL20: 250000 | AM20: =SUM(AK20:AL20) -> 500000 | AO20: 250000 | AP20: 250000 | AQ20: 1 | AR20: =AP20*AQ20 -> 250000 | AS20: 29.8113 | AU20: 17737
A21: 44807 | B21: 44804 | C21: 58076 | D21: 14540 | E21: =SUM(C21:D21) -> 72616 | F21: =SUM(Q21,V21,AD21,AN21)-AV21 -> 1597795.9 | G21: =(F21-F20)/F20 -> 0.0031235825 | H21: - | I21: 343132 | J21: 1715 | K21: - | L21: 2874 | M21: 21228 | N21: 20590 | O21: 600.53 | P21: 221.66 | Q21: =SUM(I21:N21)+SUM(O21:P21)*$AS21 -> 414719.97 | R21: =Q21/F21 -> 0.25955754 | S21: 180785 | T21: 6364 | U21: 923.66 | V21: =SUM(S21:T21)+U21*$AS21 -> 215437.66 | W21: =V21/F21 -> 0.13483428 | X21: =sum(T21,U21*AS21)/V21 -> 0.16084773 | Y21: 711110 | Z21: 200380 | AA21: =349.08+673.6+810.63 -> 1833.31 | AC21: - | AD21: =SUM(Y21:Z21)+AA21*$AS21 -> 967638.24 | AE21: =AD21/F21 -> 0.60560818 | AF21: =SUM(AA21:AC21)*AS21/AD21 -> 0.058026061 | AG21: - | AH21: - | AJ21: - | AK21: 250000 | AL21: 250000 | AM21: =SUM(AK21:AL21) -> 500000 | AO21: 250000 | AP21: 250000 | AQ21: 1 | AR21: =AP21*AQ21 -> 250000 | AS21: 30.6267 | AU21: 17245
A22: 44828 | B22: 44828 | C22: 69273 | D22: 21763 | E22: =SUM(C22:D22) -> 91036 | F22: =SUM(Q22,V22,AD22,AN22)-AV22 -> 1668736.6 | G22: =(F22-F21)/F21 -> 0.044399105 | H22: - | I22: =364133+25917 -> 390050 | J22: 3944 | K22: - | L22: 1720 | M22: 2221 | N22: 34212 | O22: 500.53 | P22: 821.66 | Q22: =SUM(I22:N22)+SUM(O22:P22)*$AS22 -> 474199.25 | R22: =Q22/F22 -> 0.28416663 | S22: 188988 | T22: 6844 | U22: 988.9 | V22: =SUM(S22:T22)+U22*$AS22 -> 227283.96 | W22: =V22/F22 -> 0.13620123 | X22: =sum(T22,U22*AS22)/V22 -> 0.16849391 | Y22: 701640 | Z22: 208656 | AA22: =328.04+636.8+825.99 -> 1790.83 | AC22: - | AD22: =SUM(Y22:Z22)+AA22*$AS22 -> 967253.35 | AE22: =AD22/F22 -> 0.57963214 | AF22: =SUM(AA22:AC22)*AS22/AD22 -> 0.058885656 | AG22: - | AH22: - | AJ22: - | AK22: 250000 | AL22: 250000 | AM22: =SUM(AK22:AL22) -> 500000 | AO22: 250000 | AP22: 250000 | AQ22: 1 | AR22: =AP22*AQ22 -> 250000 | AS22: 31.805 | AU22: 4957
A23: 44860 | B23: 44860 | C23: 51743 | D23: 22546.54 | E23: =SUM(C23:D23) -> 74289.54 | F23: =SUM(Q23,V23,AD23,AN23)-AV23 -> 1580257.9 | G23: =(F23-F22)/F22 -> -0.053021336 | H23: - | I23: =441659+50388 -> 492047 | J23: 4991 | K23: - | L23: 3695 | M23: 2221 | N23: =27860-13020 -> 14840 | O23: 400.53 | P23: 743.81 | Q23: =SUM(I23:N23)+SUM(O23:P23)*$AS23 -> 554834.57 | R23: =Q23/F23 -> 0.3511038 | S23: 167769 | T23: 7123 | U23: 1033.66 | V23: =SUM(S23:T23)+U23*$AS23 -> 208350.02 | W23: =V23/F23 -> 0.13184558 | X23: =sum(T23,U23*AS23)/V23 -> 0.19477331 | Y23: 678688 | Z23: 83545 | AA23: =419.7+640.8+633.75 -> 1694.25 | AC23: - | AD23: =SUM(Y23:Z23)+AA23*$AS23 -> 817073.33 | AE23: =AD23/F23 -> 0.51705061 | AF23: =SUM(AA23:AC23)*AS23/AD23 -> 0.067118004 | AG23: - | AH23: - | AJ23: - | AK23: 250000 | AL23: 250000 | AM23: =SUM(AK23:AL23) -> 500000 | AO23: 250000 | AP23: 250000 | AQ23: 1 | AR23: =AP23*AQ23 -> 250000 | AS23: 32.3685
A24: 44899 | B24: 44895 | C24: 51743 | D24: 13148 | E24: =SUM(C24:D24) -> 64891 | F24: =SUM(Q24,V24,AD24,AN24)-AV24 -> 1735312.1 | G24: =(F24-F23)/F23 -> 0.098119511 | H24: - | I24: =419950+47236 -> 467186 | J24: 1030 | K24: - | L24: 566 | M24: 2221 | N24: 1570 | O24: 1300.53 | P24: 752.97 | Q24: =SUM(I24:N24)+SUM(O24:P24)*$AS24 -> 535313.59 | R24: =Q24/F24 -> 0.30848261 | S24: 217486 | T24: 8168 | U24: 1178.47 | V24: =SUM(S24:T24)+U24*$AS24 -> 261659.79 | W24: =V24/F24 -> 0.15078544 | X24: =sum(T24,U24*AS24)/V24 -> 0.16882148 | Y24: 783954 | Z24: 102407 | AA24: =451.85+664.8+584.58 -> 1701.23 | AC24: - | AD24: =SUM(Y24:Z24)+AA24*$AS24 -> 938338.68 | AE24: =AD24/F24 -> 0.54073195 | AF24: =SUM(AA24:AC24)*AS24/AD24 -> 0.055393304 | AG24: - | AH24: - | AJ24: - | AK24: 250000 | AL24: 250000 | AM24: =SUM(AK24:AL24) -> 500000 | AO24: 250000 | AP24: 250000 | AQ24: 1 | AR24: =AP24*AQ24 -> 250000 | AS24: 30.553
A25: 44925 | B25: 44925 | C25: =51743+110190+7000 -> 168933 | D25: 5627.9 | E25: =SUM(C25:D25) -> 174560.9 | F25: =SUM(Q25,V25,AD25,AN25)-AV25 -> 1769795 | G25: =(F25-F24)/F24 -> 0.019871341 | H25: - | I25: =51964+453119 -> 505083 | J25: 1916 | K25: - | L25: 574 | M25: 2369 | N25: 2935 | O25: 1202.87 | P25: 627.38 | Q25: =SUM(I25:N25)+SUM(O25:P25)*$AS25 -> 569004.36 | R25: =Q25/F25 -> 0.32150862 | S25: 206934 | T25: 8016 | U25: 1112.3 | V25: =SUM(S25:T25)+U25*$AS25 -> 249060.35 | W25: =V25/F25 -> 0.14072836 | X25: =sum(T25,U25*AS25)/V25 -> 0.16914113 | Y25: 769186 | Z25: 135041 | AA25: =424.95+636.8+487.28 -> 1549.03 | AC25: - | AD25: =SUM(Y25:Z25)+AA25*$AS25 -> 951730.33 | AE25: =AD25/F25 -> 0.53776302 | AF25: =SUM(AA25:AC25)*AS25/AD25 -> 0.049912593 | AG25: - | AH25: - | AJ25: - | AK25: 350000 | AL25: 250000 | AM25: =SUM(AK25:AL25) -> 600000 | AO25: 250000 | AP25: 265625 | AQ25: 6.4 | AR25: =AP25*AQ25 -> 1700000 | AS25: 30.6665 | AU25: 聚動增資 +50000 (50000)
A26: 44956 | B26: 44956 | C26: 62193 | D26: 248.17 | E26: =SUM(C26:D26) -> 62441.17 | F26: =SUM(Q26,V26,AD26,AN26)-AV26 -> 1862470.9 | G26: =(F26-F25)/F25 -> 0.052365327 | H26: - | I26: =383774+41996 -> 425770 | J26: =11529-9276 -> 2253 | K26: - | L26: 695 | M26: 2369 | N26: 2935 | O26: 2102.87 | P26: =426.74+115.29 -> 542.03 | Q26: =SUM(I26:N26)+SUM(O26:P26)*$AS26 -> 513798.8 | R26: =Q26/F26 -> 0.27586943 | S26: 220040 | T26: 9115 | U26: 1353.41 | V26: =SUM(S26:T26)+U26*$AS26 -> 269977.23 | W26: =V26/F26 -> 0.14495648 | X26: =sum(T26,U26*AS26)/V26 -> 0.1849683 | Y26: 828283 | Z26: 192220 | AA26: =542.88+674.8+711.6 -> 1929.28 | AC26: - | AD26: =SUM(Y26:Z26)+AA26*$AS26 -> 1078694.9 | AE26: =AD26/F26 -> 0.57917409 | AF26: =SUM(AA26:AC26)*AS26/AD26 -> 0.053946586 | AG26: - | AH26: - | AJ26: - | AK26: 350000 | AL26: 250000 | AM26: =SUM(AK26:AL26) -> 600000 | AO26: 250000 | AP26: 265625 | AQ26: 6.4 | AR26: =AP26*AQ26 -> 1700000 | AS26: 30.1625
A27: 44985 | B27: 44985 | C27: 52394 | D27: =13230+251 -> 13481 | E27: =SUM(C27:D27) -> 65875 | F27: =SUM(Q27,V27,AD27,AN27)-AV27 -> 1918473.2 | G27: =(F27-F26)/F26 -> 0.030068778 | H27: - | I27: 420762 | J27: 795 | K27: - | L27: 569 | M27: 2369 | N27: 2935 | O27: 2002.87 | P27: 352.29 | Q27: =SUM(I27:N27)+SUM(O27:P27)*$AS27 -> 499647.45 | R27: =Q27/F27 -> 0.26044016 | S27: 249010 | T27: 9821 | U27: 1489.81 | V27: =SUM(S27:T27)+U27*$AS27 -> 304513.79 | W27: =V27/F27 -> 0.15872716 | X27: =sum(T27,U27*AS27)/V27 -> 0.1822702 | Y27: 831701 | Z27: 214323 | AA27: =532.86+656+1038.15 -> 2227.01 | AC27: - | AD27: =SUM(Y27:Z27)+AA27*$AS27 -> 1114311.9 | AE27: =AD27/F27 -> 0.58083269 | AF27: =SUM(AA27:AC27)*AS27/AD27 -> 0.06128259 | AG27: - | AH27: - | AJ27: - | AK27: 350000 | AL27: 250000 | AM27: =SUM(AK27:AL27) -> 600000 | AO27: 250000 | AP27: 265625 | AQ27: 6.4 | AR27: =AP27*AQ27 -> 1700000 | AS27: 30.6635
A28: 45014 | B28: 45014 | C28: 51697 | D28: 7886.32 | E28: =SUM(C28:D28) -> 59583.32 | F28: =SUM(Q28,V28,AD28,AN28)-AV28 -> 1958878.8 | G28: =(F28-F27)/F27 -> 0.02106133 | H28: - | I28: =16419+396558 -> 412977 | J28: 1266 | K28: - | L28: 1569 | M28: 2369 | N28: 2601 | O28: =257.6+1634.37 -> 1891.97 | P28: =131.33+95 -> 226.33 | Q28: =SUM(I28:N28)+SUM(O28:P28)*$AS28 -> 485330.41 | R28: =Q28/F28 -> 0.24775929 | S28: 262070 | T28: 10173 | U28: 1542.54 | V28: =SUM(S28:T28)+U28*$AS28 -> 319246.97 | W28: =V28/F28 -> 0.16297434 | X28: =sum(T28,U28*AS28)/V28 -> 0.17909949 | Y28: 853031 | Z28: 231461 | AA28: =101.03+676.4+1513.52 -> 2290.95 | AC28: - | AD28: =SUM(Y28:Z28)+AA28*$AS28 -> 1154301.4 | AE28: =AD28/F28 -> 0.58926637 | AF28: =SUM(AA28:AC28)*AS28/AD28 -> 0.060477595 | AG28: - | AH28: - | AJ28: - | AK28: 350000 | AL28: 250000 | AM28: =SUM(AK28:AL28) -> 600000 | AO28: 250000 | AP28: 265625 | AQ28: 6.4 | AR28: =AP28*AQ28 -> 1700000 | AS28: 30.4718
A29: 45045 | B29: 45045 | C29: 64241 | D29: 7371 | E29: =SUM(C29:D29) -> 71612 | F29: =SUM(Q29,V29,AD29,AN29)-AV29 -> 2011292.6 | G29: =(F29-F28)/F28 -> 0.026757082 | H29: - | I29: =480084+14278 -> 494362 | J29: 967 | K29: - | L29: 1690 | M29: 2017 | N29: 2601 | O29: 1535.33 | P29: 347.77 | Q29: =SUM(I29:N29)+SUM(O29:P29)*$AS29 -> 559556.26 | R29: =Q29/F29 -> 0.27820728 | S29: 269468 | T29: 10810 | U29: 1623.24 | V29: =SUM(S29:T29)+U29*$AS29 -> 330204.64 | W29: =V29/F29 -> 0.16417534 | X29: =sum(T29,U29*AS29)/V29 -> 0.18393637 | Y29: 872955 | Z29: 189684 | AA29: =107.34+1807.41 -> 1914.75 | AC29: - | AD29: =SUM(Y29:Z29)+AA29*$AS29 -> 1121531.7 | AE29: =AD29/F29 -> 0.55761738 | AF29: =SUM(AA29:AC29)*AS29/AD29 -> 0.052510981 | AG29: - | AH29: - | AJ29: - | AK29: 350000 | AL29: 250000 | AM29: =SUM(AK29:AL29) -> 600000 | AO29: 250000 | AP29: 265625 | AQ29: 6.4 | AR29: =AP29*AQ29 -> 1700000 | AS29: 30.7574
A30: 45075 | B30: 45075 | C30: 51660 | D30: 2273.77 | E30: =SUM(C30:D30) -> 53933.77 | F30: =SUM(Q30,V30,AD30,AN30)-AV30 -> 2148034.4 | G30: =(F30-F29)/F29 -> 0.067987015 | H30: - | I30: =428500+18342 -> 446842 | J30: 1817 | K30: - | L30: 1569 | M30: 2017 | N30: 2601 | O30: =435.33+242.7 -> 678.03 | P30: 194.46 | Q30: =SUM(I30:N30)+SUM(O30:P30)*$AS30 -> 481559.72 | R30: =Q30/F30 -> 0.22418622 | S30: 299504 | T30: 11844 | U30: 1823.4 | V30: =SUM(S30:T30)+U30*$AS30 -> 367176.5 | W30: =V30/F30 -> 0.17093604 | X30: =sum(T30,U30*AS30)/V30 -> 0.18430509 | Y30: 937532 | Z30: 197254 | AA30: 2442.56 | AC30: 2930.53 | AD30: =SUM(Y30:Z30)+(AA30+AC30)*$AS30 -> 1299298.2 | AE30: =AD30/F30 -> 0.60487774 | AF30: =SUM(AA30:AC30)*AS30/AD30 -> 0.1266162 | AG30: - | AH30: - | AJ30: - | AK30: 350000 | AL30: 250000 | AM30: =SUM(AK30:AL30) -> 600000 | AO30: 250000 | AP30: 265625 | AQ30: 6.4 | AR30: =AP30*AQ30 -> 1700000 | AS30: 30.6178
A31: 45102 | B31: 45102 | C31: =51961+80800 -> 132761 | D31: 4268 | E31: =SUM(C31:D31) -> 137029 | F31: =SUM(Q31,V31,AD31,AN31)-AV31 -> 2361353.4 | G31: =(F31-F30)/F30 -> 0.099308938 | H31: - | I31: =12323+517721 -> 530044 | J31: =30086-28281 -> 1805 | K31: - | L31: 6580 | M31: 2017 | N31: 2601 | O31: =343.73+252.03 -> 595.76 | P31: 196.39 | Q31: =SUM(I31:N31)+SUM(O31:P31)*$AS31 -> 567606.42 | R31: =Q31/F31 -> 0.24037334 | S31: 322948 | T31: 13404 | U31: 2150.75 | V31: =SUM(S31:T31)+U31*$AS31 -> 403032.78 | W31: =V31/F31 -> 0.17067872 | X31: =sum(T31,U31*AS31)/V31 -> 0.19870537 | Y31: 968828 | Z31: 229472 | AA31: =122.34+3079.2 -> 3201.54 | AC31: 3004.67 | AD31: =SUM(Y31:Z31)+(AA31+AC31)*$AS31 -> 1390714.2 | AE31: =AD31/F31 -> 0.58894794 | AF31: =SUM(AA31:AC31)*AS31/AD31 -> 0.13835641 | AG31: - | AH31: - | AJ31: - | AK31: 350000 | AL31: 250000 | AM31: =SUM(AK31:AL31) -> 600000 | AO31: 250000 | AP31: 265625 | AQ31: 6.4 | AR31: =AP31*AQ31 -> 1700000 | AS31: 31.0035
A32: 45137 | B32: 45137 | C32: =51660+21965 -> 73625 | D32: 33824 | E32: =SUM(C32:D32) -> 107449 | F32: =SUM(Q32,V32,AD32,AN32)-AV32 -> 2550295.3 | G32: =(F32-F31)/F31 -> 0.08001421 | H32: =(F32-F20)/F20 -> 0.60111901 | I32: =528648+27166 -> 555814 | J32: 2228 | K32: - | L32: 580 | M32: 2017 | N32: =131619-16297 -> 115322 | O32: 245.38 | P32: 196.39 | Q32: =SUM(I32:N32)+SUM(O32:P32)*$AS32 -> 689801.57 | R32: =Q32/F32 -> 0.2704791 | S32: 372217 | T32: 14442 | U32: 2378.23 | V32: =SUM(S32:T32)+U32*$AS32 -> 461168.47 | W32: =V32/F32 -> 0.18082944 | X32: =sum(T32,U32*AS32)/V32 -> 0.19288281 | Y32: 886087 | Z32: 315915 | AA32: 3329.86 | AC32: 2968.4 | AD32: =SUM(Y32:Z32)+(AA32+AC32)*$AS32 -> 1399325.2 | AE32: =AD32/F32 -> 0.54869146 | AF32: =SUM(AA32:AC32)*AS32/AD32 -> 0.14101313 | AG32: - | AH32: - | AJ32: - | AK32: 350000 | AL32: 250000 | AM32: =SUM(AK32:AL32) -> 600000 | AO32: 250000 | AP32: 265625 | AQ32: 6.4 | AR32: =AP32*AQ32 -> 1700000 | AS32: 31.3298
A33: 45173 | B33: 45169 | C33: 51660 | D33: 44007 | E33: =SUM(C33:D33) -> 95667 | F33: =SUM(Q33,V33,AD33,AN33)-AV33 -> 2453442.7 | G33: =(F33-F32)/F32 -> -0.037977008 | H33: =(F33-F21)/F21 -> 0.53551698 | I33: =563876+22769 -> 586645 | J33: 1831 | K33: - | L33: 14473 | M33: 10160 | N33: 62931 | O33: =145.38 -> 145.38 | P33: 812.86 | Q33: =SUM(I33:N33)+SUM(O33:P33)*$AS33 -> 706586.77 | R33: =Q33/F33 -> 0.28799808 | S33: 241758 | T33: 14468 | U33: 2324.02 | V33: =SUM(S33:T33)+U33*$AS33 -> 330311.11 | W33: =V33/F33 -> 0.13463168 | X33: =sum(T33,U33*AS33)/V33 -> 0.26809001 | Y33: 923479 | Z33: 297814 | AA33: =271.32+3185.13 -> 3456.45 | AC33: 2668.52 | AD33: =SUM(Y33:Z33)+(AA33+AC33)*$AS33 -> 1416544.8 | AE33: =AD33/F33 -> 0.57737024 | AF33: =SUM(AA33:AC33)*AS33/AD33 -> 0.13783665 | AG33: - | AH33: - | AJ33: - | AK33: 350000 | AL33: 250000 | AM33: =SUM(AK33:AL33) -> 600000 | AO33: 250000 | AP33: 265625 | AQ33: 6.4 | AR33: =AP33*AQ33 -> 1700000 | AS33: 31.878 | AU33: 基金贖回1/3
A34: 45205 | B34: 45199 | C34: 51811 | D34: 9771.96 | E34: =SUM(C34:D34) -> 61582.96 | F34: =SUM(Q34,V34,AD34,AN34)-AV34 -> 2453026.2 | G34: =(F34-F33)/F33 -> -0.00016974634 | H34: =(F34-F22)/F22 -> 0.46999009 | I34: =632667-51697+25084 -> 606054 | J34: 537 | K34: - | L34: 473 | M34: 10160 | N34: 12964 | O34: 46.79 | P34: 261.15 | Q34: =SUM(I34:N34)+SUM(O34:P34)*$AS34 -> 640106.29 | R34: =Q34/F34 -> 0.26094555 | S34: 255122 | T34: 13638 | U34: 2210.66 | V34: =SUM(S34:T34)+U34*$AS34 -> 339962.04 | W34: =V34/F34 -> 0.13858883 | X34: =sum(T34,U34*AS34)/V34 -> 0.2495574 | Y34: 965765 | Z34: 300767 | AA34: =286.4+270.14+3640.7 -> 4197.24 | AC34: 2211.81 | AD34: =SUM(Y34:Z34)+(AA34+AC34)*$AS34 -> 1472957.9 | AE34: =AD34/F34 -> 0.60046561 | AF34: =SUM(AA34:AC34)*AS34/AD34 -> 0.14014378 | AG34: - | AH34: - | AJ34: - | AK34: 350000 | AL34: 250000 | AM34: =SUM(AK34:AL34) -> 600000 | AO34: 250000 | AP34: 265625 | AQ34: 6.4 | AR34: =AP34*AQ34 -> 1700000 | AS34: 32.2085
A35: 45232 | B35: 45229 | C35: 51697 | D35: 580.84 | E35: =SUM(C35:D35) -> 52277.84 | F35: =SUM(Q35,V35,AD35,AN35)-AV35 -> 2379631.9 | G35: =(F35-F34)/F34 -> -0.029919923 | H35: =(F35-F23)/F23 -> 0.50585029 | I35: =17047+524667+9400 -> 551114 | J35: 1057 | K35: - | L35: 1583 | M35: 10160 | N35: 12964 | O35: =168.2+146.79 -> 314.99 | P35: 9.33 | Q35: =SUM(I35:N35)+SUM(O35:P35)*$AS35 -> 587368.29 | R35: =Q35/F35 -> 0.24683158 | S35: 246455 | T35: 13595 | U35: 2162.31 | V35: =SUM(S35:T35)+U35*$AS35 -> 329991 | W35: =V35/F35 -> 0.13867313 | X35: =sum(T35,U35*AS35)/V35 -> 0.25314629 | Y35: 962371 | Z35: 313291 | AA35: =330.02+379.35+2879.24 -> 3588.61 | AC35: 2180.68 | AD35: =SUM(Y35:Z35)+(AA35+AC35)*$AS35 -> 1462272.6 | AE35: =AD35/F35 -> 0.61449529 | AF35: =SUM(AA35:AC35)*AS35/AD35 -> 0.12761682 | AG35: - | AH35: - | AJ35: - | AK35: 350000 | AL35: 250000 | AM35: =SUM(AK35:AL35) -> 600000 | AO35: 250000 | AP35: 265625 | AQ35: 6.4 | AR35: =AP35*AQ35 -> 1700000 | AS35: 32.3455
A36: 45259 | B36: 45259 | C36: 56175 | D36: 360.05 | E36: =SUM(C36:D36) -> 56535.05 | F36: =SUM(Q36,V36,AD36,AN36)-AV36 -> 2515930.2 | G36: =(F36-F35)/F35 -> 0.057277071 | H36: =(F36-F24)/F24 -> 0.44984309 | I36: =23399+423205+81050 -> 527654 | J36: =2001+9665 -> 11666 | K36: - | L36: 583 | M36: 160 | N36: 31139 | O36: =192.5+46.79 -> 239.29 | P36: 336.6 | Q36: =SUM(I36:N36)+SUM(O36:P36)*$AS36 -> 589206.62 | R36: =Q36/F36 -> 0.23419037 | S36: 272069 | T36: 15413 | U36: 2575.82 | V36: =SUM(S36:T36)+U36*$AS36 -> 368012.44 | W36: =V36/F36 -> 0.14627291 | X36: =sum(T36,U36*AS36)/V36 -> 0.26070705 | Y36: 984411 | Z36: 366443 | AA36: =341.04+411.6+3454.08 -> 4206.72 | AC36: 2441.73 | AD36: =SUM(Y36:Z36)+(AA36+AC36)*$AS36 -> 1558711.1 | AE36: =AD36/F36 -> 0.61953672 | AF36: =SUM(AA36:AC36)*AS36/AD36 -> 0.13335193 | AG36: - | AH36: - | AJ36: - | AK36: 350000 | AL36: 250000 | AM36: =SUM(AK36:AL36) -> 600000 | AO36: 250000 | AP36: 265625 | AQ36: 13.5 | AR36: =AP36*AQ36 -> 3585937.5 | AS36: 31.264
A37: 45290 | B37: 45290 | C37: =51697+6000+117399 -> 175096 | D37: 12881 | E37: =SUM(C37:D37) -> 187977 | F37: =SUM(Q37,V37,AD37,AN37)-AV37 -> 2739417.8 | G37: =(F37-F36)/F36 -> 0.088828997 | H37: =(F37-F25)/F25 -> 0.54787289 | I37: =38995+514596+100000 -> 653591 | J37: =69+9945 -> 10014 | K37: - | L37: 2494 | M37: 173 | N37: 39918 | O37: 249.5 | P37: 218.04 | Q37: =SUM(I37:N37)+SUM(O37:P37)*$AS37 -> 720535.79 | R37: =Q37/F37 -> 0.26302516 | S37: 288346 | T37: =10629+6035 -> 16664 | U37: 3106.55 | V37: =SUM(S37:T37)+U37*$AS37 -> 400329.98 | W37: =V37/F37 -> 0.14613689 | X37: =sum(T37,U37*AS37)/V37 -> 0.27972919 | Y37: 1002842 | Z37: 394006 | AA37: =351.48+560.92+3544.52 -> 4456.92 | AC37: 2768.58 | AD37: =SUM(Y37:Z37)+(AA37+AC37)*$AS37 -> 1618552 | AE37: =AD37/F37 -> 0.59083796 | AF37: =SUM(AA37:AC37)*AS37/AD37 -> 0.13697675 | AG37: - | AH37: - | AJ37: - | AK37: 350000 | AL37: 250000 | AM37: =SUM(AK37:AL37) -> 600000 | AO37: 250000 | AP37: 265625 | AQ37: 13.5 | AR37: =AP37*AQ37 -> 3585937.5 | AS37: 30.68355
A38: 45323 | B38: 45322 | C38: 51197 | D38: 29050.42 | E38: =SUM(C38:D38) -> 80247.42 | F38: =SUM(Q38,V38,AD38,AN38)-AV38 -> 2698158.4 | G38: =(F38-F37)/F37 -> -0.015061375 | H38: =(F38-F26)/F26 -> 0.44869824 | I38: =465070+23362+10000 -> 498432 | J38: =4337+9582 -> 13919 | K38: 102985 | L38: 91210 | M38: 173 | N38: =67513-61048 -> 6465 | O38: =149.5+212 -> 361.5 | P38: 163.78 | Q38: =SUM(I38:N38)+SUM(O38:P38)*$AS38 -> 729633.3 | R38: =Q38/F38 -> 0.27041901 | S38: 214359 | T38: 11295 | U38: 3020.35 | V38: =SUM(S38:T38)+U38*$AS38 -> 320237.17 | W38: =V38/F38 -> 0.11868731 | X38: =sum(T38,U38*AS38)/V38 -> 0.33062423 | Y38: 1012863 | Z38: =292243+50150 -> 342393 | AA38: =312.2+560.4+2622.06 -> 3494.66 | AC38: 2669.48 | AD38: =SUM(Y38:Z38)+(AA38+AC38)*$AS38 -> 1548287.9 | AE38: =AD38/F38 -> 0.57383136 | AF38: =SUM(AA38:AC38)*AS38/AD38 -> 0.12467442 | AG38: - | AH38: - | AJ38: - | AK38: 350000 | AL38: 250000 | AM38: =SUM(AK38:AL38) -> 600000 | AN38: 100000 | AO38: 250000 | AP38: 265625 | AQ38: 13.5 | AR38: =AP38*AQ38 -> 3585937.5 | AS38: 31.3153
A39: 45350 | B39: 45350 | C39: =57667+3500 -> 61167 | D39: 4355 | E39: =SUM(C39:D39) -> 65522 | F39: =SUM(Q39,V39,AD39,AN39)-AV39 -> 2706574.4 | G39: =(F39-F38)/F38 -> 0.0031191694 | H39: =(F39-F27)/F27 -> 0.41079606 | I39: =299723+23362+57070 -> 380155 | J39: =9761+9582 -> 19343 | K39: 103089 | L39: 8513 | M39: 173 | N39: 6465 | O39: 49.5 | P39: 146.8 | Q39: =SUM(I39:N39)+SUM(O39:P39)*$AS39 -> 523952.37 | R39: =Q39/F39 -> 0.19358506 | S39: 231238 | T39: 12259 | U39: 3414.27 | V39: =SUM(S39:T39)+U39*$AS39 -> 351584.25 | W39: =V39/F39 -> 0.12990009 | X39: =sum(T39,U39*AS39)/V39 -> 0.34229705 | Y39: 1033765 | Z39: =300450+51250 -> 351700 | AA39: =353.21+555.52+2796.22 -> 3704.95 | AC39: 2472.82 | AD39: =SUM(Y39:Z39)+(AA39+AC39)*$AS39 -> 1581037.8 | AE39: =AD39/F39 -> 0.58414717 | AF39: =SUM(AA39:AC39)*AS39/AD39 -> 0.12369898 | AG39: - | AH39: - | AJ39: - | AK39: 350000 | AL39: 250000 | AM39: =SUM(AK39:AL39) -> 600000 | AN39: 250000 | AO39: 250000 | AP39: 265625 | AQ39: 13.5 | AR39: =AP39*AQ39 -> 3585937.5 | AS39: 31.6575
A40: 45382 | B40: 45382 | C40: 56697 | D40: 37439.45 | E40: =SUM(C40:D40) -> 94136.45 | F40: =SUM(Q40,V40,AD40,AN40)-AV40 -> 2706383.5 | G40: =(F40-F39)/F39 -> -7.0525291e-05 | H40: =(F40-F28)/F28 -> 0.38159827 | I40: =254522+120092+13821 -> 388435 | J40: =75+9669 -> 9744 | K40: 94386 | L40: 610 | M40: 173 | N40: =88284 -> 88284 | O40: =110.55+200.2 -> 310.75 | P40: 282.11 | Q40: =SUM(I40:N40)+SUM(O40:P40)*$AS40 -> 600568.48 | R40: =Q40/F40 -> 0.22190812 | S40: 249930 | T40: 13374 | U40: 3612.98 | V40: =SUM(S40:T40)+U40*$AS40 -> 378705.83 | W40: =V40/F40 -> 0.13993059 | X40: =sum(T40,U40*AS40)/V40 -> 0.34004185 | Y40: 1040965 | Z40: 251123 | AA40: =603.72+2636.85 -> 3240.57 | AC40: 2552.04 | AD40: =SUM(Y40:Z40)+(AA40+AC40)*$AS40 -> 1477109.2 | AE40: =AD40/F40 -> 0.54578709 | AF40: =SUM(AA40:AC40)*AS40/AD40 -> 0.12525897 | AG40: - | AH40: - | AJ40: - | AK40: 350000 | AL40: 250000 | AM40: =SUM(AK40:AL40) -> 600000 | AN40: 250000 | AO40: 250000 | AP40: 265625 | AQ40: 13.5 | AR40: =AP40*AQ40 -> 3585937.5 | AS40: 31.9409
A41: 45412 | B41: 45412 | C41: 58841 | D41: 5421.61 | E41: =SUM(C41:D41) -> 64262.61 | F41: =SUM(Q41,V41,AD41,AN41)-AV41 -> 2742000 | G41: =(F41-F40)/F40 -> 0.013160188 | H41: =(F41-F29)/F29 -> 0.36330237 | I41: =13821+348977 -> 362798 | J41: =2505+9425 -> 11930 | K41: 97624 | L41: 610 | M41: 173 | N41: =88284 -> 88284 | O41: =175.6+12.91 -> 188.51 | P41: 294.56 | Q41: =SUM(I41:N41)+SUM(O41:P41)*$AS41 -> 577177.23 | R41: =Q41/F41 -> 0.21049498 | S41: 257529 | T41: 11752 | U41: 3437.82 | V41: =SUM(S41:T41)+U41*$AS41 -> 381426.13 | W41: =V41/F41 -> 0.13910508 | X41: =sum(T41,U41*AS41)/V41 -> 0.32482601 | Y41: 1040819 | Z41: 308025 | AA41: =651.12+2749.2 -> 3400.32 | AC41: 2257.16 | AD41: =SUM(Y41:Z41)+(AA41+AC41)*$AS41 -> 1533396.7 | AE41: =AD41/F41 -> 0.55922562 | AF41: =SUM(AA41:AC41)*AS41/AD41 -> 0.12035546 | AG41: - | AH41: - | AJ41: - | AK41: 350000 | AL41: 250000 | AM41: =SUM(AK41:AL41) -> 600000 | AN41: 250000 | AO41: 250000 | AP41: 265625 | AQ41: 13.5 | AR41: =AP41*AQ41 -> 3585937.5 | AS41: 32.621 | AU41: 交屋 4/26貸款撥款 | AY41: =SUM(Q41,V41,AD41,11000000)/AV41 -> #DIV/0!
A42: 45448 | B42: 45443 | C42: =51697+1250 -> 52947 | D42: 357 | E42: =SUM(C42:D42) -> 53304 | F42: =SUM(Q42,V42,AD42,AN42)-AV42 -> 2838040.9 | G42: =(F42-F41)/F41 -> 0.035025854 | H42: =(F42-F30)/F30 -> 0.32122692 | I42: =13821+630138-51697 -> 592262 | J42: =417+9554 -> 9971 | K42: 112613 | L42: 610 | M42: 173 | N42: 57160 | O42: =195.2+212.91 -> 408.11 | P42: 294.56 | Q42: =SUM(I42:N42)+SUM(O42:P42)*$AS42 -> 795515.81 | R42: =Q42/F42 -> 0.28030456 | S42: 275832 | T42: 12574 | U42: 3374.18 | V42: =SUM(S42:T42)+U42*$AS42 -> 397538.79 | W42: =V42/F42 -> 0.14007507 | X42: =sum(T42,U42*AS42)/V42 -> 0.30615073 | Y42: 1101566 | Z42: 272928 | AA42: =692.68+2644.35 -> 3337.03 | AC42: 2447.14 | AD42: =SUM(Y42:Z42)+(AA42+AC42)*$AS42 -> 1561574.3 | AE42: =AD42/F42 -> 0.55022967 | AF42: =SUM(AA42:AC42)*AS42/AD42 -> 0.11980237 | AG42: - | AH42: - | AJ42: - | AK42: 350000 | AL42: 250000 | AM42: =SUM(AK42:AL42) -> 600000 | AN42: =11000000-2400000+250000 -> 8850000 | AO42: 250000 | AP42: 265625 | AQ42: 13.5 | AR42: =AP42*AQ42 -> 3585937.5 | AS42: 32.3435 | AU42: 裝潢 傢具支出 | AV42: =8800000-33412 -> 8766588 | AY42: =SUM(Q42,V42,AD42,11000000)/AV42 -> 1.5689832
A43: 45473 | B43: 45444 | C43: =51697+86272 -> 137969 | D43: =752+8867 -> 9619 | E43: =SUM(C43:D43) -> 147588 | F43: =SUM(Q43,V43,AD43,AN43)-AV43 -> 2762874.8 | G43: =(F43-F42)/F42 -> -0.026485214 | H43: =(F43-F31)/F31 -> 0.17003865 | I43: =13821+403716 -> 417537 | J43: =885+9223 -> 10108 | K43: 100429 | L43: 652 | M43: 173 | N43: =57160-29223 -> 27937 | O43: =188.3+114 -> 302.3 | P43: 296.48 | Q43: =SUM(I43:N43)+SUM(O43:P43)*$AS43 -> 576308.03 | R43: =Q43/F43 -> 0.20858999 | S43: 302295 | T43: 13274 | U43: 3646.45 | V43: =SUM(S43:T43)+U43*$AS43 -> 434149.73 | W43: =V43/F43 -> 0.15713696 | X43: =sum(T43,U43*AS43)/V43 -> 0.30370796 | Y43: 1178297 | Z43: 290945 | AA43: =741.96+2961.3 -> 3703.26 | AC43: 2396.65 | AD43: =SUM(Y43:Z43)+(AA43+AC43)*$AS43 -> 1667608 | AE43: =AD43/F43 -> 0.60357713 | AF43: =SUM(AA43:AC43)*AS43/AD43 -> 0.11895243 | AG43: - | AH43: - | AJ43: - | AK43: 350000 | AL43: 250000 | AM43: =SUM(AK43:AL43) -> 600000 | AN43: =11000000-2400000+250000 -> 8850000 | AO43: 250000 | AP43: 265625 | AQ43: 13.5 | AR43: =AP43*AQ43 -> 3585937.5 | AS43: 32.5195 | AU43: 裝潢 傢具 電器支出 | AV43: =8765191 -> 8765191 | AW43: =AV43-AV42 -> -1397
A44: 45505 | B44: 45474 | C44: =51697+63997 -> 115694 | D44: =13533.45+2289 -> 15822.45 | E44: =SUM(C44:D44) -> 131516.45 | F44: =SUM(Q44,V44,AD44,AN44)-AV44 -> 2878723.1 | G44: =(F44-F43)/F43 -> 0.041930366 | H44: =(F44-F32)/F32 -> 0.12878033 | I44: =13821+382108 -> 395929 | J44: =4140+9950 -> 14090 | K44: 113409 | L44: 1652 | M44: 173 | N44: 80573 | O44: =200.9+15.43 -> 216.33 | P44: 296.48 | Q44: =SUM(I44:N44)+SUM(O44:P44)*$AS44 -> 622621.55 | R44: =Q44/F44 -> 0.21628393 | S44: 290198 | T44: 9410 | U44: 3767.49 | V44: =SUM(S44:T44)+U44*$AS44 -> 423000.83 | W44: =V44/F44 -> 0.14694044 | X44: =sum(T44,U44*AS44)/V44 -> 0.31395407 | Y44: 1159731 | Z44: 349718 | AA44: =686.16+3481.05 -> 4167.21 | AC44: 2592.4 | AD44: =SUM(Y44:Z44)+(AA44+AC44)*$AS44 -> 1730839.7 | AE44: =AD44/F44 -> 0.60125259 | AF44: =SUM(AA44:AC44)*AS44/AD44 -> 0.12790944 | AG44: - | AH44: - | AJ44: - | AK44: 350000 | AL44: 250000 | AM44: =SUM(AK44:AL44) -> 600000 | AN44: =11000000-2400000+250000 -> 8850000 | AO44: 250000 | AP44: 265625 | AQ44: 13.5 | AR44: =AP44*AQ44 -> 3585937.5 | AS44: 32.752 | AV44: 8747739 | AW44: =AV44-AV43 -> -17452
A45: 45535 | B45: 45505 | C45: =56266 -> 56266 | D45: 14195.45 | E45: =SUM(C45:D45) -> 70461.45 | F45: =SUM(Q45,V45,AD45,AN45)-AV45 -> 2861217.5 | G45: =(F45-F44)/F44 -> -0.00608104 | H45: =(F45-F33)/F33 -> 0.16620516 | I45: =21478+308753 -> 330231 | J45: =2108+9996 -> 12104 | K45: 103187 | L45: 652 | M45: 173 | N45: 53706 | O45: 742.76 | P45: 97.88 | Q45: =SUM(I45:N45)+SUM(O45:P45)*$AS45 -> 526962.73 | R45: =Q45/F45 -> 0.1841743 | S45: 309001 | T45: 9905 | U45: 4090.51 | V45: =SUM(S45:T45)+U45*$AS45 -> 449847.32 | W45: =V45/F45 -> 0.15722234 | X45: =sum(T45,U45*AS45)/V45 -> 0.31309805 | Y45: 1152795 | Z45: 378772 | AA45: =647.12+3300.48 -> 3947.6 | AB45: 654.68 | AC45: 2679.45 | AD45: =SUM(Y45:Z45)+(AA45+AC45+AB45)*$AS45 -> 1764662.5 | AE45: =AD45/F45 -> 0.61675229 | AF45: =SUM(AA45:AC45)*AS45/AD45 -> 0.13209068 | AG45: - | AH45: - | AJ45: - | AK45: 350000 | AL45: 250000 | AM45: =SUM(AK45:AL45) -> 600000 | AN45: =11000000-2400000+250000 -> 8850000 | AO45: 250000 | AP45: 265625 | AQ45: 13.5 | AR45: =AP45*AQ45 -> 3585937.5 | AS45: 32.011 | AU45: 台幣升值美元資產減損，故較上月少~10000資產 | AV45: 8730255 | AW45: =AV45-AV44 -> -17484
A46: 45564 | B46: 45536 | C46: 62155 | D46: 14952.62 | E46: =SUM(C46:D46) -> 77107.62 | F46: =SUM(Q46,V46,AD46,AN46)-AV46 -> 2971873.6 | G46: =(F46-F45)/F45 -> 0.03867447 | H46: =(F46-F34)/F34 -> 0.21151317 | I46: =319553+20062 -> 339615 | J46: =1007+10184 -> 11191 | K46: 101163 | L46: 652 | M46: 173 | N46: =40127 -> 40127 | O46: 442.66 | P46: 98.44 | Q46: =SUM(I46:N46)+SUM(O46:P46)*$AS46 -> 510014.35 | R46: =Q46/F46 -> 0.17161374 | S46: 307197 | T46: 10793 | U46: 4481.34 | V46: =SUM(S46:T46)+U46*$AS46 -> 459555.53 | W46: =V46/F46 -> 0.15463495 | X46: =sum(T46,U46*AS46)/V46 -> 0.33153454 | Y46: 1200129 | Z46: 401340 | AA46: =650.92+4067.52 -> 4718.44 | AB46: 916.35 | AC46: 2708.79 | AD46: =SUM(Y46:Z46)+(AA46+AC46+AB46)*$AS46 -> 1865042.7 | AE46: =AD46/F46 -> 0.62756461 | AF46: =SUM(AA46:AC46)*AS46/AD46 -> 0.14132314 | AG46: - | AH46: - | AJ46: - | AK46: 350000 | AL46: 250000 | AM46: =SUM(AK46:AL46) -> 600000 | AN46: =11000000-2400000+250000 -> 8850000 | AO46: 250000 | AP46: 265625 | AQ46: 13.5 | AR46: =AP46*AQ46 -> 3585937.5 | AS46: 31.59 | AV46: 8712739 | AW46: =AV46-AV45 -> -17516
A47: 45596 | B47: 45566 | C47: 57143 | D47: =42439+6581.82 -> 49020.82 | E47: =SUM(C47:D47) -> 106163.82 | F47: =SUM(Q47,V47,AD47,AN47)-AV47 -> 2977687.6 | G47: =(F47-F46)/F46 -> 0.0019563669 | H47: =(F47-F35)/F35 -> 0.25132282 | I47: =13038+377957 -> 390995 | J47: =1904+9628 -> 11532 | K47: 100157 | L47: 106802 | M47: 173 | N47: 40127 | O47: 629.71 | P47: 124.71 | Q47: =SUM(I47:N47)+SUM(O47:P47)*$AS47 -> 673898.02 | R47: =Q47/F47 -> 0.22631589 | S47: 209223 | T47: 11464 | U47: 4855.87 | V47: =SUM(S47:T47)+U47*$AS47 -> 375885.46 | W47: =V47/F47 -> 0.12623401 | X47: =sum(T47,U47*AS47)/V47 -> 0.44338629 | Y47: 1183634 | Z47: 330633 | AA47: =697.84+4378.35 -> 5076.19 | AB47: 595.48 | AC47: 2426.58 | AD47: =SUM(Y47:Z47)+(AA47+AC47+AB47)*$AS47 -> 1773095.2 | AE47: =AD47/F47 -> 0.59546043 | AF47: =SUM(AA47:AC47)*AS47/AD47 -> 0.14597534 | AG47: - | AH47: - | AJ47: - | AK47: 350000 | AL47: 250000 | AM47: =SUM(AK47:AL47) -> 600000 | AN47: =11000000-2400000+250000 -> 8850000 | AO47: 250000 | AP47: 265625 | AQ47: 13.5 | AR47: =AP47*AQ47 -> 3585937.5 | AS47: 31.961 | AV47: 8695191 | AW47: =AV47-AV46 -> -17548
A48: 45628 | B48: 45597 | C48: =58743+1600 -> 60343 | D48: 166 | E48: =SUM(C48:D48) -> 60509 | F48: =SUM(Q48,V48,AD48,AN48)-AV48 -> 3084722.8 | G48: =(F48-F47)/F47 -> 0.035945722 | H48: =(F48-F36)/F36 -> 0.22607645 | I48: =12123+391848 -> 403971 | J48: =1282+9954 -> 11236 | K48: 114528 | L48: 778 | M48: 173 | N48: 43233 | O48: 329.61 | P48: 124.71 | Q48: =SUM(I48:N48)+SUM(O48:P48)*$AS48 -> 588727.88 | R48: =Q48/F48 -> 0.19085277 | S48: 219193 | T48: 12531 | U48: 6025.74 | V48: =SUM(S48:T48)+U48*$AS48 -> 428137.21 | W48: =V48/F48 -> 0.13879277 | X48: =sum(T48,U48*AS48)/V48 -> 0.48803096 | Y48: 1172341 | Z48: 400589 | AA48: =675.8+5867.72 -> 6543.52 | AB48: 841.04 | AC48: 2510.57 | AD48: =SUM(Y48:Z48)+(AA48+AC48+AB48)*$AS48 -> 1895468.7 | AE48: =AD48/F48 -> 0.6144697 | AF48: =SUM(AA48:AC48)*AS48/AD48 -> 0.17016303 | AG48: - | AH48: - | AJ48: - | AK48: 350000 | AL48: 250000 | AM48: =SUM(AK48:AL48) -> 600000 | AN48: =11000000-2400000+250000 -> 8850000 | AO48: 250000 | AP48: 265625 | AQ48: 13.5 | AR48: =AP48*AQ48 -> 3585937.5 | AS48: 32.5957 | AV48: 8677611 | AW48: =AV48-AV47 -> -17580
A49: 45657 | B49: 45627 | C49: =56280+189298+7000 -> 252578 | D49: 8490 | E49: =SUM(C49:D49) -> 261068 | F49: =SUM(Q49,V49,AD49,AN49)-AV49 -> 3357375.4 | G49: =(F49-F48)/F48 -> 0.088388041 | H49: =(F49-F37)/F37 -> 0.22557992 | I49: =12123+569611 -> 581734 | J49: =554+9609 -> 10163 | K49: 117620 | L49: 904 | M49: 173 | N49: 47424 | O49: 33.76 | P49: 126.19 | Q49: =SUM(I49:N49)+SUM(O49:P49)*$AS49 -> 763263.69 | R49: =Q49/F49 -> 0.22733939 | S49: 230992 | T49: 13298 | U49: 5901.78 | V49: =SUM(S49:T49)+U49*$AS49 -> 437843.6 | W49: =V49/F49 -> 0.13041246 | X49: =sum(T49,U49*AS49)/V49 -> 0.47243262 | Y49: 1192848 | Z49: 410955 | AA49: =764.96+7095.97 -> 7860.93 | AB49: 989 | AC49: 2202.22 | AD49: =SUM(Y49:Z49)+(AA49+AC49+AB49)*$AS49 -> 1966267.1 | AE49: =AD49/F49 -> 0.58565602 | AF49: =SUM(AA49:AC49)*AS49/AD49 -> 0.18434123 | AG49: - | AH49: - | AJ49: - | AK49: 350000 | AL49: 250000 | AM49: =SUM(AK49:AL49) -> 600000 | AN49: =11000000-2400000+250000 -> 8850000 | AO49: 250000 | AP49: 265625 | AQ49: 13.5 | AR49: =AP49*AQ49 -> 3585937.5 | AS49: 32.7958 | AV49: 8659999 | AW49: =AV49-AV48 -> -17612
A50: 45694 | B50: 45658 | C50: =74375+2550 -> 76925 | D50: 4604.93 | E50: =SUM(C50:D50) -> 81529.93 | F50: =SUM(Q50,V50,AD50,AN50)-AV50 -> 3450232.3 | G50: =(F50-F49)/F49 -> 0.027657586 | H50: =(F50-F38)/F38 -> 0.27873602 | I50: =12123+554521 -> 566644 | J50: =1016+9858 -> 10874 | K50: 119805 | L50: 785 | M50: 566 | N50: 25107 | O50: 535.04 | P50: 1326.19 | Q50: =SUM(I50:N50)+SUM(O50:P50)*$AS50 -> 784954.6 | R50: =Q50/F50 -> 0.22750776 | S50: 216253 | T50: 13945 | U50: 6569.99 | V50: =SUM(S50:T50)+U50*$AS50 -> 446135.83 | W50: =V50/F50 -> 0.12930603 | X50: =sum(T50,U50*AS50)/V50 -> 0.51527543 | Y50: 1236433 | Z50: 419792 | AA50: =765.32+6428.89 -> 7194.21 | AB50: 1427.38 | AC50: 2187.69 | AD50: =SUM(Y50:Z50)+(AA50+AC50+AB50)*$AS50 -> 2011496.8 | AE50: =AD50/F50 -> 0.58300331 | AF50: =SUM(AA50:AC50)*AS50/AD50 -> 0.17662063 | AG50: - | AH50: - | AJ50: - | AK50: 350000 | AL50: 250000 | AM50: =SUM(AK50:AL50) -> 600000 | AN50: =11000000-2400000+250000 -> 8850000 | AO50: 250000 | AP50: 265625 | AQ50: 13.5 | AR50: =AP50*AQ50 -> 3585937.5 | AS50: 32.8673 | AV50: 8642355 | AW50: =AV50-AV49 -> -17644
A51: 45718 | B51: 45689 | C51: 60297 | D51: 4137 | E51: =SUM(C51:D51) -> 64434 | F51: =SUM(Q51,V51,AD51,AN51)-AV51 -> 3320867 | G51: =(F51-F50)/F50 -> -0.037494669 | H51: =(F51-F39)/F39 -> 0.22696313 | I51: =12123+470164 -> 482287 | J51: =1403+9977 -> 11380 | K51: 109113 | L51: 785 | M51: 566 | N51: 28847 | O51: 435.04 | P51: 975.31 | Q51: =SUM(I51:N51)+SUM(O51:P51)*$AS51 -> 679406.72 | R51: =Q51/F51 -> 0.20458715 | S51: 223646 | T51: 13908 | U51: 6233.56 | V51: =SUM(S51:T51)+U51*$AS51 -> 442762.8 | W51: =V51/F51 -> 0.13332747 | X51: =sum(T51,U51*AS51)/V51 -> 0.49488529 | Y51: 1237891 | Z51: 429392 | AA51: =674+5075.1 -> 5749.1 | AB51: 1406.98 | AC51: 2142.02 | AD51: =SUM(Y51:Z51)+(AA51+AC51+AB51)*$AS51 -> 1973376.5 | AE51: =AD51/F51 -> 0.59423532 | AF51: =SUM(AA51:AC51)*AS51/AD51 -> 0.15511154 | AG51: - | AH51: - | AJ51: - | AK51: 350000 | AL51: 250000 | AM51: =SUM(AK51:AL51) -> 600000 | AN51: =11000000-2400000+250000 -> 8850000 | AO51: 250000 | AP51: 265625 | AQ51: 13.5 | AR51: =AP51*AQ51 -> 3585937.5 | AS51: 32.92 | AV51: 8624679 | AW51: =AV51-AV50 -> -17676
A52: 45751 | B52: 45717 | C52: 76471 | D52: 8694.62 | E52: =SUM(C52:D52) -> 85165.62 | F52: =SUM(Q52,V52,AD52,AN52)-AV52 -> 3159404.7 | G52: =(F52-F51)/F51 -> -0.048620523 | H52: =(F52-F40)/F40 -> 0.16738987 | I52: =12123+405654 -> 417777 | J52: =473+10387 -> 10860 | K52: 138496 | L52: 785 | M52: 566 | N52: 28847 | O52: 139.27 | P52: 975.87 | Q52: =SUM(I52:N52)+SUM(O52:P52)*$AS52 -> 634263.88 | R52: =Q52/F52 -> 0.20075424 | S52: 203452 | T52: 13012 | U52: 5513.51 | V52: =SUM(S52:T52)+U52*$AS52 -> 399068.69 | W52: =V52/F52 -> 0.12631136 | X52: =sum(T52,U52*AS52)/V52 -> 0.49018301 | Y52: 1163806 | Z52: 415112 | AA52: =628.16+5089.68 -> 5717.84 | AB52: 1471.63 | AC52: 1993.19 | AD52: =SUM(Y52:Z52)+(AA52+AC52+AB52)*$AS52 -> 1883043.1 | AE52: =AD52/F52 -> 0.596012 | AF52: =SUM(AA52:AC52)*AS52/AD52 -> 0.16150725 | AG52: - | AH52: - | AJ52: - | AK52: 350000 | AL52: 250000 | AM52: =SUM(AK52:AL52) -> 600000 | AN52: =11000000-2400000+250000 -> 8850000 | AO52: 250000 | AP52: 265625 | AQ52: 13.5 | AR52: =AP52*AQ52 -> 3585937.5 | AS52: 33.1195 | AV52: 8606971 | AW52: =AV52-AV51 -> -17708
A53: 45782 | B53: 45748 | C53: 91784 | D53: 5312.05 | E53: =SUM(C53:D53) -> 97096.05 | F53: =SUM(Q53,V53,AD53,AN53)-AV53 -> 3086647.7 | G53: =(F53-F52)/F52 -> -0.023028688 | H53: =(F53-F41)/F41 -> 0.1256921 | I53: =12123+456645-66645 -> 402123 | J53: =460+9591 -> 10051 | K53: 108769 | L53: 785 | M53: 566 | N53: 28847 | O53: 1041.54 | P53: =723.85+256 -> 979.85 | Q53: =SUM(I53:N53)+SUM(O53:P53)*$AS53 -> 610004.89 | R53: =Q53/F53 -> 0.19762699 | S53: 202091 | T53: 13150 | U53: 6252.43 | V53: =SUM(S53:T53)+U53*$AS53 -> 397314.89 | W53: =V53/F53 -> 0.12872052 | X53: =sum(T53,U53*AS53)/V53 -> 0.4913581 | Y53: 1118640 | Z53: 428112 | AA53: =656.12+5169.78 -> 5825.9 | AB53: 1514.14 | AC53: 1993.83 | AD53: =SUM(Y53:Z53)+(AA53+AC53+AB53)*$AS53 -> 1818559 | AE53: =AD53/F53 -> 0.58916958 | AF53: =SUM(AA53:AC53)*AS53/AD53 -> 0.14946283 | AG53: - | AH53: - | AJ53: - | AK53: 350000 | AL53: 250000 | AM53: =SUM(AK53:AL53) -> 600000 | AN53: =11000000-2400000+250000 -> 8850000 | AO53: 250000 | AP53: 265625 | AQ53: 13.5 | AR53: =AP53*AQ53 -> 3585937.5 | AS53: 29.1205 | AV53: 8589231 | AW53: =AV53-AV52 -> -17740
A54: 45807 | B54: 45778 | C54: =66645+10020 -> 76665 | D54: =1546+2700 -> 4246 | E54: =SUM(C54:D54) -> 80911 | F54: =SUM(Q54,V54,AD54,AN54)-AV54 -> 3287897.8 | G54: =(F54-F53)/F53 -> 0.065200201 | H54: =(F54-F42)/F42 -> 0.15850966 | I54: =19899+359407 -> 379306 | J54: =922+9536 -> 10458 | K54: 108593 | L54: 785 | M54: 566 | N54: 34888 | O54: 1425.94 | P54: 347.84 | Q54: =SUM(I54:N54)+SUM(O54:P54)*$AS54 -> 586169.36 | R54: =Q54/F54 -> 0.1782809 | S54: 225935 | T54: 14396 | U54: 6980.47 | V54: =SUM(S54:T54)+U54*$AS54 -> 443290.96 | W54: =V54/F54 -> 0.13482504 | X54: =sum(T54,U54*AS54)/V54 -> 0.49032346 | Y54: 1173681 | Z54: 443360 | AA54: =1374.88+6451.74 -> 7826.62 | AB54: 2586.87 | AC54: 2066.32 | AD54: =SUM(Y54:Z54)+(AA54+AC54+AB54)*$AS54 -> 1979896.5 | AE54: =AD54/F54 -> 0.60217701 | AF54: =SUM(AA54:AC54)*AS54/AD54 -> 0.18326992 | AG54: - | AH54: - | AJ54: - | AK54: 350000 | AL54: 250000 | AM54: =SUM(AK54:AL54) -> 600000 | AN54: =11000000-2400000+250000 -> 8850000 | AO54: 250000 | AP54: 265625 | AQ54: 13.5 | AR54: =AP54*AQ54 -> 3585937.5 | AS54: 29.0754 | AV54: 8571459 | AW54: =AV54-AV53 -> -17772
A55: 45837 | B55: 45809 | C55: =141147+56958 -> 198105 | D55: 15846 | E55: =SUM(C55:D55) -> 213951 | F55: =SUM(Q55,V55,AD55,AN55)-AV55 -> 3522773.2 | G55: =(F55-F54)/F54 -> 0.071436337 | H55: =(F55-F43)/F43 -> 0.27503902 | I55: =441596+30574 -> 472170 | J55: =207+9223 -> 9430 | K55: 103073 | L55: 785 | M55: 566 | N55: 12119 | O55: 1288.71 | P55: 16.72 | Q55: =SUM(I55:N55)+SUM(O55:P55)*$AS55 -> 637118.3 | R55: =Q55/F55 -> 0.18085703 | S55: 251246 | T55: 15280 | U55: 7423.16 | V55: =SUM(S55:T55)+U55*$AS55 -> 488154.01 | W55: =V55/F55 -> 0.13857095 | X55: =sum(T55,U55*AS55)/V55 -> 0.48531407 | Y55: 1221406 | Z55: 456424 | AA55: =1735.4+5864.04 -> 7599.44 | AB55: 4537.49 | AC55: 2041.82 | AD55: =SUM(Y55:Z55)+(AA55+AC55+AB55)*$AS55 -> 2101154.9 | AE55: =AD55/F55 -> 0.59644909 | AF55: =SUM(AA55:AC55)*AS55/AD55 -> 0.20147247 | AG55: - | AH55: - | AJ55: - | AK55: 350000 | AL55: 250000 | AM55: =SUM(AK55:AL55) -> 600000 | AN55: =11000000-2400000+250000 -> 8850000 | AO55: 250000 | AP55: 265625 | AQ55: 13.5 | AR55: =AP55*AQ55 -> 3585937.5 | AS55: 29.856289 | AV55: 8553654 | AW55: =AV55-AV54 -> -17805
A56: 45870 | B56: 45839 | C56: =56958+124071 -> 181029 | D56: 46463.66 | E56: =SUM(C56:D56) -> 227492.66 | F56: =SUM(Q56,V56,AD56,AN56,AI56)-AV56 -> 3767669.3 | G56: =(F56-F55)/F55 -> 0.069517999 | H56: =(F56-F44)/F44 -> 0.30879877 | I56: =34535+503070 -> 537605 | J56: =789+9251 -> 10040 | K56: 126472 | L56: 89101 | M56: 5288 | N56: 54938 | O56: 721.5 | P56: 274.95 | Q56: =SUM(I56:N56)+SUM(O56:P56)*$AS56 -> 852991.23 | R56: =Q56/F56 -> 0.22639759 | S56: 194294 | T56: 16839 | U56: 7957.11 | V56: =SUM(S56:T56)+U56*$AS56 -> 447081.2 | W56: =V56/F56 -> 0.11866254 | X56: =sum(T56,U56*AS56)/V56 -> 0.56541675 | Y56: 1228948 | Z56: 470734 | AA56: =2110.9+6165.4 -> 8276.3 | AB56: 4849.1 | AC56: 1992.43 | AD56: =SUM(Y56:Z56)+(AA56+AC56+AB56)*$AS56 -> 2147963.4 | AE56: =AD56/F56 -> 0.57010403 | AF56: =SUM(AA56:AC56)*AS56/AD56 -> 0.20870069 | AG56: 0.01 | AH56: =174.15+9.65 -> 183.8 | AI56: =(AH56+AG56)*$AS56 -> 5450.4259 | AJ56: =AI56/F56 -> 0.0014466307 | AK56: 350000 | AL56: 250000 | AM56: =SUM(AK56:AL56) -> 600000 | AN56: =11000000-2400000+250000 -> 8850000 | AO56: 250000 | AP56: 265625 | AQ56: 13.5 | AR56: =AP56*AQ56 -> 3585937.5 | AS56: 29.652499 | AV56: 8535817 | AW56: =AV56-AV55 -> -17837
A57: 45901 | B57: 45870 | C57: 56958 | D57: 36960 | E57: =SUM(C57:D57) -> 93918 | F57: =SUM(Q57,V57,AD57,AN57,AI57)-AV57 -> 3868924.3 | G57: =(F57-F56)/F56 -> 0.026874698 | H57: =(F57-F45)/F45 -> 0.3521951 | I57: =36589+546118 -> 582707 | J57: =9576+9508 -> 19084 | K57: 106073 | L57: 34089 | M57: 15288 | N57: 46211 | O57: 2141.76 | P57: 67.83 | Q57: =SUM(I57:N57)+SUM(O57:P57)*$AS57 -> 871011.32 | R57: =Q57/F57 -> 0.2251301 | S57: 226650 | T57: 9007 | U57: 5466.4 | V57: =SUM(S57:T57)+U57*$AS57 -> 402794.91 | W57: =V57/F57 -> 0.10411031 | X57: =sum(T57,U57*AS57)/V57 -> 0.4373067 | Y57: 1247328 | Z57: 434136 | AA57: =2539.68+6919.6 -> 9459.28 | AB57: 6010.64 | AC57: 2107.25 | AD57: =SUM(Y57:Z57)+(AA57+AC57+AB57)*$AS57 -> 2218894.8 | AE57: =AD57/F57 -> 0.57351724 | AF57: =SUM(AA57:AC57)*AS57/AD57 -> 0.24220651 | AG57: 0.01 | AH57: 1444.62 | AI57: =(AH57+AG57)*$AS57 -> 44170.285 | AJ57: =AI57/F57 -> 0.011416684 | AK57: 350000 | AL57: 250000 | AM57: =SUM(AK57:AL57) -> 600000 | AN57: =11000000-2400000+250000 -> 8850000 | AO57: 250000 | AP57: 265625 | AQ57: 13.5 | AR57: =AP57*AQ57 -> 3585937.5 | AS57: 30.5755 | AV57: 8517947 | AW57: =AV57-AV56 -> -17870
A58: 45930 | B58: 45901 | C58: 56958 | D58: 20342.24 | E58: =SUM(C58:D58) -> 77300.24 | F58: =SUM(Q58,V58,AD58,AN58,AI58)-AV58 -> 4118923.6 | G58: =(F58-F57)/F57 -> 0.06461726 | H58: =(F58-F46)/F46 -> 0.38596864 | I58: =38944+506562 -> 545506 | J58: =291+9393 -> 9684 | K58: 101282 | L58: 29089 | M58: 15288 | N58: 50738 | O58: 1104.08 | P58: 69.59 | Q58: =SUM(I58:N58)+SUM(O58:P58)*$AS58 -> 787388.97 | R58: =Q58/F58 -> 0.19116377 | S58: 226041 | T58: 10056 | U58: 5982.81 | V58: =SUM(S58:T58)+U58*$AS58 -> 418598.37 | W58: =V58/F58 -> 0.1016281 | X58: =sum(T58,U58*AS58)/V58 -> 0.46000507 | Y58: 1362237 | Z58: 456237 | AA58: =2928.6+8864.2 -> 11792.8 | AB58: 7624.59 | AC58: 2160.45 | AD58: =SUM(Y58:Z58)+(AA58+AC58+AB58)*$AS58 -> 2476690.7 | AE58: =AD58/F58 -> 0.60129562 | AF58: =SUM(AA58:AC58)*AS58/AD58 -> 0.26576459 | AG58: 0.01 | AH58: 2828.79 | AI58: =(AH58+AG58)*$AS58 -> 86290.536 | AJ58: =AI58/F58 -> 0.020949778 | AK58: 350000 | AL58: 250000 | AM58: =SUM(AK58:AL58) -> 600000 | AN58: =11000000-2400000+250000 -> 8850000 | AO58: 250000 | AP58: 265625 | AQ58: 13.5 | AR58: =AP58*AQ58 -> 3585937.5 | AS58: 30.50429 | AV58: 8500045 | AW58: =AV58-AV57 -> -17902
A59: 45962 | B59: 45931 | C59: 57051 | D59: 37665.4 | E59: =SUM(C59:D59) -> 94716.4 | F59: =SUM(Q59,V59,AD59,AN59,AI59)-AV59 -> 4316490.2 | G59: =(F59-F58)/F58 -> 0.047965596 | H59: =(F59-F47)/F47 -> 0.44961148 | I59: =38944+462627 -> 501571 | J59: =9126+716 -> 9842 | K59: 172169 | L59: 24089 | M59: 288 | N59: 25456 | O59: 1194.45 | P59: 134.41 | Q59: =SUM(I59:N59)+SUM(O59:P59)*$AS59 -> 774259.11 | R59: =Q59/F59 -> 0.17937238 | S59: 279186 | T59: 11499 | U59: 5977.4 | V59: =SUM(S59:T59)+U59*$AS59 -> 474407.56 | W59: =V59/F59 -> 0.10990586 | X59: =sum(T59,U59*AS59)/V59 -> 0.41150601 | Y59: 1448081 | Z59: 419440 | AA59: =3377.76+9242.1 -> 12619.86 | AB59: 8246.94 | AC59: 2136.5 | AD59: =SUM(Y59:Z59)+(AA59+AC59+AB59)*$AS59 -> 2574555 | AE59: =AD59/F59 -> 0.5964464 | AF59: =SUM(AA59:AC59)*AS59/AD59 -> 0.27462378 | AG59: 0.01 | AH59: =1391.73+20.53+1317.07+147.86+1102.82+99.16 -> 4079.17 | AI59: =(AH59+AG59)*$AS59 -> 125378.49 | AJ59: =AI59/F59 -> 0.029046398 | AK59: 350000 | AL59: 250000 | AM59: =SUM(AK59:AL59) -> 600000 | AN59: =11000000-2400000+250000 -> 8850000 | AO59: 250000 | AP59: 265625 | AQ59: 13.5 | AR59: =AP59*AQ59 -> 3585937.5 | AS59: 30.7362 | AV59: 8482110 | AW59: =AV59-AV58 -> -17935
A60: 45991 | B60: 45962 | C60: 57051 | D60: 44050 | E60: =SUM(C60:D60) -> 101101 | F60: =SUM(Q60,V60,AD60,AN60,AI60)-AV60 -> 4231268.9 | G60: =(F60-F59)/F59 -> -0.019743197 | H60: =(F60-F48)/F48 -> 0.37168529 | I60: =40383+561794 -> 602177 | J60: 4815 | K60: 112255 | L60: 19089 | M60: 0 | N60: 63873 | O60: 1061.12 | P60: 63.27 | Q60: =SUM(I60:N60)+SUM(O60:P60)*$AS60 -> 837505.74 | R60: =Q60/F60 -> 0.19793253 | S60: 295543 | T60: 8636 | U60: 5480.61 | V60: =SUM(S60:T60)+U60*$AS60 -> 476225.76 | W60: =V60/F60 -> 0.11254916 | X60: =sum(T60,U60*AS60)/V60 -> 0.37940568 | Y60: 1374791 | Z60: 264839 | AA60: =9463.74+3842.16 -> 13305.9 | AB60: 9140.55 | AC60: 2043.27 | AD60: =SUM(Y60:Z60)+(AA60+AC60+AB60)*$AS60 -> 2408408.8 | AE60: =AD60/F60 -> 0.56919305 | AF60: =SUM(AA60:AC60)*AS60/AD60 -> 0.31920612 | AG60: 0.01 | AH60: =1506.76+1341+9.3+69.1+9.998+913.33+77.36 -> 3926.848 | AI60: =(AH60+AG60)*$AS60 -> 123271.53 | AJ60: =AI60/F60 -> 0.029133467 | AK60: 350000 | AL60: 250000 | AM60: =SUM(AK60:AL60) -> 600000 | AN60: =11000000-2400000+250000 -> 8850000 | AO60: 250000 | AP60: 265625 | AQ60: 13.5 | AR60: =AP60*AQ60 -> 3585937.5 | AS60: 31.3919 | AV60: 8464143 | AW60: =AV60-AV59 -> -17967
A61: 46023 | B61: 45992 | C61: 164180 | D61: 17584.16 | E61: =SUM(C61:D61) -> 181764.16 | F61: =SUM(Q61,V61,AD61,AN61,AI61)-AV61 -> 4528515.2 | G61: =(F61-F60)/F60 -> 0.070249919 | H61: =(F61-F49)/F49 -> 0.34882599 | I61: =581133+39870 -> 621003 | J61: 908 | K61: 132626 | L61: 14183 | M61: 25 | N61: 51362 | O61: 2348.11 | P61: 65.6 | Q61: =SUM(I61:N61)+SUM(O61:P61)*$AS61 -> 895860.08 | R61: =Q61/F61 -> 0.19782645 | S61: 312622 | T61: 9551 | U61: 5781.67 | V61: =SUM(S61:T61)+U61*$AS61 -> 503627.82 | W61: =V61/F61 -> 0.11121257 | X61: =sum(T61,U61*AS61)/V61 -> 0.37925987 | Y61: 1472255 | Z61: 282880 | AA61: =3766.2+9997.46 -> 13763.66 | AB61: 10904.12 | AC61: 2076.99 | AD61: =SUM(Y61:Z61)+(AA61+AC61+AB61)*$AS61 -> 2594506.2 | AE61: =AD61/F61 -> 0.57292648 | AF61: =SUM(AA61:AC61)*AS61/AD61 -> 0.32351868 | AG61: 0.01 | AH61: =1800.88+68.52+1311.02+13.76+882.33+76.81+10 -> 4163.32 | AI61: =(AH61+AG61)*$AS61 -> 130664.03 | AJ61: =AI61/F61 -> 0.028853614 | AK61: 350000 | AL61: 250000 | AM61: =SUM(AK61:AL61) -> 600000 | AN61: =11000000-2400000+250000 -> 8850000 | AO61: 250000 | AP61: 265625 | AQ61: 13.5 | AR61: =AP61*AQ61 -> 3585937.5 | AS61: 31.3845 | AV61: 8446143 | AW61: =AV61-AV60 -> -18000
A62: 46054 | B62: 46023 | C62: 57551 | D62: 19772 | E62: =SUM(C62:D62) -> 77323 | F62: =SUM(Q62,V62,AD62,AN62,AI62)-AV62 -> 4677907.2 | G62: =(F62-F61)/F61 -> 0.032989182 | H62: =(F62-F50)/F50 -> 0.35582384 | I62: =55733+527548 -> 583281 | J62: 631 | K62: 100066 | L62: 9183 | M62: 25025 | N62: 52007 | O62: 1762.86 | P62: 65.6 | Q62: =SUM(I62:N62)+SUM(O62:P62)*$AS62 -> 827968.68 | R62: =Q62/F62 -> 0.17699553 | S62: 342886 | T62: 10659 | U62: 5471.19 | V62: =SUM(S62:T62)+U62*$AS62 -> 526423.66 | W62: =V62/F62 -> 0.11253401 | X62: =sum(T62,U62*AS62)/V62 -> 0.3486501 | Y62: 1560926 | Z62: 354536 | AA62: =4059+9164.32 -> 13223.32 | AB62: 12065.87 | AC62: 1991.45 | AD62: =SUM(Y62:Z62)+(AA62+AC62+AB62)*$AS62 -> 2777475.7 | AE62: =AD62/F62 -> 0.59374322 | AF62: =SUM(AA62:AC62)*AS62/AD62 -> 0.31035867 | AG62: 0.01 | AH62: =1776.16+67.19+1215.62+12.91+61.09+786+10.04 -> 3929.01 | AI62: =(AH62+AG62)*$AS62 -> 124149.17 | AJ62: =AI62/F62 -> 0.026539469 | AK62: 350000 | AL62: 250000 | AM62: =SUM(AK62:AL62) -> 600000 | AN62: =11000000-2400000+250000 -> 8850000 | AO62: 250000 | AP62: 265625 | AQ62: 13.5 | AR62: =AP62*AQ62 -> 3585937.5 | AS62: 31.598 | AV62: 8428110 | AW62: =AV62-AV61 -> -18033
A63: 46082 | B63: 46054 | C63: 57250 | D63: 71101 | E63: =SUM(C63:D63) -> 128351 | F63: =SUM(Q63,V63,AD63,AN63,AI63)-AV63 -> 4842876.5 | G63: =(F63-F62)/F62 -> 0.035265633 | H63: =(F63-F51)/F51 -> 0.45831693 | I63: =55733+499976 -> 555709 | J63: 3545 | K63: 116124 | L63: 86141 | M63: 0 | N63: 59947 | O63: 975.66 | P63: 144.79 | Q63: =SUM(I63:N63)+SUM(O63:P63)*$AS63 -> 856549.53 | R63: =Q63/F63 -> 0.17686793 | S63: 269946 | T63: 11447 | U63: 5230.46 | V63: =SUM(S63:T63)+U63*$AS63 -> 445169.16 | W63: =V63/F63 -> 0.091922468 | X63: =sum(T63,U63*AS63)/V63 -> 0.39361029 | Y63: 1734489 | Z63: 376804 | AA63: =3688.56+9397.34 -> 13085.9 | AB63: 12896.89 | AC63: 2019.86 | AD63: =SUM(Y63:Z63)+(AA63+AC63+AB63)*$AS63 -> 2988112 | AE63: =AD63/F63 -> 0.6170118 | AF63: =SUM(AA63:AC63)*AS63/AD63 -> 0.29343578 | AG63: 0.01 | AH63: =1793+1030+12.3+65+659.4+52 -> 3611.7 | AI63: =(AH63+AG63)*$AS63 -> 113089.86 | AJ63: =AI63/F63 -> 0.023351796 | AK63: 350000 | AL63: 250000 | AM63: =SUM(AK63:AL63) -> 600000 | AN63: =11000000-2400000+250000 -> 8850000 | AO63: 250000 | AP63: 265625 | AQ63: 25 | AR63: =AP63*AQ63 -> 6640625 | AS63: 31.312 | AV63: 8410044 | AW63: =AV63-AV62 -> -18066
A64: 46144 | B64: 46113 | C64: 64975 | D64: 1868 | E64: =SUM(C64:D64) -> 66843 | F64: =SUM(Q64,V64,AD64,AN64,AI64)-AV64 -> 5248031.8 | G64: =(F64-F63)/F63 -> 0.083660052 | H64: =(F64-F53)/F53 -> 0.70023672 | I64: =60999+421921 -> 482920 | J64: 764 | K64: 137401 | L64: 76141 | M64: 11055 | N64: 24204 | O64: 1043.13 | P64: 427.76 | Q64: =SUM(I64:N64)+SUM(O64:P64)*$AS64 -> 779008.52 | R64: =Q64/F64 -> 0.14843822 | S64: 410839 | T64: 13531 | U64: 5531.04 | V64: =SUM(S64:T64)+U64*$AS64 -> 599314.03 | W64: =V64/F64 -> 0.11419786 | X64: =sum(T64,U64*AS64)/V64 -> 0.31448459 | Y64: 1865536 | Z64: 381799 | AA64: 14362.78 | AB64: 15176.74 | AC64: 2079.6 | AD64: =SUM(Y64:Z64)+(AA64+AC64+AB64)*$AS64 -> 3247432 | AE64: =AD64/F64 -> 0.61879045 | AF64: =SUM(AA64:AC64)*AS64/AD64 -> 0.30796548 | AG64: 0.01 | AH64: =12.82+1232.08+66.32+2453.31+61.97+786.48+5.81 -> 4618.79 | AI64: =(AH64+AG64)*$AS64 -> 146090.33 | AJ64: =AI64/F64 -> 0.027837166 | AK64: 350000 | AL64: 250000 | AM64: =SUM(AK64:AL64) -> 600000 | AN64: =11000000-2400000+250000 -> 8850000 | AO64: 250000 | AP64: 265625 | AQ64: 25 | AR64: =AP64*AQ64 -> 6640625 | AS64: 31.6295 | AV64: 8373813 | AW64: =AV64-AV63 -> -36231
A65: 46172 | B65: 46143 | C65: 60052 | D65: 26815 | E65: =SUM(C65:D65) -> 86867 | F65: =SUM(Q65,V65,AD65,AN65,AI65)-AV65 -> 5910630.6 | G65: =(F65-F64)/F64 -> 0.12625663 | H65: =(F65-F54)/F54 -> 0.79769294 | I65: =174229+305571 -> 479800 | J65: 629 | K65: 118774 | L65: 71141 | M65: 3055 | N65: 24204 | O65: 2834.03 | P65: 30.36 | Q65: =SUM(I65:N65)+SUM(O65:P65)*$AS65 -> 787621.61 | R65: =Q65/F65 -> 0.13325509 | S65: 462162 | T65: 15342 | U65: 6023.89 | V65: =SUM(S65:T65)+U65*$AS65 -> 666815.59 | W65: =V65/F65 -> 0.11281632 | X65: =sum(T65,U65*AS65)/V65 -> 0.30691182 | Y65: 2075032 | Z65: 565233 | AA65: 15893 | AB65: 19076.18 | AC65: 2189.29 | AD65: =SUM(Y65:Z65)+(AA65+AC65+AB65)*$AS65 -> 3808036.8 | AE65: =AD65/F65 -> 0.64426912 | AF65: =SUM(AA65:AC65)*AS65/AD65 -> 0.3066598 | AG65: 0.01 | AH65: =1365.76+7.55+2646.45+79.72+5.82+53.86+734.89 -> 4894.05 | AI65: =(AH65+AG65)*$AS65 -> 153804.64 | AJ65: =AI65/F65 -> 0.026021698 | AK65: 350000 | AL65: 250000 | AM65: =SUM(AK65:AL65) -> 600000 | AN65: =11000000-2400000+250000 -> 8850000 | AO65: 250000 | AP65: 265625 | AQ65: 25 | AR65: =AP65*AQ65 -> 6640625 | AS65: 31.4268 | AV65: 8355648 | AW65: =AV65-AV64 -> -18165

Sheet Spot Holdings
B1: Holding Assets | E1: VIX INDEX | F1: =IFERROR(__xludf.DUMMYFUNCTION("GOOGLEFINANCE(""INDEXCBOE:VIX"",""price"")"),15.32) -> 15.32 | G1: SKEW INDEX | H1: =IFERROR(__xludf.DUMMYFUNCTION("GOOGLEFINANCE(""INDEXCBOE:SKEW"",""price"")"),144.18) -> 144.18
B2: Current Holdiing Value | E2: USD/TWD | F2: Total P/L Day | G2: Total P/L Day% | I2: Total Holding | L2: Cost Basis | M2: Total P/L | N2: Total P/L% | O2: 總報酬率(含息)
B3: =SUM(I6:I39) -> 3904601.2 | E3: =IFERROR(__xludf.DUMMYFUNCTION("GOOGLEFINANCE(""USDTWD"")"),31.426800000000004) -> 31.4268 | F3: =SUMPRODUCT(F6:F39,H6:H39) -> 39964.184 | G3: =F3/(I3-F3)*100% -> 0.010340993 | I3: =SUM(I6:I39) -> 3904601.2 | L3: =SUM(L6:L39) -> 2190622.7 | M3: =I3-L3 -> 1713978.5 | N3: =M3/L3 -> 0.78241612 | O3: =(M3+SUM(P3,Q3,R3,S3,T3))/L3 -> 0.90538284 | P3: =SUM(P6:P39) -> 13207 | Q3: =SUM(Q6:Q39) -> 35557.764 | R3: =SUM(R6:R39) -> 52674.896 | S3: =SUM(S6:S39) -> 79406.661 | T3: =SUM(T6:T39) -> 88527.36 | U3: =SUM(U6:U39) -> 27260 | V3: =SUM(P3:T3) -> 269373.68
B5: Symbol | C5: Exchange (Optional) | D5: Stock Name | E5: Current Price | F5: P/L Day | G5: P/L Day% | H5: Shares | I5: 預估現值 | J5: 持有現值比例 | K5: Trade Price | L5: 買進成本 | M5: P/L Open | N5: 含息報酬率 | O5: 產業類型 | P5: 2021年股息 | Q5: 2022年股息 | R5: 2023年股息 | S5: 2024年股息 | T5: 2025年股息 | U5: 2026年股息 | V5: 開始買進日 | W5: 持有天數
B6: TPE:00692 | D6: 00692 | E6: =IFERROR(__xludf.DUMMYFUNCTION("IF(ISBLANK(B6), 0, GOOGLEFINANCE(IF(ISBLANK(C6), B6, C6&"":""&B6), ""price""))"),90.45) -> 90.45 | F6: =IFERROR(__xludf.DUMMYFUNCTION("IF(ISBLANK(B6), 0, GOOGLEFINANCE(IF(ISBLANK(C6), B6, C6&"":""&B6), ""change""))"),3.2) -> 3.2 | G6: =IFERROR(__xludf.DUMMYFUNCTION("IF(ISBLANK(B6), 0, GOOGLEFINANCE(IF(ISBLANK(C6), B6, C6&"":""&B6), ""changepct"")/100)"),0.036699999999999997) -> 0.0367 | H6: ='00692 富邦公司治理'!J8 -> 7500 | I6: =H6 * E6 -> 678375 | J6: =I6/$I$3 -> 0.17373733 | K6: ='00692 富邦公司治理'!L8 -> 34.499067 | L6: =H6*K6 -> 258743 | M6: =I6-L6 -> 419632 | N6: =IF(H6=0,0,IF(L6=0,1,(M6+P6+Q6+R6+S6+T6+U6)/L6*100%)) -> 1.7539644 | O6: 指數型ETF | P6: 3914 | Q6: =2950+1375 -> 4325 | R6: =1820+4230 -> 6050 | S6: =1650+4190 -> 5840 | T6: =4700+9365 -> 14065 | V6: 43879 | W6: =DAYS(TODAY(),V6) -> 2293
B7: TPE:00878 | D7: 00878 | E7: =IFERROR(__xludf.DUMMYFUNCTION("IF(ISBLANK(B7), 0, GOOGLEFINANCE(IF(ISBLANK(C7), B7, C7&"":""&B7), ""price""))"),30.76) -> 30.76 | F7: =IFERROR(__xludf.DUMMYFUNCTION("IF(ISBLANK(B7), 0, GOOGLEFINANCE(IF(ISBLANK(C7), B7, C7&"":""&B7), ""change""))"),0.76) -> 0.76 | G7: =IFERROR(__xludf.DUMMYFUNCTION("IF(ISBLANK(B7), 0, GOOGLEFINANCE(IF(ISBLANK(C7), B7, C7&"":""&B7), ""changepct"")/100)"),0.0253) -> 0.0253 | H7: ='00878 國泰永續'!J8 -> 17243 | I7: =H7 * E7 -> 530394.68 | J7: =I7/$I$3 -> 0.13583837 | K7: ='00878 國泰永續'!L8 -> 18.604 | L7: =H7*K7 -> 320788.78 | M7: =I7-L7 -> 209605.9 | N7: =IF(H7=0,0,IF(L7=0,1,(M7+P7+Q7+R7+S7+T7+U7)/L7*100%)) -> 0.97423887 | O7: 高股息型ETF | P7: 1270 | Q7: =2470+2230+(11000*0.28-10)+3070 -> 10840 | R7: =(13000*0.27-10)+3500+4540+4540 -> 16080 | S7: =5330+6988+7815+8069 -> 28202 | T7: =7576+7374+6475+6617 -> 28042 | U7: =7126+11359 -> 18485 | V7: 44396 | W7: =DAYS(TODAY(),V7) -> 1776
B8: TPE:2330 | D8: 台積電 | E8: =IFERROR(__xludf.DUMMYFUNCTION("IF(ISBLANK(B8), 0, GOOGLEFINANCE(IF(ISBLANK(C8), B8, C8&"":""&B8), ""price""))"),2355.0) -> 2355 | F8: =IFERROR(__xludf.DUMMYFUNCTION("IF(ISBLANK(B8), 0, GOOGLEFINANCE(IF(ISBLANK(C8), B8, C8&"":""&B8), ""change""))"),60.0) -> 60 | G8: =IFERROR(__xludf.DUMMYFUNCTION("IF(ISBLANK(B8), 0, GOOGLEFINANCE(IF(ISBLANK(C8), B8, C8&"":""&B8), ""changepct"")/100)"),0.026099999999999998) -> 0.0261 | H8: ='2330 台積電'!J8 -> 160 | I8: =H8 * E8 -> 376800 | J8: =I8/$I$3 -> 0.096501532 | K8: ='2330 台積電'!L8 -> 1428.5062 | L8: =H8*K8 -> 228561 | M8: =I8-L8 -> 148239 | N8: =IF(H8=0,0,IF(L8=0,1,(M8+P8+Q8+R8+S8+T8+U8)/L8*100%)) -> 0.65946946 | O8: 電子/科技 | T8: =240+770+645 -> 1655 | U8: =835 -> 835 | V8: 45846 | W8: =DAYS(TODAY(),V8) -> 326
B9: TSLA | C9: NASDAQ | D9: TSLA | E9: =IFERROR(__xludf.DUMMYFUNCTION("IF(ISBLANK(B9), 0, GOOGLEFINANCE(IF(ISBLANK(C9), B9, C9&"":""&B9), ""price""))"),435.79) -> 435.79 | F9: =IFERROR(__xludf.DUMMYFUNCTION("IF(ISBLANK(B9), 0, GOOGLEFINANCE(IF(ISBLANK(C9), B9, C9&"":""&B9), ""change""))*$E$3"),-198.303108) -> -198.30311 | G9: =IFERROR(__xludf.DUMMYFUNCTION("IF(ISBLANK(B9), 0, GOOGLEFINANCE(IF(ISBLANK(C9), B9, C9&"":""&B9), ""changepct"")/100)"),-0.0143) -> -0.0143 | H9: 26 | I9: =H9 * E9*$E$3 -> 356082.61 | J9: =I9/$I$3 -> 0.091195642 | K9: =256.775 -> 256.775 | L9: =H9*K9*$E$3 -> 209810.03 | M9: =I9-L9 -> 146272.58 | N9: =IF(H9=0,0,IF(L9=0,1,(M9+P9+Q9+R9+S9+T9+U9)/L9*100%)) -> 0.69716678 | O9: 耐用消費品 | V9: 44755 | W9: =DAYS(TODAY(),V9) -> 1417
B10: RKLB | D10: RKLB | E10: =IFERROR(__xludf.DUMMYFUNCTION("IF(ISBLANK(B10), 0, GOOGLEFINANCE(IF(ISBLANK(C10), B10, C10&"":""&B10), ""price""))"),143.48) -> 143.48 | F10: =IFERROR(__xludf.DUMMYFUNCTION("IF(ISBLANK(B10), 0, GOOGLEFINANCE(IF(ISBLANK(C10), B10, C10&"":""&B10), ""change""))*$E$3"),-142.99194) -> -142.99194 | G10: =IFERROR(__xludf.DUMMYFUNCTION("IF(ISBLANK(B10), 0, GOOGLEFINANCE(IF(ISBLANK(C10), B10, C10&"":""&B10), ""changepct"")/100)"),-0.030699999999999998) -> -0.0307 | H10: 50 | I10: =H10 * E10*$E$3 -> 225455.86 | J10: =I10/$I$3 -> 0.057741073 | K10: 50.61 | L10: =H10*K10*$E$3 -> 79525.517 | M10: =I10-L10 -> 145930.35 | N10: =IF(H10=0,0,IF(L10=0,1,(M10+P10+Q10+R10+S10+T10+U10)/L10*100%)) -> 1.8350128 | O10: 電子/科技 | V10: 45834 | W10: =DAYS(TODAY(),V10) -> 338
B11: TPE:2890 | D11: 永豐金 | E11: =IFERROR(__xludf.DUMMYFUNCTION("IF(ISBLANK(B11), 0, GOOGLEFINANCE(IF(ISBLANK(C11), B11, C11&"":""&B11), ""price""))"),30.0) -> 30 | F11: =IFERROR(__xludf.DUMMYFUNCTION("IF(ISBLANK(B11), 0, GOOGLEFINANCE(IF(ISBLANK(C11), B11, C11&"":""&B11), ""change""))"),0.5) -> 0.5 | G11: =IFERROR(__xludf.DUMMYFUNCTION("IF(ISBLANK(B11), 0, GOOGLEFINANCE(IF(ISBLANK(C11), B11, C11&"":""&B11), ""changepct"")/100)"),0.0169) -> 0.0169 | H11: 7238 | I11: =H11 * E11 -> 217140 | J11: =I11/$I$3 -> 0.055611313 | K11: 21.88 | L11: =H11*K11 -> 158367.44 | M11: =I11-L11 -> 58772.56 | N11: =IF(H11=0,0,IF(L11=0,1,(M11+P11+Q11+R11+S11+T11+U11)/L11*100%)) -> 0.42505934 | O11: 金融 | Q11: 790 | R11: 590 | S11: 803 | T11: 6360 | V11: 44427 | W11: =DAYS(TODAY(),V11) -> 1745
B12: VTI | D12: VTI | E12: =IFERROR(__xludf.DUMMYFUNCTION("IF(ISBLANK(B12), 0, GOOGLEFINANCE(IF(ISBLANK(C12), B12, C12&"":""&B12), ""price""))"),372.54) -> 372.54 | F12: =IFERROR(__xludf.DUMMYFUNCTION("IF(ISBLANK(B12), 0, GOOGLEFINANCE(IF(ISBLANK(C12), B12, C12&"":""&B12), ""change""))*$E$3"),27.655584000000005) -> 27.655584 | G12: =IFERROR(__xludf.DUMMYFUNCTION("IF(ISBLANK(B12), 0, GOOGLEFINANCE(IF(ISBLANK(C12), B12, C12&"":""&B12), ""changepct"")/100)"),0.0024) -> 0.0024 | H12: =VTI!J8 -> 17.30997 | I12: =H12 * E12*$E$3 -> 202660.63 | J12: =I12/$I$3 -> 0.051903029 | K12: =VTI!L8 -> 307.66307 | L12: =H12*K12*$E$3 -> 167367.78 | M12: =I12-L12 -> 35292.852 | N12: =IF(H12=0,0,IF(L12=0,1,(M12+P12+Q12+R12+S12+T12+U12)/L12*100%)) -> 0.21089282 | O12: 指數型ETF | S12: 0.45 | T12: 3.36 | V12: 45162 | W12: =DAYS(TODAY(),V12) -> 1010
B13: TPE:2885 | D13: 元大金 | E13: =IFERROR(__xludf.DUMMYFUNCTION("IF(ISBLANK(B13), 0, GOOGLEFINANCE(IF(ISBLANK(C13), B13, C13&"":""&B13), ""price""))"),59.6) -> 59.6 | F13: =IFERROR(__xludf.DUMMYFUNCTION("IF(ISBLANK(B13), 0, GOOGLEFINANCE(IF(ISBLANK(C13), B13, C13&"":""&B13), ""change""))"),0.5) -> 0.5 | G13: =IFERROR(__xludf.DUMMYFUNCTION("IF(ISBLANK(B13), 0, GOOGLEFINANCE(IF(ISBLANK(C13), B13, C13&"":""&B13), ""changepct"")/100)"),0.0085) -> 0.0085 | H13: 3000 | I13: =H13 * E13 -> 178800 | J13: =I13/$I$3 -> 0.045792128 | K13: 22.02 | L13: =H13*K13 -> 66060 | M13: =I13-L13 -> 112740 | N13: =IF(H13=0,0,IF(L13=0,1,(M13+P13+Q13+R13+S13+T13+U13)/L13*100%)) -> 1.897366 | O13: 金融 | P13: 2390 | Q13: 2990 | R13: 1638 | S13: 2289 | T13: 3293 | V13: 44060 | W13: =DAYS(TODAY(),V13) -> 2112
B14: TPE:00881 | D14: 00881 | E14: =IFERROR(__xludf.DUMMYFUNCTION("IF(ISBLANK(B14), 0, GOOGLEFINANCE(IF(ISBLANK(C14), B14, C14&"":""&B14), ""price""))"),54.9) -> 54.9 | F14: =IFERROR(__xludf.DUMMYFUNCTION("IF(ISBLANK(B14), 0, GOOGLEFINANCE(IF(ISBLANK(C14), B14, C14&"":""&B14), ""change""))"),1.75) -> 1.75 | G14: =IFERROR(__xludf.DUMMYFUNCTION("IF(ISBLANK(B14), 0, GOOGLEFINANCE(IF(ISBLANK(C14), B14, C14&"":""&B14), ""changepct"")/100)"),0.0329) -> 0.0329 | H14: 3000 | I14: =H14 * E14 -> 164700 | J14: =I14/$I$3 -> 0.042181004 | K14: 17.29 | L14: =H14*K14 -> 51870 | M14: =I14-L14 -> 112830 | N14: =IF(H14=0,0,IF(L14=0,1,(M14+P14+Q14+R14+S14+T14+U14)/L14*100%)) -> 2.7989204 | O14: 科技主題型ETF | P14: 2150 | Q14: =2340+1030 -> 3370 | R14: =1390+2290 -> 3680 | S14: =3740+4990 -> 8730 | T14: =3740+2740 -> 6480 | U14: =7940 -> 7940 | V14: 44214 | W14: =DAYS(TODAY(),V14) -> 1958
B15: TPE:2480 | D15: 敦陽科 | E15: =IFERROR(__xludf.DUMMYFUNCTION("IF(ISBLANK(B15), 0, GOOGLEFINANCE(IF(ISBLANK(C15), B15, C15&"":""&B15), ""price""))"),148.5) -> 148.5 | F15: =IFERROR(__xludf.DUMMYFUNCTION("IF(ISBLANK(B15), 0, GOOGLEFINANCE(IF(ISBLANK(C15), B15, C15&"":""&B15), ""change""))"),1.5) -> 1.5 | G15: =IFERROR(__xludf.DUMMYFUNCTION("IF(ISBLANK(B15), 0, GOOGLEFINANCE(IF(ISBLANK(C15), B15, C15&"":""&B15), ""changepct"")/100)"),0.0102) -> 0.0102 | H15: 1000 | I15: =H15 * E15 -> 148500 | J15: =I15/$I$3 -> 0.038032053 | K15: 85.92 | L15: =H15*K15 -> 85920 | M15: =I15-L15 -> 62580 | N15: =IF(H15=0,0,IF(L15=0,1,(M15+P15+Q15+R15+S15+T15+U15)/L15*100%)) -> 0.96450186 | O15: 科技服務 | R15: 6250 | S15: 6630 | T15: 7410 | V15: 44778 | W15: =DAYS(TODAY(),V15) -> 1394
B16: TPE:2327 | D16: 國巨* | E16: =IFERROR(__xludf.DUMMYFUNCTION("IF(ISBLANK(B16), 0, GOOGLEFINANCE(IF(ISBLANK(C16), B16, C16&"":""&B16), ""price""))"),738.0) -> 738 | F16: =IFERROR(__xludf.DUMMYFUNCTION("IF(ISBLANK(B16), 0, GOOGLEFINANCE(IF(ISBLANK(C16), B16, C16&"":""&B16), ""change""))"),-4.0) -> -4 | G16: =IFERROR(__xludf.DUMMYFUNCTION("IF(ISBLANK(B16), 0, GOOGLEFINANCE(IF(ISBLANK(C16), B16, C16&"":""&B16), ""changepct"")/100)"),-0.0054) -> -0.0054 | H16: 200 | I16: =H16 * E16 -> 147600 | J16: =I16/$I$3 -> 0.037801555 | K16: 328.25 | L16: =H16*K16 -> 65650 | M16: =I16-L16 -> 81950 | N16: =IF(H16=0,0,IF(L16=0,1,(M16+P16+Q16+R16+S16+T16+U16)/L16*100%)) -> 1.2482864 | O16: 電子/科技 | V16: 46126 | W16: =DAYS(TODAY(),V16) -> 46
B17: GOOGL | D17: GOOGL | E17: =IFERROR(__xludf.DUMMYFUNCTION("IF(ISBLANK(B17), 0, GOOGLEFINANCE(IF(ISBLANK(C17), B17, C17&"":""&B17), ""price""))"),380.34) -> 380.34 | F17: =IFERROR(__xludf.DUMMYFUNCTION("IF(ISBLANK(B17), 0, GOOGLEFINANCE(IF(ISBLANK(C17), B17, C17&"":""&B17), ""change""))*$E$3"),-307.66837200000003) -> -307.66837 | G17: =IFERROR(__xludf.DUMMYFUNCTION("IF(ISBLANK(B17), 0, GOOGLEFINANCE(IF(ISBLANK(C17), B17, C17&"":""&B17), ""changepct"")/100)"),-0.025099999999999997) -> -0.0251 | H17: 12 | I17: =H17 * E17*$E$3 -> 143434.43 | J17: =I17/$I$3 -> 0.036734719 | K17: 155.06 | L17: =H17*K17*$E$3 -> 58476.475 | M17: =I17-L17 -> 84957.954 | N17: =IF(H17=0,0,IF(L17=0,1,(M17+P17+Q17+R17+S17+T17+U17)/L17*100%)) -> 1.452857 | O17: 科技服務 | V17: 45012 | W17: =DAYS(TODAY(),V17) -> 1160
B18: CURRENCY:BTC/USD | D18: $Bitcoin | E18: =IFERROR(__xludf.DUMMYFUNCTION("GOOGLEFINANCE(B18)"),73523.1) -> 73523.1 | H18: =0.01004+0.01221016+0.03118442 -> 0.05343458 | I18: =H18 * E18* $E$3 -> 123465.71 | J18: =I18/$I$3 -> 0.031620569 | K18: 94000 | L18: =H18*K18 *$E$3 -> 157852.12 | M18: =I18-L18 -> -34386.405 | N18: =IF(H18=0,0,IF(L18=0,1,(M18+P18+Q18+R18+S18+T18+U18)/L18*100%)) -> -0.21783936 | O18: Crypto | V18: 45864 | W18: =DAYS(TODAY(),V18) -> 308
B19: TPE:2887 | D19: 台新新光金 | E19: =IFERROR(__xludf.DUMMYFUNCTION("IF(ISBLANK(B19), 0, GOOGLEFINANCE(IF(ISBLANK(C19), B19, C19&"":""&B19), ""price""))"),23.35) -> 23.35 | F19: =IFERROR(__xludf.DUMMYFUNCTION("IF(ISBLANK(B19), 0, GOOGLEFINANCE(IF(ISBLANK(C19), B19, C19&"":""&B19), ""change""))"),0.35) -> 0.35 | G19: =IFERROR(__xludf.DUMMYFUNCTION("IF(ISBLANK(B19), 0, GOOGLEFINANCE(IF(ISBLANK(C19), B19, C19&"":""&B19), ""changepct"")/100)"),0.0152) -> 0.0152 | H19: ='2887 台新金'!J8 -> 5000 | I19: =H19 * E19 -> 116750 | J19: =I19/$I$3 -> 0.029900621 | K19: ='2887 台新金'!L8 -> 11.00958 | L19: =H19*K19 -> 55047.9 | M19: =I19-L19 -> 61702.1 | N19: =IF(H19=0,0,IF(L19=0,1,(M19+P19+Q19+R19+S19+T19+U19)/L19*100%)) -> 1.7692246 | O19: 金融 | P19: 1100 | Q19: 7260 | R19: 8150 | S19: 11990 | T19: 7190 | V19: 44403 | W19: =DAYS(TODAY(),V19) -> 1769
B20: NVDA | D20: =IFERROR(__xludf.DUMMYFUNCTION("IF(ISBLANK(B20), ""-"", GOOGLEFINANCE(IF(ISBLANK(C20), B20, C20&"":""&B20), ""name""))"),"NVIDIA Corp") -> NVIDIA Corp | E20: =IFERROR(__xludf.DUMMYFUNCTION("IF(ISBLANK(B20), 0, GOOGLEFINANCE(IF(ISBLANK(C20), B20, C20&"":""&B20), ""price""))"),211.14) -> 211.14 | F20: =IFERROR(__xludf.DUMMYFUNCTION("IF(ISBLANK(B20), 0, GOOGLEFINANCE(IF(ISBLANK(C20), B20, C20&"":""&B20), ""change""))*$E$3"),-97.73734800000001) -> -97.737348 | G20: =IFERROR(__xludf.DUMMYFUNCTION("IF(ISBLANK(B20), 0, GOOGLEFINANCE(IF(ISBLANK(C20), B20, C20&"":""&B20), ""changepct"")/100)"),-0.014499999999999999) -> -0.0145 | H20: 17 | I20: =H20 * E20*$E$3 -> 112802.73 | J20: =I20/$I$3 -> 0.028889692 | K20: 167.848 | L20: =H20*K20*$E$3 -> 89673.734 | M20: =I20-L20 -> 23128.993 | N20: =IF(H20=0,0,IF(L20=0,1,(M20+P20+Q20+R20+S20+T20+U20)/L20*100%)) -> 0.25792384 | O20: 電子/科技 | V20: 45817 | W20: =DAYS(TODAY(),V20) -> 355
B21: TPE:2834 | D21: 臺企銀 | E21: =IFERROR(__xludf.DUMMYFUNCTION("IF(ISBLANK(B21), 0, GOOGLEFINANCE(IF(ISBLANK(C21), B21, C21&"":""&B21), ""price""))"),16.25) -> 16.25 | F21: =IFERROR(__xludf.DUMMYFUNCTION("IF(ISBLANK(B21), 0, GOOGLEFINANCE(IF(ISBLANK(C21), B21, C21&"":""&B21), ""change""))"),0.35) -> 0.35 | G21: =IFERROR(__xludf.DUMMYFUNCTION("IF(ISBLANK(B21), 0, GOOGLEFINANCE(IF(ISBLANK(C21), B21, C21&"":""&B21), ""changepct"")/100)"),0.022000000000000002) -> 0.022 | H21: ='2834 臺企銀'!J8 -> 5019 | I21: =H21 * E21 -> 81558.75 | J21: =I21/$I$3 -> 0.020887856 | K21: ='2834 臺企銀'!L8 -> 8.1162283 | L21: =H21*K21 -> 40735.35 | M21: =I21-L21 -> 40823.4 | N21: =IF(H21=0,0,IF(L21=0,1,(M21+P21+Q21+R21+S21+T21+U21)/L21*100%)) -> 1.0733822 | O21: 金融 | P21: 310 | Q21: 390 | R21: 414.8 | S21: 849.4 | T21: 937 | V21: 43816 | W21: =DAYS(TODAY(),V21) -> 2356
B22: ASTS | D22: =IFERROR(__xludf.DUMMYFUNCTION("IF(ISBLANK(B22), ""-"", GOOGLEFINANCE(IF(ISBLANK(C22), B22, C22&"":""&B22), ""name""))"),"AST SpaceMobile Inc") -> AST SpaceMobile Inc | E22: =IFERROR(__xludf.DUMMYFUNCTION("IF(ISBLANK(B22), 0, GOOGLEFINANCE(IF(ISBLANK(C22), B22, C22&"":""&B22), ""price""))"),113.41) -> 113.41 | F22: =IFERROR(__xludf.DUMMYFUNCTION("IF(ISBLANK(B22), 0, GOOGLEFINANCE(IF(ISBLANK(C22), B22, C22&"":""&B22), ""change""))*$E$3"),-618.4794240000001) -> -618.47942 | G22: =IFERROR(__xludf.DUMMYFUNCTION("IF(ISBLANK(B22), 0, GOOGLEFINANCE(IF(ISBLANK(C22), B22, C22&"":""&B22), ""changepct"")/100)"),-0.1479) -> -0.1479 | H22: 10 | I22: =H22 * E22*$E$3 -> 35641.134 | J22: =I22/$I$3 -> 0.0091279831 | K22: =82.186 -> 82.186 | L22: =H22*K22*$E$3 -> 25828.43 | M22: =I22-L22 -> 9812.704 | N22: =IF(H22=0,0,IF(L22=0,1,(M22+P22+Q22+R22+S22)/L22*100%)) -> 0.37991872 | O22: 電子/科技 | V22: 46160 | W22: =DAYS(TODAY(),V22) -> 12
B23: UNCY | D23: UNCY | E23: =IFERROR(__xludf.DUMMYFUNCTION("IF(ISBLANK(B23), 0, GOOGLEFINANCE(IF(ISBLANK(C23), B23, C23&"":""&B23), ""price""))"),7.38) -> 7.38 | F23: =IFERROR(__xludf.DUMMYFUNCTION("IF(ISBLANK(B23), 0, GOOGLEFINANCE(IF(ISBLANK(C23), B23, C23&"":""&B23), ""change""))*$E$3"),11.313648) -> 11.313648 | G23: =IFERROR(__xludf.DUMMYFUNCTION("IF(ISBLANK(B23), 0, GOOGLEFINANCE(IF(ISBLANK(C23), B23, C23&"":""&B23), ""changepct"")/100)"),0.0513) -> 0.0513 | H23: 100 | I23: =H23 * E23* $E$3 -> 23192.978 | J23: =I23/$I$3 -> 0.0059399096 | K23: 6.8667 | L23: =H23*K23 *$E$3 -> 21579.841 | M23: =I23-L23 -> 1613.1376 | N23: =IF(H23=0,0,IF(L23=0,1,(M23+P23+Q23+R23+S23+T23+U23)/L23*100%)) -> 0.074752064 | O23: 健康科技 | V23: 45832 | W23: =DAYS(TODAY(),V23) -> 340
B24: CRCL | D24: =IFERROR(__xludf.DUMMYFUNCTION("IF(ISBLANK(B24), ""-"", GOOGLEFINANCE(IF(ISBLANK(C24), B24, C24&"":""&B24), ""name""))"),"Circle Internet Group Inc") -> Circle Internet Group Inc | E24: =IFERROR(__xludf.DUMMYFUNCTION("IF(ISBLANK(B24), 0, GOOGLEFINANCE(IF(ISBLANK(C24), B24, C24&"":""&B24), ""price""))"),113.0) -> 113 | F24: =IFERROR(__xludf.DUMMYFUNCTION("IF(ISBLANK(B24), 0, GOOGLEFINANCE(IF(ISBLANK(C24), B24, C24&"":""&B24), ""change""))*$E$3"),149.59156800000002) -> 149.59157 | G24: =IFERROR(__xludf.DUMMYFUNCTION("IF(ISBLANK(B24), 0, GOOGLEFINANCE(IF(ISBLANK(C24), B24, C24&"":""&B24), ""changepct"")/100)"),0.044000000000000004) -> 0.044 | H24: 6 | I24: =H24 * E24*$E$3 -> 21307.37 | J24: =I24/$I$3 -> 0.0054569901 | K24: 85.6 | L24: =H24*K24*$E$3 -> 16140.804 | M24: =I24-L24 -> 5166.5659 | N24: =IF(H24=0,0,IF(L24=0,1,(M24+P24+Q24+R24+S24+T24+U24)/L24*100%)) -> 0.32009346 | O24: 科技服務 | V24: 45973 | W24: =DAYS(TODAY(),V24) -> 199
B25: GRAB | D25: =IFERROR(__xludf.DUMMYFUNCTION("IF(ISBLANK(B25), ""-"", GOOGLEFINANCE(IF(ISBLANK(C25), B25, C25&"":""&B25), ""name""))"),"Grab Holdings Ltd") -> Grab Holdings Ltd | E25: =IFERROR(__xludf.DUMMYFUNCTION("IF(ISBLANK(B25), 0, GOOGLEFINANCE(IF(ISBLANK(C25), B25, C25&"":""&B25), ""price""))"),3.54) -> 3.54 | F25: =IFERROR(__xludf.DUMMYFUNCTION("IF(ISBLANK(B25), 0, GOOGLEFINANCE(IF(ISBLANK(C25), B25, C25&"":""&B25), ""change""))*$E$3"),0.0) -> 0 | G25: =IFERROR(__xludf.DUMMYFUNCTION("IF(ISBLANK(B25), 0, GOOGLEFINANCE(IF(ISBLANK(C25), B25, C25&"":""&B25), ""changepct"")/100)"),0.0) -> 0 | H25: 120 | I25: =H25 * E25*$E$3 -> 13350.105 | J25: =I25/$I$3 -> 0.0034190699 | K25: 4.8 | L25: =H25*K25*$E$3 -> 18101.837 | M25: =I25-L25 -> -4751.7322 | N25: =IF(H25=0,0,IF(L25=0,1,(M25+P25+Q25+R25+S25+T25+U25)/L25*100%)) -> -0.2625 | O25: 金融 | V25: 45659 | W25: =DAYS(TODAY(),V25) -> 513
B26: NVO | D26: =IFERROR(__xludf.DUMMYFUNCTION("IF(ISBLANK(B26), ""-"", GOOGLEFINANCE(IF(ISBLANK(C26), B26, C26&"":""&B26), ""name""))"),"Novo Nordisk A/S") -> Novo Nordisk A/S | E26: =IFERROR(__xludf.DUMMYFUNCTION("IF(ISBLANK(B26), 0, GOOGLEFINANCE(IF(ISBLANK(C26), B26, C26&"":""&B26), ""price""))"),45.58) -> 45.58 | F26: =IFERROR(__xludf.DUMMYFUNCTION("IF(ISBLANK(B26), 0, GOOGLEFINANCE(IF(ISBLANK(C26), B26, C26&"":""&B26), ""change""))*$E$3"),2.1998760000000006) -> 2.199876 | G26: =IFERROR(__xludf.DUMMYFUNCTION("IF(ISBLANK(B26), 0, GOOGLEFINANCE(IF(ISBLANK(C26), B26, C26&"":""&B26), ""changepct"")/100)"),0.0015) -> 0.0015 | H26: 4 | I26: =H26 * E26*$E$3 -> 5729.7342 | J26: =I26/$I$3 -> 0.0014674313 | K26: 106.65 | L26: =H26*K26*$E$3 -> 13406.673 | M26: =I26-L26 -> -7676.9387 | N26: =IF(H26=0,0,IF(L26=0,1,(M26+P26+Q26+R26+S26+T26+U26)/L26*100%)) -> -0.57262072 | O26: 健康科技 | V26: 45497 | W26: =DAYS(TODAY(),V26) -> 675
B27: AMZN | D27: =IFERROR(__xludf.DUMMYFUNCTION("IF(ISBLANK(B27), ""-"", GOOGLEFINANCE(IF(ISBLANK(C27), B27, C27&"":""&B27), ""name""))"),"Amazon.com Inc") -> Amazon.com Inc | E27: =IFERROR(__xludf.DUMMYFUNCTION("IF(ISBLANK(B27), 0, GOOGLEFINANCE(IF(ISBLANK(C27), B27, C27&"":""&B27), ""price""))"),270.64) -> 270.64 | F27: =IFERROR(__xludf.DUMMYFUNCTION("IF(ISBLANK(B27), 0, GOOGLEFINANCE(IF(ISBLANK(C27), B27, C27&"":""&B27), ""change""))*$E$3"),-105.59404800000002) -> -105.59405 | G27: =IFERROR(__xludf.DUMMYFUNCTION("IF(ISBLANK(B27), 0, GOOGLEFINANCE(IF(ISBLANK(C27), B27, C27&"":""&B27), ""changepct"")/100)"),-0.0123) -> -0.0123 | I27: =H27 * E27*$E$3 -> 0 | J27: =I27/$I$3 -> 0 | K27: 241.5675 | L27: =H27*K27*$E$3 -> 0 | M27: =I27-L27 -> 0 | N27: =IF(H27=0,0,IF(L27=0,1,(M27+P27+Q27+R27+S27)/L27*100%)) -> 0 | O27: 電子/科技 | V27: 46056 | W27: =DAYS(TODAY(),V27) -> 116
B28: TPE:2002 | D28: =IFERROR(__xludf.DUMMYFUNCTION("IF(ISBLANK(B28), ""-"", GOOGLEFINANCE(IF(ISBLANK(C28), B28, C28&"":""&B28), ""name""))"),"China Steel Corp") -> China Steel Corp | E28: =IFERROR(__xludf.DUMMYFUNCTION("IF(ISBLANK(B28), 0, GOOGLEFINANCE(IF(ISBLANK(C28), B28, C28&"":""&B28), ""price""))"),19.1) -> 19.1 | F28: =IFERROR(__xludf.DUMMYFUNCTION("IF(ISBLANK(B28), 0, GOOGLEFINANCE(IF(ISBLANK(C28), B28, C28&"":""&B28), ""change""))"),0.25) -> 0.25 | G28: =IFERROR(__xludf.DUMMYFUNCTION("IF(ISBLANK(B28), 0, GOOGLEFINANCE(IF(ISBLANK(C28), B28, C28&"":""&B28), ""changepct"")/100)"),0.013300000000000001) -> 0.0133 | H28: 45 | I28: =H28 * E28 -> 859.5 | J28: =I28/$I$3 -> 0.00022012491 | K28: 24.8 | L28: =H28*K28 -> 1116 | M28: =I28-L28 -> -256.5 | N28: =IF(H28=0,0,IF(L28=0,1,(M28+P28+Q28+R28+S28)/L28*100%)) -> -0.22983871 | O28: 工業 | V28: 43133 | W28: =DAYS(TODAY(),V28) -> 3039
B29: SCHD | D29: =IFERROR(__xludf.DUMMYFUNCTION("IF(ISBLANK(B29), ""-"", GOOGLEFINANCE(IF(ISBLANK(C29), B29, C29&"":""&B29), ""name""))"),"Schwab US Dividend Equity ETF") -> Schwab US Dividend Equity ETF | E29: =IFERROR(__xludf.DUMMYFUNCTION("IF(ISBLANK(B29), 0, GOOGLEFINANCE(IF(ISBLANK(C29), B29, C29&"":""&B29), ""price""))"),32.5) -> 32.5 | F29: =IFERROR(__xludf.DUMMYFUNCTION("IF(ISBLANK(B29), 0, GOOGLEFINANCE(IF(ISBLANK(C29), B29, C29&"":""&B29), ""change""))*$E$3"),-4.085484000000001) -> -4.085484 | G29: =IFERROR(__xludf.DUMMYFUNCTION("IF(ISBLANK(B29), 0, GOOGLEFINANCE(IF(ISBLANK(C29), B29, C29&"":""&B29), ""changepct"")/100)"),-0.004) -> -0.004 | H29: =21.6612-21.6612 -> 0 | I29: =H29 * E29*$E$3 -> 0 | J29: =I29/$I$3 -> 0 | K29: =24.33 -> 24.33 | L29: =H29*K29*$E$3 -> 0 | M29: =I29-L29 -> 0 | N29: =IF(H29=0,0,IF(L29=0,1,(M29+P29+Q29+R29+S29)/L29*100%)) -> 0 | O29: 高股息型ETF | V29: 45068 | W29: =DAYS(TODAY(),V29) -> 1104
B30: TPE:00713 | D30: 00713 | E30: =IFERROR(__xludf.DUMMYFUNCTION("IF(ISBLANK(B30), 0, GOOGLEFINANCE(IF(ISBLANK(C30), B30, C30&"":""&B30), ""price""))"),56.55) -> 56.55 | F30: =IFERROR(__xludf.DUMMYFUNCTION("IF(ISBLANK(B30), 0, GOOGLEFINANCE(IF(ISBLANK(C30), B30, C30&"":""&B30), ""change""))"),0.8) -> 0.8 | G30: =IFERROR(__xludf.DUMMYFUNCTION("IF(ISBLANK(B30), 0, GOOGLEFINANCE(IF(ISBLANK(C30), B30, C30&"":""&B30), ""changepct"")/100)"),0.0143) -> 0.0143 | I30: =H30 * E30 -> 0 | J30: =I30/$I$3 -> 0 | K30: 53.4 | L30: =H30*K30 -> 0 | M30: =I30-L30 -> 0 | N30: =IF(H30=0,0,IF(L30=0,1,(M30+P30+Q30+R30+S30+T30)/L30*100%)) -> 0 | O30: 高股息型ETF | R30: 746 | S30: =1092+2495+3270+3563 -> 10420 | T30: =3976+3907+2900 -> 10783 | V30: 45261 | W30: =DAYS(TODAY(),V30) -> 911
B31: PL | D31: =IFERROR(__xludf.DUMMYFUNCTION("IF(ISBLANK(B31), ""-"", GOOGLEFINANCE(IF(ISBLANK(C31), B31, C31&"":""&B31), ""name""))"),"Planet Labs PBC") -> Planet Labs PBC | E31: =IFERROR(__xludf.DUMMYFUNCTION("IF(ISBLANK(B31), 0, GOOGLEFINANCE(IF(ISBLANK(C31), B31, C31&"":""&B31), ""price""))"),51.14) -> 51.14 | F31: =IFERROR(__xludf.DUMMYFUNCTION("IF(ISBLANK(B31), 0, GOOGLEFINANCE(IF(ISBLANK(C31), B31, C31&"":""&B31), ""change""))*$E$3"),-8.170968000000002) -> -8.170968 | G31: =IFERROR(__xludf.DUMMYFUNCTION("IF(ISBLANK(B31), 0, GOOGLEFINANCE(IF(ISBLANK(C31), B31, C31&"":""&B31), ""changepct"")/100)"),-0.0051) -> -0.0051 | I31: =H31 * E31*$E$3 -> 0 | J31: =I31/$I$3 -> 0 | K31: 8.1165 | L31: =H31*K31 *$E$3 -> 0 | M31: =I31-L31 -> 0 | N31: =IF(H31=0,0,IF(L31=0,1,(M31+P31+Q31+R31+S31)/L31*100%)) -> 0 | O31: 電子/科技 | W31: =DAYS(TODAY(),V31) -> 46172
B32: TPE:2317 | D32: 鴻海 | E32: =IFERROR(__xludf.DUMMYFUNCTION("IF(ISBLANK(B32), 0, GOOGLEFINANCE(IF(ISBLANK(C32), B32, C32&"":""&B32), ""price""))"),289.0) -> 289 | F32: =IFERROR(__xludf.DUMMYFUNCTION("IF(ISBLANK(B32), 0, GOOGLEFINANCE(IF(ISBLANK(C32), B32, C32&"":""&B32), ""change""))"),26.0) -> 26 | G32: =IFERROR(__xludf.DUMMYFUNCTION("IF(ISBLANK(B32), 0, GOOGLEFINANCE(IF(ISBLANK(C32), B32, C32&"":""&B32), ""changepct"")/100)"),0.0989) -> 0.0989 | I32: =H32 * E32 -> 0 | J32: =I32/$I$3 -> 0 | K32: 207 | L32: =H32*K32 -> 0 | M32: =I32-L32 -> 0 | N32: =IF(H32=0,0,IF(L32=0,1,(M32+P32+Q32+R32+T32)/L32*100%)) -> 0 | O32: 電子/科技 | T32: 2309 | V32: 45597 | W32: =DAYS(TODAY(),V32) -> 575
B33: TPE:2301 | D33: =IFERROR(__xludf.DUMMYFUNCTION("IF(ISBLANK(B33), ""-"", GOOGLEFINANCE(IF(ISBLANK(C33), B33, C33&"":""&B33), ""name""))"),"Lite-On Technology Corp") -> Lite-On Technology Corp | E33: =IFERROR(__xludf.DUMMYFUNCTION("IF(ISBLANK(B33), 0, GOOGLEFINANCE(IF(ISBLANK(C33), B33, C33&"":""&B33), ""price""))"),234.5) -> 234.5 | F33: =IFERROR(__xludf.DUMMYFUNCTION("IF(ISBLANK(B33), 0, GOOGLEFINANCE(IF(ISBLANK(C33), B33, C33&"":""&B33), ""change""))"),4.0) -> 4 | G33: =IFERROR(__xludf.DUMMYFUNCTION("IF(ISBLANK(B33), 0, GOOGLEFINANCE(IF(ISBLANK(C33), B33, C33&"":""&B33), ""changepct"")/100)"),0.0174) -> 0.0174 | I33: =H33 * E33 -> 0 | J33: =I33/$I$3 -> 0 | K33: =((((65.47*1012)+9413)/1112)*900+13900+14405+8643)/1200 -> 81.825504 | L33: =H33*K33 -> 0 | M33: =I33-L33 -> 0 | N33: =IF(H33=0,0,IF(L33=0,1,(M33+P33+Q33+R33+S33)/L33*100%)) -> 0 | O33: 電子/科技 | P33: 1990 | Q33: =1630+453 -> 2083 | R33: =2426+1990 -> 4416 | S33: =3002 -> 3002 | V33: 44432 | W33: 947天 2024/03/29平倉
B34: TSLY | D34: =IFERROR(__xludf.DUMMYFUNCTION("IF(ISBLANK(B34), ""-"", GOOGLEFINANCE(IF(ISBLANK(C34), B34, C34&"":""&B34), ""name""))"),"YieldMax TSLA Option Income Strategy ETF") -> YieldMax TSLA Option Income Strategy ETF | E34: =IFERROR(__xludf.DUMMYFUNCTION("IF(ISBLANK(B34), 0, GOOGLEFINANCE(IF(ISBLANK(C34), B34, C34&"":""&B34), ""price""))"),30.63) -> 30.63 | F34: =IFERROR(__xludf.DUMMYFUNCTION("IF(ISBLANK(B34), 0, GOOGLEFINANCE(IF(ISBLANK(C34), B34, C34&"":""&B34), ""change""))*$E$3"),-8.170968000000002) -> -8.170968 | G34: =IFERROR(__xludf.DUMMYFUNCTION("IF(ISBLANK(B34), 0, GOOGLEFINANCE(IF(ISBLANK(C34), B34, C34&"":""&B34), ""changepct"")/100)"),-0.0084) -> -0.0084 | I34: =H34 * E34*$E$3 -> 0 | J34: =I34/$I$3 -> 0 | K34: 26.6 | L34: =H34*K34 *$E$3 -> 0 | M34: =I34-L34 -> 0 | N34: =IF(H34=0,0,IF(L34=0,1,(M34+P34+Q34+R34+S34)/L34*100%)) -> 0 | O34: 高股息ETF | R34: =(8.19+8.0766+11.8755+12.2612+11.3071)*$E$3 -> 1625.0924 | S34: =(9.9225+10.7863)*$E$3 -> 650.81132 | V34: 45056 | W34: =DAYS(TODAY(),V34) -> 1116
B35: TPE:2891 | D35: =IFERROR(__xludf.DUMMYFUNCTION("IF(ISBLANK(B35), ""-"", GOOGLEFINANCE(IF(ISBLANK(C35), B35, C35&"":""&B35), ""name""))"),"CTBC Financial Holding Co Ltd") -> CTBC Financial Holding Co Ltd | E35: =IFERROR(__xludf.DUMMYFUNCTION("IF(ISBLANK(B35), 0, GOOGLEFINANCE(IF(ISBLANK(C35), B35, C35&"":""&B35), ""price""))"),60.5) -> 60.5 | F35: =IFERROR(__xludf.DUMMYFUNCTION("IF(ISBLANK(B35), 0, GOOGLEFINANCE(IF(ISBLANK(C35), B35, C35&"":""&B35), ""change""))"),1.2) -> 1.2 | G35: =IFERROR(__xludf.DUMMYFUNCTION("IF(ISBLANK(B35), 0, GOOGLEFINANCE(IF(ISBLANK(C35), B35, C35&"":""&B35), ""changepct"")/100)"),0.0202) -> 0.0202 | I35: =H35 * E35 -> 0 | J35: =I35/$I$3 -> 0 | K35: 24.87 | L35: =H35*K35 -> 0 | M35: =I35-L35 -> 0 | N35: =IF(H35=0,0,IF(L35=0,0,(M35+P35+Q35)/L35*100%)) -> 0 | O35: 金控 | V35: 45148 | W35: =DAYS(TODAY(),V35) -> 1024
B36: TPE:6257 | D36: =IFERROR(__xludf.DUMMYFUNCTION("IF(ISBLANK(B36), ""-"", GOOGLEFINANCE(IF(ISBLANK(C36), B36, C36&"":""&B36), ""name""))"),"Sigurd Microelectronics Corp") -> Sigurd Microelectronics Corp | E36: =IFERROR(__xludf.DUMMYFUNCTION("IF(ISBLANK(B36), 0, GOOGLEFINANCE(IF(ISBLANK(C36), B36, C36&"":""&B36), ""price""))"),227.5) -> 227.5 | F36: =IFERROR(__xludf.DUMMYFUNCTION("IF(ISBLANK(B36), 0, GOOGLEFINANCE(IF(ISBLANK(C36), B36, C36&"":""&B36), ""change""))"),-1.5) -> -1.5 | G36: =IFERROR(__xludf.DUMMYFUNCTION("IF(ISBLANK(B36), 0, GOOGLEFINANCE(IF(ISBLANK(C36), B36, C36&"":""&B36), ""changepct"")/100)"),-0.0066) -> -0.0066 | I36: =H36 * E36 -> 0 | J36: =I36/$I$3 -> 0 | K36: 49.519 | L36: =H36*K36 -> 0 | M36: =I36-L36 -> 0 | N36: =IF(H36=0,0,IF(L36=0,1,(M36+P36+Q36+R36)/L36*100%)) -> 0 | O36: 電子/科技 | V36: 44936 | W36: =DAYS(TODAY(),V36) -> 1236
B37: QYLD | D37: =IFERROR(__xludf.DUMMYFUNCTION("IF(ISBLANK(B37), ""-"", GOOGLEFINANCE(IF(ISBLANK(C37), B37, C37&"":""&B37), ""name""))"),"Global X NASDAQ 100 Covered Call ETF") -> Global X NASDAQ 100 Covered Call ETF | E37: =IFERROR(__xludf.DUMMYFUNCTION("IF(ISBLANK(B37), 0, GOOGLEFINANCE(IF(ISBLANK(C37), B37, C37&"":""&B37), ""price""))"),18.08) -> 18.08 | F37: =IFERROR(__xludf.DUMMYFUNCTION("IF(ISBLANK(B37), 0, GOOGLEFINANCE(IF(ISBLANK(C37), B37, C37&"":""&B37), ""change""))*$E$3"),0.9428040000000001) -> 0.942804 | G37: =IFERROR(__xludf.DUMMYFUNCTION("IF(ISBLANK(B37), 0, GOOGLEFINANCE(IF(ISBLANK(C37), B37, C37&"":""&B37), ""changepct"")/100)"),0.0017000000000000001) -> 0.0017 | H37: =QYLD!J8 -> 0 | I37: =H37 * E37*$E$3 -> 0 | J37: =I37/$I$3 -> 0 | K37: =QYLD!L8 -> 17.68 | L37: =H37*K37*$E$3 -> 0 | M37: =I37-L37 -> 0 | N37: =IF(H37=0,0,IF(L37=0,1,(M37+P37+Q37+R37)/L37*100%)) -> 0 | O37: 高股息ETF | Q37: =(19.45)*$E$3 -> 611.25126 | R37: =(4.75+4.68+4.73)*$E$3 -> 445.00349 | V37: 44729 | W37: =DAYS(TODAY(),V37) -> 1443
B38: ITOT | D38: =IFERROR(__xludf.DUMMYFUNCTION("IF(ISBLANK(B38), ""-"", GOOGLEFINANCE(IF(ISBLANK(C38), B38, C38&"":""&B38), ""name""))"),"iShares Core S&P Total US Stock Market ETF") -> iShares Core S&P Total US Stock Market ETF | E38: =IFERROR(__xludf.DUMMYFUNCTION("IF(ISBLANK(B38), 0, GOOGLEFINANCE(IF(ISBLANK(C38), B38, C38&"":""&B38), ""price""))"),165.48) -> 165.48 | F38: =IFERROR(__xludf.DUMMYFUNCTION("IF(ISBLANK(B38), 0, GOOGLEFINANCE(IF(ISBLANK(C38), B38, C38&"":""&B38), ""change""))*$E$3"),13.827792000000002) -> 13.827792 | G38: =IFERROR(__xludf.DUMMYFUNCTION("IF(ISBLANK(B38), 0, GOOGLEFINANCE(IF(ISBLANK(C38), B38, C38&"":""&B38), ""changepct"")/100)"),0.0027) -> 0.0027 | I38: =H38 * E38*$E$3 -> 0 | J38: =I38/$I$3 -> 0 | K38: =ITOT!L8 -> 90.998333 | L38: =H38*K38*$E$3 -> 0 | M38: =I38-L38 -> 0 | N38: =IF(H38=0,0,IF(L38=0,1,(M38+P38+Q38+R38)/L38*100%)) -> 0 | O38: =ITOT!N8 -> 指數ETF | Q38: =(1.13)*$E$3 -> 35.512284 | V38: 44781 | W38: =DAYS(TODAY(),V38) -> 1391
B39: TPE:0050 | D39: =IFERROR(__xludf.DUMMYFUNCTION("IF(ISBLANK(B39), ""-"", GOOGLEFINANCE(IF(ISBLANK(C39), B39, C39&"":""&B39), ""name""))"),"Yuanta/P-shares Taiwan Top 50 ETF") -> Yuanta/P-shares Taiwan Top 50 ETF | E39: =IFERROR(__xludf.DUMMYFUNCTION("IF(ISBLANK(B39), 0, GOOGLEFINANCE(IF(ISBLANK(C39), B39, C39&"":""&B39), ""price""))"),105.4) -> 105.4 | F39: =IFERROR(__xludf.DUMMYFUNCTION("IF(ISBLANK(B39), 0, GOOGLEFINANCE(IF(ISBLANK(C39), B39, C39&"":""&B39), ""change""))"),4.9) -> 4.9 | G39: =IFERROR(__xludf.DUMMYFUNCTION("IF(ISBLANK(B39), 0, GOOGLEFINANCE(IF(ISBLANK(C39), B39, C39&"":""&B39), ""changepct"")/100)"),0.048799999999999996) -> 0.0488 | H39: ='0050 元大台50'!J8 -> 0 | I39: =H39 * E39 -> 0 | J39: =I39/$I$3 -> 0 | K39: ='0050 元大台50'!L8 -> 128.01475 | L39: =H39*K39 -> 0 | M39: =I39-L39 -> 0 | N39: =IF(H39=0,0,IF(L39=0,1,(M39+P39+Q39+R39)/L39*100%)) -> 0 | O39: 指數ETF | P39: 83 | Q39: =1612+1251 -> 2863 | R39: =2590 -> 2590 | V39: 44308 | W39: =DAYS(TODAY(),V39) -> 1864
O41: =SUM(I29:I39)/E3 -> 0

Sheet Futrures Holdings
A2: Asset Type | B2: Underlying | C2: Futures Symbol | D2: Market | E2: Direction | F2: Contracts | G2: Multiplier | H2: Entry Price | I2: Current Price | J2: Notional Exposure | K2: Margin Used | L2: Unrealized P/L | M2: Realized P/L | N2: Net Exposure | O2: Expiry | P2: Strategy Tag | Q2: Currency | R2: FX Rate | S2: Notional Exposure (TWD) | T2: Margin Used (TWD) | U2: Unrealized P/L (TWD) | V2: Notes

Sheet Holding Funds

Sheet Option Tracker
A1: Type | B1: Open | C1: Expire | D1: Close | E1: Ticker | F1: Event | G1: Strike | H1: IV | I1: Qty | J1: Fill$ | K1: Close$ | L1: P/L | M1: Days | N1: ROI | O1: AROI | P1: Notes
A2: Sell | B2: 45789 | C2: 45807 | D2: 45807 | E2: NVO | F2: Put Spread | G2: 62/61 | H2: ? | I2: 1 | J2: 0.25 | K2: 0 | L2: =(J2-K2)*100*I2 -> 25 | M2: =D2-B2 -> 18 | N2: =L2/(100-L2) -> 0.33333333 | O2: =(1+N2)^(1/(M2/365))-1 -> 340.57017
A3: Sell | B3: 45804 | C3: 45806 | D3: 45806 | E3: SPY | F3: Put Spread | G3: 578/577 | H3: ? | I3: 1 | J3: 0.14 | K3: 0 | L3: =(J3-K3)*100*I3 -> 14 | M3: =D3-B3 -> 2 | N3: =L3/(100-L3) -> 0.1627907 | O3: =(1+N3)^(1/(M3/365))-1 -> 899565203721
A4: Sell | B4: 45807 | C4: 45811 | D4: 45811 | E4: SPY | F4: Put Spread | G4: 580/579 | H4: ? | I4: 1 | J4: 0.15 | K4: 0 | L4: =(J4-K4)*100*I4 -> 15 | M4: =D4-B4 -> 4 | N4: =L4/(100-L4) -> 0.17647059 | O4: =(1+N4)^(1/(M4/365))-1 -> 2757546.7
A5: Sell | B5: 45811 | C5: 45828 | D5: 45825 | E5: PEP | F5: IC | G5: 135/136|125/124 | H5: 0.248 | I5: 1 | J5: 0.33 | K5: 0.1 | L5: =(J5-K5)*100*I5 -> 23 | M5: =D5-B5 -> 14 | N5: =L5/(100-L5) -> 0.2987013 | O5: =(1+N5)^(1/(M5/365))-1 -> 909.64467 | P5: https://www.reddit.com/r/thetagang/s/r3P8jUIPaV
A6: Sell | B6: 45831 | C6: 45833 | D6: 45833 | E6: SPY | F6: IC | G6: 601/602|588/587 | H6: 0.2037 | I6: 1 | J6: 0.4 | K6: 1 | L6: =(J6-K6)*100*I6 -> -60 | M6: =D6-B6 -> 2 | N6: =L6/(100-L6) -> -0.375 | O6: =(1+N6)^(1/(M6/365))-1 -> -1 | P6: 不該在世界局勢不穩時(以伊戰爭停火)賣IC 容易被穿
A7: Sell | B7: 45852 | C7: 45856 | D7: 45856 | E7: SPY | F7: Put Spread | G7: 615/614 | H7: 0.1691 | I7: 1 | J7: 0.17 | K7: 0 | L7: =(J7-K7)*100*I7 -> 17 | M7: =D7-B7 -> 4 | N7: =L7/(100-L7) -> 0.20481928 | O7: =(1+N7)^(1/(M7/365))-1 -> 24217207 | P7: 點位Delta 20%
A8: Sell | B8: 45861 | C8: 45870 | D8: 45862 | E8: NVO | F8: Put Spread | G8: 65/64 | H8: 0.4686 | I8: 1 | J8: 0.1 | K8: 0.01 | L8: =(J8-K8)*100*I8 -> 9 | M8: =D8-B8 -> 1 | N8: =L8/(100-L8) -> 0.098901099
A9: Sell | B9: 45873 | C9: 45877 | D9: 45877 | E9: SPY | F9: Put Spread | G9: 620/619 | H9: 0.1681 | I9: 1 | J9: 0.17 | K9: 0 | L9: =(J9-K9)*100*I9 -> 17 | M9: =D9-B9 -> 4 | N9: =L9/(100-L9) -> 0.20481928 | P9: SPY打到震盪區間(620~625)故開倉
A10: Sell | B10: 45880 | C10: 45884 | D10: 45884 | E10: SPY | F10: Put Spread | G10: 626/625 | H10: 0.1607 | I10: 2 | J10: 0.11 | K10: 0 | L10: =(J10-K10)*100*I10 -> 22 | M10: =D10-B10 -> 4 | N10: =L10/(100-L10) -> 0.28205128 | P10: SPY碰觸上升線上緣有撐(636)故開倉
A11: Sell | B11: 45903 | C11: 45904 | D11: 45904 | E11: SPY | F11: Put Spread | G11: 637/636 | H11: 0.1736 | I11: 1 | J11: 0.12 | K11: 0 | L11: =(J11-K11)*100*I11 -> 12 | M11: =D11-B11 -> 1 | N11: =L11/(100-L11) -> 0.13636364
A12: Sell | B12: 45903 | C12: 45919 | D12: 45919 | E12: SPY | F12: Put Spread | G12: 625/624 | H12: 0.1736 | I12: 1 | J12: 0.15 | K12: 0 | L12: =(J12-K12)*100*I12 -> 15 | M12: =D12-B12 -> 16 | N12: =L12/(100-L12) -> 0.17647059
A13: Sell | B13: 45918 | C13: 45925 | D13: 45923 | E13: SPY | F13: Put Spread | G13: 653/654 | H13: 0.154 | I13: 1 | J13: 0.21 | K13: 0.03 | L13: =(J13-K13)*100*I13 -> 18 | M13: =D13-B13 -> 5 | N13: =L13/(100-L13) -> 0.2195122
A14: Sell | B14: 45966 | C14: 45968 | D14: 45968 | E14: SPY | F14: Put Spread | G14: 667/666 | H14: 0.1898 | I14: 1 | J14: 0.16 | K14: 0.57 | L14: =(J14-K14)*100*I14 -> -41 | M14: =D14-B14 -> 2 | N14: =L14/(100-L14) -> -0.29078014 | P14: 盤跌開倉
A15: Sell | B15: 45992 | C15: 46038 | D15: 46038 | E15: GRAB | F15: CSP | G15: 5 | H15: 0.5146 | I15: 1 | J15: 0.2 | K15: 5 | L15: =(J15-K15)*100*I15 -> -480 | M15: =D15-B15 -> 46 | N15: =L15/(100-L15) -> -0.82758621 | P15: Option Assigned
A16: Sell | B16: 46002 | C16: 46031 | D16: 46017 | E16: SPY | F16: Put Spread | G16: 658/656 | H16: 0.157 | I16: 1 | J16: 0.25 | K16: 0.05 | L16: =(J16-K16)*100*I16 -> 20 | M16: =D16-B16 -> 15 | N16: =L16/(100-L16) -> 0.25
A17: Sell | B17: 46021 | C17: 46038 | D17: 46038 | E17: NVO | F17: Put Spread | G17: 48/47 | H17: 0.446 | I17: 1 | J17: 0.14 | K17: 0 | L17: =(J17-K17)*100*I17 -> 14 | M17: =D17-B17 -> 17 | N17: =L17/(100-L17) -> 0.1627907
A18: Sell | B18: 46048 | C18: 46073 | D18: 46073 | E18: GRAB | F18: Covered Call | G18: 5 | H18: 0.4821 | I18: 1 | J18: 0.15 | K18: 0 | L18: =(J18-K18)*100*I18 -> 15 | M18: =D18-B18 -> 25 | N18: =L18/(100-L18) -> 0.17647059
A19: Sell | B19: 46050 | C19: 46052 | D19: 46051 | E19: STX | F19: Put Spread | G19: 395/392.5 | H19: 0.7498 | I19: 1 | J19: 0.45 | K19: 0.05 | L19: =(J19-K19)*100*I19 -> 40 | M19: =D19-B19 -> 1 | N19: =L19/(100-L19) -> 0.66666667
A20: Sell | B20: 46055 | C20: 46059 | D20: 46059 | E20: SPY | F20: Put Spread | G20: 679/677 | H20: 0.1685 | I20: 1 | J20: 0.3 | K20: 0.19 | L20: =(J20-K20)*100*I20 -> 11 | M20: =D20-B20 -> 4 | N20: =L20/(100-L20) -> 0.12359551
A21: Sell | B21: 46168 | C21: 46171 | D21: 46171 | E21: CRCL | F21: Put Spread | G21: 99/98 | H21: 0.91 | I21: 1 | J21: 0.2 | K21: 0.01 | L21: =(J21-K21)*100*I21 -> 19 | M21: =D21-B21 -> 3 | N21: =L21/(100-L21) -> 0.2345679
L22: =(J22-K22)*100*I22 -> 0 | M22: =D22-B22 -> 0 | N22: =L22/(100-L22) -> 0
L23: =(J23-K23)*100*I23 -> 0 | M23: =D23-B23 -> 0 | N23: =L23/(100-L23) -> 0
L24: =(J24-K24)*100*I24 -> 0 | M24: =D24-B24 -> 0 | N24: =L24/(100-L24) -> 0
L25: =(J25-K25)*100*I25 -> 0 | M25: =D25-B25 -> 0 | N25: =L25/(100-L25) -> 0
L26: =(J26-K26)*100*I26 -> 0 | M26: =D26-B26 -> 0 | N26: =L26/(100-L26) -> 0
L29: =SUM(L2:L26) -> -275

Sheet VTI
B2: VTI | C2: << enter a symbol
C3: << optionally, enter an exchange (ex: NASDAQ, NYSE)
B5: =IFERROR(__xludf.DUMMYFUNCTION("GOOGLEFINANCE(B16,""name"")"),"Vanguard Total Stock Market Index Fund ETF") -> Vanguard Total Stock Market Index Fund ETF | O5: 定期定額
B7: Current Price | D7: Change | E7: % Change | J7: 持有股數 | K7: 持有成本 | L7: 平均股價 | N7: 類型
B8: =IFERROR(__xludf.DUMMYFUNCTION("GOOGLEFINANCE(B16,""price"")"),372.54) -> 372.54 | D8: =IFERROR(__xludf.DUMMYFUNCTION("IFERROR(GOOGLEFINANCE(B16,""change""),""-"")"),0.88) -> 0.88 | E8: =IFERROR(__xludf.DUMMYFUNCTION("IFERROR(GOOGLEFINANCE(B16,""changepct"")/100,""-"")"),0.0024) -> 0.0024 | J8: =SUM(K26:K100) -> 17.30997 | K8: =SUM(N26:N100) -> 5325.6385 | L8: =K8/J8 -> 307.66307 | N8: 指數ETF
B11: Market Cap | C11: P/E Ratio | D11: Beta
B12: =IFERROR(__xludf.DUMMYFUNCTION("IFERROR(GOOGLEFINANCE(B16,""marketcap""),""-"")"),3.04915912875E11) -> 304915912875 | C12: =IFERROR(__xludf.DUMMYFUNCTION("IFERROR(GOOGLEFINANCE(B16,""pe""),""-"")"),"-") -> - | D12: =IFERROR(__xludf.DUMMYFUNCTION("IFERROR(GOOGLEFINANCE(B16,""beta""),""-"")"),"-") -> -
G13: 6 Months
B16: =IF(ISBLANK(B3),"",B3&":")&B2 -> VTI
J24: Transaction detail list
B25: =IFERROR(__xludf.DUMMYFUNCTION("GOOGLEFINANCE(B16, ""all"", EDATE(TODAY(), -LEFT(G13, FIND("" "", G13))), TODAY(), ""DAILY"")"),"Date") -> Date | C25: =IFERROR(__xludf.DUMMYFUNCTION("""COMPUTED_VALUE"""),"Open") -> Open | D25: =IFERROR(__xludf.DUMMYFUNCTION("""COMPUTED_VALUE"""),"High") -> High | E25: =IFERROR(__xludf.DUMMYFUNCTION("""COMPUTED_VALUE"""),"Low") -> Low | F25: =IFERROR(__xludf.DUMMYFUNCTION("""COMPUTED_VALUE"""),"Close") -> Close | G25: =IFERROR(__xludf.DUMMYFUNCTION("""COMPUTED_VALUE"""),"Volume") -> Volume | J25: Date | K25: Shares | L25: Prices | M25: Fee | N25: Cost | O25: Average Cost | P25: Note
B26: =IFERROR(__xludf.DUMMYFUNCTION("""COMPUTED_VALUE"""),45992.66666666667) -> 45992.667 | C26: =IFERROR(__xludf.DUMMYFUNCTION("""COMPUTED_VALUE"""),333.96) -> 333.96 | D26: =IFERROR(__xludf.DUMMYFUNCTION("""COMPUTED_VALUE"""),336.1) -> 336.1 | E26: =IFERROR(__xludf.DUMMYFUNCTION("""COMPUTED_VALUE"""),333.75) -> 333.75 | F26: =IFERROR(__xludf.DUMMYFUNCTION("""COMPUTED_VALUE"""),334.66) -> 334.66 | G26: =IFERROR(__xludf.DUMMYFUNCTION("""COMPUTED_VALUE"""),4270595.0) -> 4270595 | J26: 45162 | K26: 1 | L26: 217 | N26: =K26*L26+M26 -> 217 | O26: =N26/K26 -> 217
B27: =IFERROR(__xludf.DUMMYFUNCTION("""COMPUTED_VALUE"""),45993.66666666667) -> 45993.667 | C27: =IFERROR(__xludf.DUMMYFUNCTION("""COMPUTED_VALUE"""),335.65) -> 335.65 | D27: =IFERROR(__xludf.DUMMYFUNCTION("""COMPUTED_VALUE"""),336.36) -> 336.36 | E27: =IFERROR(__xludf.DUMMYFUNCTION("""COMPUTED_VALUE"""),334.18) -> 334.18 | F27: =IFERROR(__xludf.DUMMYFUNCTION("""COMPUTED_VALUE"""),335.06) -> 335.06 | G27: =IFERROR(__xludf.DUMMYFUNCTION("""COMPUTED_VALUE"""),2920009.0) -> 2920009 | J27: 45195 | K27: 0.003 | L27: 0 | M27: 0.56 | N27: =K27*L27+M27 -> 0.56 | O27: =SUM($N$26:N27)/SUM($K$26:K27) -> 216.90927
B28: =IFERROR(__xludf.DUMMYFUNCTION("""COMPUTED_VALUE"""),45994.66666666667) -> 45994.667 | C28: =IFERROR(__xludf.DUMMYFUNCTION("""COMPUTED_VALUE"""),334.76) -> 334.76 | D28: =IFERROR(__xludf.DUMMYFUNCTION("""COMPUTED_VALUE"""),337.07) -> 337.07 | E28: =IFERROR(__xludf.DUMMYFUNCTION("""COMPUTED_VALUE"""),334.41) -> 334.41 | F28: =IFERROR(__xludf.DUMMYFUNCTION("""COMPUTED_VALUE"""),336.56) -> 336.56 | G28: =IFERROR(__xludf.DUMMYFUNCTION("""COMPUTED_VALUE"""),3779878.0) -> 3779878 | J28: 45287 | K28: 0.003 | L28: 0 | M28: 0.7 | N28: =K28*L28+M28 -> 0.7 | O28: =SUM($N$26:N28)/SUM($K$26:K28) -> 216.95825
B29: =IFERROR(__xludf.DUMMYFUNCTION("""COMPUTED_VALUE"""),45995.66666666667) -> 45995.667 | C29: =IFERROR(__xludf.DUMMYFUNCTION("""COMPUTED_VALUE"""),337.24) -> 337.24 | D29: =IFERROR(__xludf.DUMMYFUNCTION("""COMPUTED_VALUE"""),337.34) -> 337.34 | E29: =IFERROR(__xludf.DUMMYFUNCTION("""COMPUTED_VALUE"""),335.59) -> 335.59 | F29: =IFERROR(__xludf.DUMMYFUNCTION("""COMPUTED_VALUE"""),337.09) -> 337.09 | G29: =IFERROR(__xludf.DUMMYFUNCTION("""COMPUTED_VALUE"""),3587799.0) -> 3587799 | J29: 45378 | K29: 0.002 | L29: 0 | M29: 0.64 | N29: =K29*L29+M29 -> 0.64 | O29: =SUM($N$26:N29)/SUM($K$26:K29) -> 217.1627
B30: =IFERROR(__xludf.DUMMYFUNCTION("""COMPUTED_VALUE"""),45996.66666666667) -> 45996.667 | C30: =IFERROR(__xludf.DUMMYFUNCTION("""COMPUTED_VALUE"""),337.57) -> 337.57 | D30: =IFERROR(__xludf.DUMMYFUNCTION("""COMPUTED_VALUE"""),338.96) -> 338.96 | E30: =IFERROR(__xludf.DUMMYFUNCTION("""COMPUTED_VALUE"""),337.03) -> 337.03 | F30: =IFERROR(__xludf.DUMMYFUNCTION("""COMPUTED_VALUE"""),337.56) -> 337.56 | G30: =IFERROR(__xludf.DUMMYFUNCTION("""COMPUTED_VALUE"""),3340543.0) -> 3340543 | J30: 45475 | K30: 0.0025 | L30: 0 | M30: 0.67 | N30: =K30*L30+M30 -> 0.67 | O30: =SUM($N$26:N30)/SUM($K$26:K30) -> 217.28847
B31: =IFERROR(__xludf.DUMMYFUNCTION("""COMPUTED_VALUE"""),45999.66666666667) -> 45999.667 | C31: =IFERROR(__xludf.DUMMYFUNCTION("""COMPUTED_VALUE"""),338.2) -> 338.2 | D31: =IFERROR(__xludf.DUMMYFUNCTION("""COMPUTED_VALUE"""),338.2) -> 338.2 | E31: =IFERROR(__xludf.DUMMYFUNCTION("""COMPUTED_VALUE"""),335.6) -> 335.6 | F31: =IFERROR(__xludf.DUMMYFUNCTION("""COMPUTED_VALUE"""),336.57) -> 336.57 | G31: =IFERROR(__xludf.DUMMYFUNCTION("""COMPUTED_VALUE"""),3532782.0) -> 3532782 | J31: 45540 | K31: 0.73533 | L31: 271.98772 | M31: 0.1 | N31: =K31*L31+M31 -> 200.10073 | O31: =SUM($N$26:N31)/SUM($K$26:K31) -> 240.38465
B32: =IFERROR(__xludf.DUMMYFUNCTION("""COMPUTED_VALUE"""),46000.66666666667) -> 46000.667 | C32: =IFERROR(__xludf.DUMMYFUNCTION("""COMPUTED_VALUE"""),336.28) -> 336.28 | D32: =IFERROR(__xludf.DUMMYFUNCTION("""COMPUTED_VALUE"""),337.55) -> 337.55 | E32: =IFERROR(__xludf.DUMMYFUNCTION("""COMPUTED_VALUE"""),336.07) -> 336.07 | F32: =IFERROR(__xludf.DUMMYFUNCTION("""COMPUTED_VALUE"""),336.23) -> 336.23 | G32: =IFERROR(__xludf.DUMMYFUNCTION("""COMPUTED_VALUE"""),3035694.0) -> 3035694 | J32: 45566 | K32: 0.0022 | L32: 0 | M32: 0.62 | O32: =SUM($N$26:N32)/SUM($K$26:K32) -> 240.08211
B33: =IFERROR(__xludf.DUMMYFUNCTION("""COMPUTED_VALUE"""),46001.66666666667) -> 46001.667 | C33: =IFERROR(__xludf.DUMMYFUNCTION("""COMPUTED_VALUE"""),336.12) -> 336.12 | D33: =IFERROR(__xludf.DUMMYFUNCTION("""COMPUTED_VALUE"""),339.59) -> 339.59 | E33: =IFERROR(__xludf.DUMMYFUNCTION("""COMPUTED_VALUE"""),335.5) -> 335.5 | F33: =IFERROR(__xludf.DUMMYFUNCTION("""COMPUTED_VALUE"""),338.73) -> 338.73 | G33: =IFERROR(__xludf.DUMMYFUNCTION("""COMPUTED_VALUE"""),5697052.0) -> 5697052 | J33: 45572 | K33: 0.70927 | L33: 281.98 | M33: 0.1 | N33: =K33*L33+M33 -> 200.09995 | O33: =SUM($N$26:N33)/SUM($K$26:K33) -> 252.21612
B34: =IFERROR(__xludf.DUMMYFUNCTION("""COMPUTED_VALUE"""),46002.66666666667) -> 46002.667 | C34: =IFERROR(__xludf.DUMMYFUNCTION("""COMPUTED_VALUE"""),337.88) -> 337.88 | D34: =IFERROR(__xludf.DUMMYFUNCTION("""COMPUTED_VALUE"""),339.94) -> 339.94 | E34: =IFERROR(__xludf.DUMMYFUNCTION("""COMPUTED_VALUE"""),336.44) -> 336.44 | F34: =IFERROR(__xludf.DUMMYFUNCTION("""COMPUTED_VALUE"""),339.87) -> 339.87 | G34: =IFERROR(__xludf.DUMMYFUNCTION("""COMPUTED_VALUE"""),3818952.0) -> 3818952 | J34: 45601 | K34: 0.70888 | L34: 282.1354 | M34: 0.1 | N34: =K34*L34+M34 -> 200.10014 | O34: =SUM($N$26:N34)/SUM($K$26:K34) -> 258.94637
B35: =IFERROR(__xludf.DUMMYFUNCTION("""COMPUTED_VALUE"""),46003.66666666667) -> 46003.667 | C35: =IFERROR(__xludf.DUMMYFUNCTION("""COMPUTED_VALUE"""),339.5) -> 339.5 | D35: =IFERROR(__xludf.DUMMYFUNCTION("""COMPUTED_VALUE"""),339.75) -> 339.75 | E35: =IFERROR(__xludf.DUMMYFUNCTION("""COMPUTED_VALUE"""),334.85) -> 334.85 | F35: =IFERROR(__xludf.DUMMYFUNCTION("""COMPUTED_VALUE"""),335.99) -> 335.99 | G35: =IFERROR(__xludf.DUMMYFUNCTION("""COMPUTED_VALUE"""),4258897.0) -> 4258897 | J35: 45631 | K35: 0.66099 | L35: 302.5775 | M35: 0.1 | N35: =K35*L35+M35 -> 200.1007 | O35: =SUM($N$26:N35)/SUM($K$26:K35) -> 266.50803
B36: =IFERROR(__xludf.DUMMYFUNCTION("""COMPUTED_VALUE"""),46006.66666666667) -> 46006.667 | C36: =IFERROR(__xludf.DUMMYFUNCTION("""COMPUTED_VALUE"""),337.98) -> 337.98 | D36: =IFERROR(__xludf.DUMMYFUNCTION("""COMPUTED_VALUE"""),338.0) -> 338 | E36: =IFERROR(__xludf.DUMMYFUNCTION("""COMPUTED_VALUE"""),334.68) -> 334.68 | F36: =IFERROR(__xludf.DUMMYFUNCTION("""COMPUTED_VALUE"""),335.33) -> 335.33 | G36: =IFERROR(__xludf.DUMMYFUNCTION("""COMPUTED_VALUE"""),3571852.0) -> 3571852 | J36: 45652 | K36: 0.0022 | L36: 0 | M36: 0.66 | N36: =K36*L36+M36 -> 0.66 | O36: =SUM($N$26:N36)/SUM($K$26:K36) -> 266.52727
B37: =IFERROR(__xludf.DUMMYFUNCTION("""COMPUTED_VALUE"""),46007.66666666667) -> 46007.667 | C37: =IFERROR(__xludf.DUMMYFUNCTION("""COMPUTED_VALUE"""),334.59) -> 334.59 | D37: =IFERROR(__xludf.DUMMYFUNCTION("""COMPUTED_VALUE"""),335.51) -> 335.51 | E37: =IFERROR(__xludf.DUMMYFUNCTION("""COMPUTED_VALUE"""),332.42) -> 332.42 | F37: =IFERROR(__xludf.DUMMYFUNCTION("""COMPUTED_VALUE"""),334.36) -> 334.36 | G37: =IFERROR(__xludf.DUMMYFUNCTION("""COMPUTED_VALUE"""),4129247.0) -> 4129247 | J37: 45663 | K37: 0.67756 | L37: 295.17544 | M37: 0.1 | N37: =K37*L37+M37 -> 200.09907 | O37: =SUM($N$26:N37)/SUM($K$26:K37) -> 270.85635
B38: =IFERROR(__xludf.DUMMYFUNCTION("""COMPUTED_VALUE"""),46008.66666666667) -> 46008.667 | C38: =IFERROR(__xludf.DUMMYFUNCTION("""COMPUTED_VALUE"""),334.92) -> 334.92 | D38: =IFERROR(__xludf.DUMMYFUNCTION("""COMPUTED_VALUE"""),335.2) -> 335.2 | E38: =IFERROR(__xludf.DUMMYFUNCTION("""COMPUTED_VALUE"""),330.63) -> 330.63 | F38: =IFERROR(__xludf.DUMMYFUNCTION("""COMPUTED_VALUE"""),330.71) -> 330.71 | G38: =IFERROR(__xludf.DUMMYFUNCTION("""COMPUTED_VALUE"""),3980310.0) -> 3980310 | J38: 45693 | K38: 0.67059 | L38: 298.24458 | M38: 0.1 | N38: =K38*L38+M38 -> 200.09983 | O38: =SUM($N$26:N38)/SUM($K$26:K38) -> 274.42297
B39: =IFERROR(__xludf.DUMMYFUNCTION("""COMPUTED_VALUE"""),46009.66666666667) -> 46009.667 | C39: =IFERROR(__xludf.DUMMYFUNCTION("""COMPUTED_VALUE"""),333.78) -> 333.78 | D39: =IFERROR(__xludf.DUMMYFUNCTION("""COMPUTED_VALUE"""),335.35) -> 335.35 | E39: =IFERROR(__xludf.DUMMYFUNCTION("""COMPUTED_VALUE"""),332.47) -> 332.47 | F39: =IFERROR(__xludf.DUMMYFUNCTION("""COMPUTED_VALUE"""),333.25) -> 333.25 | G39: =IFERROR(__xludf.DUMMYFUNCTION("""COMPUTED_VALUE"""),3347732.0) -> 3347732 | J39: 45721 | K39: 0.70377 | L39: 284.18547 | M39: 0.1 | N39: =K39*L39+M39 -> 200.10121 | O39: =SUM($N$26:N39)/SUM($K$26:K39) -> 275.60818
B40: =IFERROR(__xludf.DUMMYFUNCTION("""COMPUTED_VALUE"""),46010.66666666667) -> 46010.667 | C40: =IFERROR(__xludf.DUMMYFUNCTION("""COMPUTED_VALUE"""),334.37) -> 334.37 | D40: =IFERROR(__xludf.DUMMYFUNCTION("""COMPUTED_VALUE"""),336.59) -> 336.59 | E40: =IFERROR(__xludf.DUMMYFUNCTION("""COMPUTED_VALUE"""),334.21) -> 334.21 | F40: =IFERROR(__xludf.DUMMYFUNCTION("""COMPUTED_VALUE"""),336.22) -> 336.22 | G40: =IFERROR(__xludf.DUMMYFUNCTION("""COMPUTED_VALUE"""),4022606.0) -> 4022606 | J40: 45747 | K40: 0.0026 | L40: 0 | M40: 0.7 | N40: =K40*L40+M40 -> 0.7 | O40: =SUM($N$26:N40)/SUM($K$26:K40) -> 275.60536
B41: =IFERROR(__xludf.DUMMYFUNCTION("""COMPUTED_VALUE"""),46013.66666666667) -> 46013.667 | C41: =IFERROR(__xludf.DUMMYFUNCTION("""COMPUTED_VALUE"""),337.0) -> 337 | D41: =IFERROR(__xludf.DUMMYFUNCTION("""COMPUTED_VALUE"""),337.91) -> 337.91 | E41: =IFERROR(__xludf.DUMMYFUNCTION("""COMPUTED_VALUE"""),336.61) -> 336.61 | F41: =IFERROR(__xludf.DUMMYFUNCTION("""COMPUTED_VALUE"""),337.6) -> 337.6 | G41: =IFERROR(__xludf.DUMMYFUNCTION("""COMPUTED_VALUE"""),3782103.0) -> 3782103 | J41: 45782 | K41: 0.72293 | L41: 276.65022 | M41: 0.1 | N41: =K41*L41+M41 -> 200.09874 | O41: =SUM($N$26:N41)/SUM($K$26:K41) -> 275.73483
B42: =IFERROR(__xludf.DUMMYFUNCTION("""COMPUTED_VALUE"""),46014.66666666667) -> 46014.667 | C42: =IFERROR(__xludf.DUMMYFUNCTION("""COMPUTED_VALUE"""),337.0) -> 337 | D42: =IFERROR(__xludf.DUMMYFUNCTION("""COMPUTED_VALUE"""),338.83) -> 338.83 | E42: =IFERROR(__xludf.DUMMYFUNCTION("""COMPUTED_VALUE"""),337.0) -> 337 | F42: =IFERROR(__xludf.DUMMYFUNCTION("""COMPUTED_VALUE"""),338.72) -> 338.72 | G42: =IFERROR(__xludf.DUMMYFUNCTION("""COMPUTED_VALUE"""),3611146.0) -> 3611146 | J42: 45813 | K42: 0.68032 | L42: 293.98008 | M42: 0.1 | N42: =K42*L42+M42 -> 200.10053 | O42: =SUM($N$26:N42)/SUM($K$26:K42) -> 277.45191
B43: =IFERROR(__xludf.DUMMYFUNCTION("""COMPUTED_VALUE"""),46015.54166666667) -> 46015.542 | C43: =IFERROR(__xludf.DUMMYFUNCTION("""COMPUTED_VALUE"""),338.78) -> 338.78 | D43: =IFERROR(__xludf.DUMMYFUNCTION("""COMPUTED_VALUE"""),340.1) -> 340.1 | E43: =IFERROR(__xludf.DUMMYFUNCTION("""COMPUTED_VALUE"""),338.71) -> 338.71 | F43: =IFERROR(__xludf.DUMMYFUNCTION("""COMPUTED_VALUE"""),339.88) -> 339.88 | G43: =IFERROR(__xludf.DUMMYFUNCTION("""COMPUTED_VALUE"""),4006460.0) -> 4006460 | J43: 45840 | K43: 0.0021 | L43: 0 | M43: 0.65 | N43: =K43*L43+M43 -> 0.65 | O43: =SUM($N$26:N43)/SUM($K$26:K43) -> 277.46115
B44: =IFERROR(__xludf.DUMMYFUNCTION("""COMPUTED_VALUE"""),46017.66666666667) -> 46017.667 | C44: =IFERROR(__xludf.DUMMYFUNCTION("""COMPUTED_VALUE"""),340.14) -> 340.14 | D44: =IFERROR(__xludf.DUMMYFUNCTION("""COMPUTED_VALUE"""),340.33) -> 340.33 | E44: =IFERROR(__xludf.DUMMYFUNCTION("""COMPUTED_VALUE"""),339.17) -> 339.17 | F44: =IFERROR(__xludf.DUMMYFUNCTION("""COMPUTED_VALUE"""),339.67) -> 339.67 | G44: =IFERROR(__xludf.DUMMYFUNCTION("""COMPUTED_VALUE"""),3543603.0) -> 3543603 | J44: 45845 | K44: 0.97723 | L44: 306.9906 | M44: 0.1 | N44: =K44*L44+M44 -> 300.10042 | O44: =SUM($N$26:N44)/SUM($K$26:K44) -> 280.9641
B45: =IFERROR(__xludf.DUMMYFUNCTION("""COMPUTED_VALUE"""),46020.66666666667) -> 46020.667 | C45: =IFERROR(__xludf.DUMMYFUNCTION("""COMPUTED_VALUE"""),338.4) -> 338.4 | D45: =IFERROR(__xludf.DUMMYFUNCTION("""COMPUTED_VALUE"""),339.27) -> 339.27 | E45: =IFERROR(__xludf.DUMMYFUNCTION("""COMPUTED_VALUE"""),337.57) -> 337.57 | F45: =IFERROR(__xludf.DUMMYFUNCTION("""COMPUTED_VALUE"""),338.39) -> 338.39 | G45: =IFERROR(__xludf.DUMMYFUNCTION("""COMPUTED_VALUE"""),3795871.0) -> 3795871 | J45: 45874 | K45: 0.96506 | L45: 310.86039 | M45: 0.1 | N45: =K45*L45+M45 -> 300.09893 | O45: =SUM($N$26:N45)/SUM($K$26:K45) -> 284.10028
B46: =IFERROR(__xludf.DUMMYFUNCTION("""COMPUTED_VALUE"""),46021.66666666667) -> 46021.667 | C46: =IFERROR(__xludf.DUMMYFUNCTION("""COMPUTED_VALUE"""),338.39) -> 338.39 | D46: =IFERROR(__xludf.DUMMYFUNCTION("""COMPUTED_VALUE"""),338.78) -> 338.78 | E46: =IFERROR(__xludf.DUMMYFUNCTION("""COMPUTED_VALUE"""),337.75) -> 337.75 | F46: =IFERROR(__xludf.DUMMYFUNCTION("""COMPUTED_VALUE"""),337.85) -> 337.85 | G46: =IFERROR(__xludf.DUMMYFUNCTION("""COMPUTED_VALUE"""),3576246.0) -> 3576246 | J46: 45905 | K46: 0.93281 | L46: 321.61 | M46: 0.1 | N46: =K46*L46+M46 -> 300.10102 | O46: =SUM($N$26:N46)/SUM($K$26:K46) -> 287.55249
B47: =IFERROR(__xludf.DUMMYFUNCTION("""COMPUTED_VALUE"""),46022.66666666667) -> 46022.667 | C47: =IFERROR(__xludf.DUMMYFUNCTION("""COMPUTED_VALUE"""),338.04) -> 338.04 | D47: =IFERROR(__xludf.DUMMYFUNCTION("""COMPUTED_VALUE"""),338.13) -> 338.13 | E47: =IFERROR(__xludf.DUMMYFUNCTION("""COMPUTED_VALUE"""),335.22) -> 335.22 | F47: =IFERROR(__xludf.DUMMYFUNCTION("""COMPUTED_VALUE"""),335.27) -> 335.27 | G47: =IFERROR(__xludf.DUMMYFUNCTION("""COMPUTED_VALUE"""),3493687.0) -> 3493687 | J47: 45931 | K47: 0.002 | L47: 0 | M47: 0.64 | N47: =K47*L47+M47 -> 0.64 | O47: =SUM($N$26:N47)/SUM($K$26:K47) -> 287.55887
B48: =IFERROR(__xludf.DUMMYFUNCTION("""COMPUTED_VALUE"""),46024.66666666667) -> 46024.667 | C48: =IFERROR(__xludf.DUMMYFUNCTION("""COMPUTED_VALUE"""),337.15) -> 337.15 | D48: =IFERROR(__xludf.DUMMYFUNCTION("""COMPUTED_VALUE"""),337.74) -> 337.74 | E48: =IFERROR(__xludf.DUMMYFUNCTION("""COMPUTED_VALUE"""),334.6) -> 334.6 | F48: =IFERROR(__xludf.DUMMYFUNCTION("""COMPUTED_VALUE"""),336.31) -> 336.31 | G48: =IFERROR(__xludf.DUMMYFUNCTION("""COMPUTED_VALUE"""),5177284.0) -> 5177284 | J48: 45936 | K48: 0.90522 | L48: 331.40999 | M48: 0.1 | N48: =K48*L48+M48 -> 300.09895 | O48: =SUM($N$26:N48)/SUM($K$26:K48) -> 291.15321
B49: =IFERROR(__xludf.DUMMYFUNCTION("""COMPUTED_VALUE"""),46027.66666666667) -> 46027.667 | C49: =IFERROR(__xludf.DUMMYFUNCTION("""COMPUTED_VALUE"""),338.0) -> 338 | D49: =IFERROR(__xludf.DUMMYFUNCTION("""COMPUTED_VALUE"""),339.61) -> 339.61 | E49: =IFERROR(__xludf.DUMMYFUNCTION("""COMPUTED_VALUE"""),337.85) -> 337.85 | F49: =IFERROR(__xludf.DUMMYFUNCTION("""COMPUTED_VALUE"""),338.84) -> 338.84 | G49: =IFERROR(__xludf.DUMMYFUNCTION("""COMPUTED_VALUE"""),5442161.0) -> 5442161 | J49: 45966 | K49: 0.90408 | L49: 331.83 | M49: 0.1 | N49: =K49*L49+M49 -> 300.10087 | O49: =SUM($N$26:N49)/SUM($K$26:K49) -> 294.23238
B50: =IFERROR(__xludf.DUMMYFUNCTION("""COMPUTED_VALUE"""),46028.66666666667) -> 46028.667 | C50: =IFERROR(__xludf.DUMMYFUNCTION("""COMPUTED_VALUE"""),338.99) -> 338.99 | D50: =IFERROR(__xludf.DUMMYFUNCTION("""COMPUTED_VALUE"""),341.39) -> 341.39 | E50: =IFERROR(__xludf.DUMMYFUNCTION("""COMPUTED_VALUE"""),338.81) -> 338.81 | F50: =IFERROR(__xludf.DUMMYFUNCTION("""COMPUTED_VALUE"""),341.21) -> 341.21 | G50: =IFERROR(__xludf.DUMMYFUNCTION("""COMPUTED_VALUE"""),6054463.0) -> 6054463 | J50: 45996 | K50: 0.8887 | L50: 337.57002 | M50: 0.1 | N50: =K50*L50+M50 -> 300.09848 | O50: =SUM($N$26:N50)/SUM($K$26:K50) -> 297.23403
B51: =IFERROR(__xludf.DUMMYFUNCTION("""COMPUTED_VALUE"""),46029.66666666667) -> 46029.667 | C51: =IFERROR(__xludf.DUMMYFUNCTION("""COMPUTED_VALUE"""),341.36) -> 341.36 | D51: =IFERROR(__xludf.DUMMYFUNCTION("""COMPUTED_VALUE"""),342.08) -> 342.08 | E51: =IFERROR(__xludf.DUMMYFUNCTION("""COMPUTED_VALUE"""),339.88) -> 339.88 | F51: =IFERROR(__xludf.DUMMYFUNCTION("""COMPUTED_VALUE"""),340.05) -> 340.05 | G51: =IFERROR(__xludf.DUMMYFUNCTION("""COMPUTED_VALUE"""),6629562.0) -> 6629562 | J51: 46015 | K51: 0.002 | L51: 0 | M51: 0.71 | N51: =K51*L51+M51 -> 0.71 | O51: =SUM($N$26:N51)/SUM($K$26:K51) -> 297.24301
B52: =IFERROR(__xludf.DUMMYFUNCTION("""COMPUTED_VALUE"""),46030.66666666667) -> 46030.667 | C52: =IFERROR(__xludf.DUMMYFUNCTION("""COMPUTED_VALUE"""),339.77) -> 339.77 | D52: =IFERROR(__xludf.DUMMYFUNCTION("""COMPUTED_VALUE"""),340.75) -> 340.75 | E52: =IFERROR(__xludf.DUMMYFUNCTION("""COMPUTED_VALUE"""),339.09) -> 339.09 | F52: =IFERROR(__xludf.DUMMYFUNCTION("""COMPUTED_VALUE"""),340.14) -> 340.14 | G52: =IFERROR(__xludf.DUMMYFUNCTION("""COMPUTED_VALUE"""),6800029.0) -> 6800029 | J52: 46027 | K52: 0.88757 | L52: 338 | M52: 0.1 | N52: =K52*L52+M52 -> 300.09866 | O52: =SUM($N$26:N52)/SUM($K$26:K52) -> 299.88042
B53: =IFERROR(__xludf.DUMMYFUNCTION("""COMPUTED_VALUE"""),46031.66666666667) -> 46031.667 | C53: =IFERROR(__xludf.DUMMYFUNCTION("""COMPUTED_VALUE"""),340.85) -> 340.85 | D53: =IFERROR(__xludf.DUMMYFUNCTION("""COMPUTED_VALUE"""),342.94) -> 342.94 | E53: =IFERROR(__xludf.DUMMYFUNCTION("""COMPUTED_VALUE"""),340.0) -> 340 | F53: =IFERROR(__xludf.DUMMYFUNCTION("""COMPUTED_VALUE"""),342.4) -> 342.4 | G53: =IFERROR(__xludf.DUMMYFUNCTION("""COMPUTED_VALUE"""),6854092.0) -> 6854092 | J53: 46058 | K53: 0.89328 | L53: 335.8403 | M53: 0.1 | N53: =K53*L53+M53 -> 300.09942 | O53: =SUM($N$26:N53)/SUM($K$26:K53) -> 302.08031
B54: =IFERROR(__xludf.DUMMYFUNCTION("""COMPUTED_VALUE"""),46034.66666666667) -> 46034.667 | C54: =IFERROR(__xludf.DUMMYFUNCTION("""COMPUTED_VALUE"""),340.91) -> 340.91 | D54: =IFERROR(__xludf.DUMMYFUNCTION("""COMPUTED_VALUE"""),343.41) -> 343.41 | E54: =IFERROR(__xludf.DUMMYFUNCTION("""COMPUTED_VALUE"""),340.78) -> 340.78 | F54: =IFERROR(__xludf.DUMMYFUNCTION("""COMPUTED_VALUE"""),343.03) -> 343.03 | G54: =IFERROR(__xludf.DUMMYFUNCTION("""COMPUTED_VALUE"""),5775945.0) -> 5775945 | J54: 46086 | K54: 0.89132 | L54: 336.58133 | M54: 0.1 | N54: =K54*L54+M54 -> 300.10167 | O54: =SUM($N$26:N54)/SUM($K$26:K54) -> 304.06579
B55: =IFERROR(__xludf.DUMMYFUNCTION("""COMPUTED_VALUE"""),46035.66666666667) -> 46035.667 | C55: =IFERROR(__xludf.DUMMYFUNCTION("""COMPUTED_VALUE"""),343.4) -> 343.4 | D55: =IFERROR(__xludf.DUMMYFUNCTION("""COMPUTED_VALUE"""),343.54) -> 343.54 | E55: =IFERROR(__xludf.DUMMYFUNCTION("""COMPUTED_VALUE"""),341.26) -> 341.26 | F55: =IFERROR(__xludf.DUMMYFUNCTION("""COMPUTED_VALUE"""),342.34) -> 342.34 | G55: =IFERROR(__xludf.DUMMYFUNCTION("""COMPUTED_VALUE"""),8088126.0) -> 8088126 | J55: 46112 | K55: 0.0022 | L55: 0 | M55: 0.71 | N55: =K55*L55+M55 -> 0.71 | O55: =SUM($N$26:N55)/SUM($K$26:K55) -> 304.06843
B56: =IFERROR(__xludf.DUMMYFUNCTION("""COMPUTED_VALUE"""),46036.66666666667) -> 46036.667 | C56: =IFERROR(__xludf.DUMMYFUNCTION("""COMPUTED_VALUE"""),341.2) -> 341.2 | D56: =IFERROR(__xludf.DUMMYFUNCTION("""COMPUTED_VALUE"""),341.47) -> 341.47 | E56: =IFERROR(__xludf.DUMMYFUNCTION("""COMPUTED_VALUE"""),338.91) -> 338.91 | F56: =IFERROR(__xludf.DUMMYFUNCTION("""COMPUTED_VALUE"""),341.0) -> 341 | G56: =IFERROR(__xludf.DUMMYFUNCTION("""COMPUTED_VALUE"""),1.2154775E7) -> 12154775 | J56: 46118 | K56: 0.92607 | L56: 323.9503 | M56: 0.1 | N56: =K56*L56+M56 -> 300.10065 | O56: =SUM($N$26:N56)/SUM($K$26:K56) -> 305.19264
B57: =IFERROR(__xludf.DUMMYFUNCTION("""COMPUTED_VALUE"""),46037.66666666667) -> 46037.667 | C57: =IFERROR(__xludf.DUMMYFUNCTION("""COMPUTED_VALUE"""),343.01) -> 343.01 | D57: =IFERROR(__xludf.DUMMYFUNCTION("""COMPUTED_VALUE"""),343.67) -> 343.67 | E57: =IFERROR(__xludf.DUMMYFUNCTION("""COMPUTED_VALUE"""),341.68) -> 341.68 | F57: =IFERROR(__xludf.DUMMYFUNCTION("""COMPUTED_VALUE"""),342.05) -> 342.05 | G57: =IFERROR(__xludf.DUMMYFUNCTION("""COMPUTED_VALUE"""),8296861.0) -> 8296861 | J57: 46147 | K57: 0.84319 | L57: 355.78999 | M57: 0.1 | N57: =K57*L57+M57 -> 300.09856 | O57: =SUM($N$26:N57)/SUM($K$26:K57) -> 307.66307
B58: =IFERROR(__xludf.DUMMYFUNCTION("""COMPUTED_VALUE"""),46038.66666666667) -> 46038.667 | C58: =IFERROR(__xludf.DUMMYFUNCTION("""COMPUTED_VALUE"""),342.87) -> 342.87 | D58: =IFERROR(__xludf.DUMMYFUNCTION("""COMPUTED_VALUE"""),343.05) -> 343.05 | E58: =IFERROR(__xludf.DUMMYFUNCTION("""COMPUTED_VALUE"""),341.07) -> 341.07 | F58: =IFERROR(__xludf.DUMMYFUNCTION("""COMPUTED_VALUE"""),341.85) -> 341.85 | G58: =IFERROR(__xludf.DUMMYFUNCTION("""COMPUTED_VALUE"""),6418521.0) -> 6418521 | N58: =K58*L58+M58 -> 0 | O58: =SUM($N$26:N58)/SUM($K$26:K58) -> 307.66307
B59: =IFERROR(__xludf.DUMMYFUNCTION("""COMPUTED_VALUE"""),46042.66666666667) -> 46042.667 | C59: =IFERROR(__xludf.DUMMYFUNCTION("""COMPUTED_VALUE"""),336.72) -> 336.72 | D59: =IFERROR(__xludf.DUMMYFUNCTION("""COMPUTED_VALUE"""),338.63) -> 338.63 | E59: =IFERROR(__xludf.DUMMYFUNCTION("""COMPUTED_VALUE"""),334.67) -> 334.67 | F59: =IFERROR(__xludf.DUMMYFUNCTION("""COMPUTED_VALUE"""),335.11) -> 335.11 | G59: =IFERROR(__xludf.DUMMYFUNCTION("""COMPUTED_VALUE"""),1.3144324E7) -> 13144324 | N59: =K59*L59+M59 -> 0 | O59: =SUM($N$26:N59)/SUM($K$26:K59) -> 307.66307
B60: =IFERROR(__xludf.DUMMYFUNCTION("""COMPUTED_VALUE"""),46043.66666666667) -> 46043.667 | C60: =IFERROR(__xludf.DUMMYFUNCTION("""COMPUTED_VALUE"""),336.19) -> 336.19 | D60: =IFERROR(__xludf.DUMMYFUNCTION("""COMPUTED_VALUE"""),340.71) -> 340.71 | E60: =IFERROR(__xludf.DUMMYFUNCTION("""COMPUTED_VALUE"""),335.44) -> 335.44 | F60: =IFERROR(__xludf.DUMMYFUNCTION("""COMPUTED_VALUE"""),339.08) -> 339.08 | G60: =IFERROR(__xludf.DUMMYFUNCTION("""COMPUTED_VALUE"""),9761843.0) -> 9761843 | N60: =K60*L60+M60 -> 0 | O60: =SUM($N$26:N60)/SUM($K$26:K60) -> 307.66307
B61: =IFERROR(__xludf.DUMMYFUNCTION("""COMPUTED_VALUE"""),46044.66666666667) -> 46044.667 | C61: =IFERROR(__xludf.DUMMYFUNCTION("""COMPUTED_VALUE"""),341.47) -> 341.47 | D61: =IFERROR(__xludf.DUMMYFUNCTION("""COMPUTED_VALUE"""),342.01) -> 342.01 | E61: =IFERROR(__xludf.DUMMYFUNCTION("""COMPUTED_VALUE"""),339.99) -> 339.99 | F61: =IFERROR(__xludf.DUMMYFUNCTION("""COMPUTED_VALUE"""),340.87) -> 340.87 | G61: =IFERROR(__xludf.DUMMYFUNCTION("""COMPUTED_VALUE"""),5505899.0) -> 5505899 | N61: =K61*L61+M61 -> 0 | O61: =SUM($N$26:N61)/SUM($K$26:K61) -> 307.66307
B62: =IFERROR(__xludf.DUMMYFUNCTION("""COMPUTED_VALUE"""),46045.66666666667) -> 46045.667 | C62: =IFERROR(__xludf.DUMMYFUNCTION("""COMPUTED_VALUE"""),340.7) -> 340.7 | D62: =IFERROR(__xludf.DUMMYFUNCTION("""COMPUTED_VALUE"""),341.55) -> 341.55 | E62: =IFERROR(__xludf.DUMMYFUNCTION("""COMPUTED_VALUE"""),339.84) -> 339.84 | F62: =IFERROR(__xludf.DUMMYFUNCTION("""COMPUTED_VALUE"""),340.56) -> 340.56 | G62: =IFERROR(__xludf.DUMMYFUNCTION("""COMPUTED_VALUE"""),4905901.0) -> 4905901 | N62: =K62*L62+M62 -> 0 | O62: =SUM($N$26:N62)/SUM($K$26:K62) -> 307.66307
B63: =IFERROR(__xludf.DUMMYFUNCTION("""COMPUTED_VALUE"""),46048.66666666667) -> 46048.667 | C63: =IFERROR(__xludf.DUMMYFUNCTION("""COMPUTED_VALUE"""),341.15) -> 341.15 | D63: =IFERROR(__xludf.DUMMYFUNCTION("""COMPUTED_VALUE"""),342.67) -> 342.67 | E63: =IFERROR(__xludf.DUMMYFUNCTION("""COMPUTED_VALUE"""),340.8) -> 340.8 | F63: =IFERROR(__xludf.DUMMYFUNCTION("""COMPUTED_VALUE"""),342.03) -> 342.03 | G63: =IFERROR(__xludf.DUMMYFUNCTION("""COMPUTED_VALUE"""),4957219.0) -> 4957219 | N63: =K63*L63+M63 -> 0 | O63: =SUM($N$26:N63)/SUM($K$26:K63) -> 307.66307
B64: =IFERROR(__xludf.DUMMYFUNCTION("""COMPUTED_VALUE"""),46049.66666666667) -> 46049.667 | C64: =IFERROR(__xludf.DUMMYFUNCTION("""COMPUTED_VALUE"""),342.85) -> 342.85 | D64: =IFERROR(__xludf.DUMMYFUNCTION("""COMPUTED_VALUE"""),343.73) -> 343.73 | E64: =IFERROR(__xludf.DUMMYFUNCTION("""COMPUTED_VALUE"""),342.29) -> 342.29 | F64: =IFERROR(__xludf.DUMMYFUNCTION("""COMPUTED_VALUE"""),343.27) -> 343.27 | G64: =IFERROR(__xludf.DUMMYFUNCTION("""COMPUTED_VALUE"""),3689039.0) -> 3689039 | N64: =K64*L64+M64 -> 0 | O64: =SUM($N$26:N64)/SUM($K$26:K64) -> 307.66307
B65: =IFERROR(__xludf.DUMMYFUNCTION("""COMPUTED_VALUE"""),46050.66666666667) -> 46050.667 | C65: =IFERROR(__xludf.DUMMYFUNCTION("""COMPUTED_VALUE"""),344.06) -> 344.06 | D65: =IFERROR(__xludf.DUMMYFUNCTION("""COMPUTED_VALUE"""),344.42) -> 344.42 | E65: =IFERROR(__xludf.DUMMYFUNCTION("""COMPUTED_VALUE"""),342.32) -> 342.32 | F65: =IFERROR(__xludf.DUMMYFUNCTION("""COMPUTED_VALUE"""),343.08) -> 343.08 | G65: =IFERROR(__xludf.DUMMYFUNCTION("""COMPUTED_VALUE"""),5854752.0) -> 5854752 | N65: =K65*L65+M65 -> 0 | O65: =SUM($N$26:N65)/SUM($K$26:K65) -> 307.66307
B66: =IFERROR(__xludf.DUMMYFUNCTION("""COMPUTED_VALUE"""),46051.66666666667) -> 46051.667 | C66: =IFERROR(__xludf.DUMMYFUNCTION("""COMPUTED_VALUE"""),343.54) -> 343.54 | D66: =IFERROR(__xludf.DUMMYFUNCTION("""COMPUTED_VALUE"""),343.83) -> 343.83 | E66: =IFERROR(__xludf.DUMMYFUNCTION("""COMPUTED_VALUE"""),337.69) -> 337.69 | F66: =IFERROR(__xludf.DUMMYFUNCTION("""COMPUTED_VALUE"""),342.29) -> 342.29 | G66: =IFERROR(__xludf.DUMMYFUNCTION("""COMPUTED_VALUE"""),8936851.0) -> 8936851 | N66: =K66*L66+M66 -> 0 | O66: =SUM($N$26:N66)/SUM($K$26:K66) -> 307.66307
B67: =IFERROR(__xludf.DUMMYFUNCTION("""COMPUTED_VALUE"""),46052.66666666667) -> 46052.667 | C67: =IFERROR(__xludf.DUMMYFUNCTION("""COMPUTED_VALUE"""),340.79) -> 340.79 | D67: =IFERROR(__xludf.DUMMYFUNCTION("""COMPUTED_VALUE"""),342.04) -> 342.04 | E67: =IFERROR(__xludf.DUMMYFUNCTION("""COMPUTED_VALUE"""),338.36) -> 338.36 | F67: =IFERROR(__xludf.DUMMYFUNCTION("""COMPUTED_VALUE"""),340.57) -> 340.57 | G67: =IFERROR(__xludf.DUMMYFUNCTION("""COMPUTED_VALUE"""),9905765.0) -> 9905765 | N67: =K67*L67+M67 -> 0 | O67: =SUM($N$26:N67)/SUM($K$26:K67) -> 307.66307
B68: =IFERROR(__xludf.DUMMYFUNCTION("""COMPUTED_VALUE"""),46055.66666666667) -> 46055.667 | C68: =IFERROR(__xludf.DUMMYFUNCTION("""COMPUTED_VALUE"""),339.55) -> 339.55 | D68: =IFERROR(__xludf.DUMMYFUNCTION("""COMPUTED_VALUE"""),343.29) -> 343.29 | E68: =IFERROR(__xludf.DUMMYFUNCTION("""COMPUTED_VALUE"""),339.49) -> 339.49 | F68: =IFERROR(__xludf.DUMMYFUNCTION("""COMPUTED_VALUE"""),342.48) -> 342.48 | G68: =IFERROR(__xludf.DUMMYFUNCTION("""COMPUTED_VALUE"""),6024494.0) -> 6024494 | N68: =K68*L68+M68 -> 0 | O68: =SUM($N$26:N68)/SUM($K$26:K68) -> 307.66307
B69: =IFERROR(__xludf.DUMMYFUNCTION("""COMPUTED_VALUE"""),46056.66666666667) -> 46056.667 | C69: =IFERROR(__xludf.DUMMYFUNCTION("""COMPUTED_VALUE"""),343.02) -> 343.02 | D69: =IFERROR(__xludf.DUMMYFUNCTION("""COMPUTED_VALUE"""),343.4) -> 343.4 | E69: =IFERROR(__xludf.DUMMYFUNCTION("""COMPUTED_VALUE"""),336.91) -> 336.91 | F69: =IFERROR(__xludf.DUMMYFUNCTION("""COMPUTED_VALUE"""),339.85) -> 339.85 | G69: =IFERROR(__xludf.DUMMYFUNCTION("""COMPUTED_VALUE"""),9060918.0) -> 9060918 | J69: =TODAY() -> 46172 | L69: =B8 -> 372.54 | N69: =K69*L69+M69 -> 0 | O69: =SUM($N$26:N69)/SUM($K$26:K69) -> 307.66307
B70: =IFERROR(__xludf.DUMMYFUNCTION("""COMPUTED_VALUE"""),46057.66666666667) -> 46057.667 | C70: =IFERROR(__xludf.DUMMYFUNCTION("""COMPUTED_VALUE"""),340.38) -> 340.38 | D70: =IFERROR(__xludf.DUMMYFUNCTION("""COMPUTED_VALUE"""),340.94) -> 340.94 | E70: =IFERROR(__xludf.DUMMYFUNCTION("""COMPUTED_VALUE"""),335.93) -> 335.93 | F70: =IFERROR(__xludf.DUMMYFUNCTION("""COMPUTED_VALUE"""),338.25) -> 338.25 | G70: =IFERROR(__xludf.DUMMYFUNCTION("""COMPUTED_VALUE"""),8973461.0) -> 8973461
B71: =IFERROR(__xludf.DUMMYFUNCTION("""COMPUTED_VALUE"""),46058.66666666667) -> 46058.667 | C71: =IFERROR(__xludf.DUMMYFUNCTION("""COMPUTED_VALUE"""),335.84) -> 335.84 | D71: =IFERROR(__xludf.DUMMYFUNCTION("""COMPUTED_VALUE"""),337.23) -> 337.23 | E71: =IFERROR(__xludf.DUMMYFUNCTION("""COMPUTED_VALUE"""),333.19) -> 333.19 | F71: =IFERROR(__xludf.DUMMYFUNCTION("""COMPUTED_VALUE"""),333.9) -> 333.9 | G71: =IFERROR(__xludf.DUMMYFUNCTION("""COMPUTED_VALUE"""),8838501.0) -> 8838501
B72: =IFERROR(__xludf.DUMMYFUNCTION("""COMPUTED_VALUE"""),46059.66666666667) -> 46059.667 | C72: =IFERROR(__xludf.DUMMYFUNCTION("""COMPUTED_VALUE"""),336.07) -> 336.07 | D72: =IFERROR(__xludf.DUMMYFUNCTION("""COMPUTED_VALUE"""),341.7) -> 341.7 | E72: =IFERROR(__xludf.DUMMYFUNCTION("""COMPUTED_VALUE"""),335.97) -> 335.97 | F72: =IFERROR(__xludf.DUMMYFUNCTION("""COMPUTED_VALUE"""),340.96) -> 340.96 | G72: =IFERROR(__xludf.DUMMYFUNCTION("""COMPUTED_VALUE"""),5093784.0) -> 5093784
B73: =IFERROR(__xludf.DUMMYFUNCTION("""COMPUTED_VALUE"""),46062.66666666667) -> 46062.667 | C73: =IFERROR(__xludf.DUMMYFUNCTION("""COMPUTED_VALUE"""),340.37) -> 340.37 | D73: =IFERROR(__xludf.DUMMYFUNCTION("""COMPUTED_VALUE"""),343.51) -> 343.51 | E73: =IFERROR(__xludf.DUMMYFUNCTION("""COMPUTED_VALUE"""),339.8) -> 339.8 | F73: =IFERROR(__xludf.DUMMYFUNCTION("""COMPUTED_VALUE"""),342.64) -> 342.64 | G73: =IFERROR(__xludf.DUMMYFUNCTION("""COMPUTED_VALUE"""),4562333.0) -> 4562333
B74: =IFERROR(__xludf.DUMMYFUNCTION("""COMPUTED_VALUE"""),46063.66666666667) -> 46063.667 | C74: =IFERROR(__xludf.DUMMYFUNCTION("""COMPUTED_VALUE"""),343.15) -> 343.15 | D74: =IFERROR(__xludf.DUMMYFUNCTION("""COMPUTED_VALUE"""),343.93) -> 343.93 | E74: =IFERROR(__xludf.DUMMYFUNCTION("""COMPUTED_VALUE"""),341.55) -> 341.55 | F74: =IFERROR(__xludf.DUMMYFUNCTION("""COMPUTED_VALUE"""),341.8) -> 341.8 | G74: =IFERROR(__xludf.DUMMYFUNCTION("""COMPUTED_VALUE"""),3879358.0) -> 3879358
B75: =IFERROR(__xludf.DUMMYFUNCTION("""COMPUTED_VALUE"""),46064.66666666667) -> 46064.667 | C75: =IFERROR(__xludf.DUMMYFUNCTION("""COMPUTED_VALUE"""),343.95) -> 343.95 | D75: =IFERROR(__xludf.DUMMYFUNCTION("""COMPUTED_VALUE"""),344.3) -> 344.3 | E75: =IFERROR(__xludf.DUMMYFUNCTION("""COMPUTED_VALUE"""),339.92) -> 339.92 | F75: =IFERROR(__xludf.DUMMYFUNCTION("""COMPUTED_VALUE"""),341.47) -> 341.47 | G75: =IFERROR(__xludf.DUMMYFUNCTION("""COMPUTED_VALUE"""),5056582.0) -> 5056582
B76: =IFERROR(__xludf.DUMMYFUNCTION("""COMPUTED_VALUE"""),46065.66666666667) -> 46065.667 | C76: =IFERROR(__xludf.DUMMYFUNCTION("""COMPUTED_VALUE"""),342.69) -> 342.69 | D76: =IFERROR(__xludf.DUMMYFUNCTION("""COMPUTED_VALUE"""),343.33) -> 343.33 | E76: =IFERROR(__xludf.DUMMYFUNCTION("""COMPUTED_VALUE"""),335.63) -> 335.63 | F76: =IFERROR(__xludf.DUMMYFUNCTION("""COMPUTED_VALUE"""),336.01) -> 336.01 | G76: =IFERROR(__xludf.DUMMYFUNCTION("""COMPUTED_VALUE"""),7012468.0) -> 7012468
B77: =IFERROR(__xludf.DUMMYFUNCTION("""COMPUTED_VALUE"""),46066.66666666667) -> 46066.667 | C77: =IFERROR(__xludf.DUMMYFUNCTION("""COMPUTED_VALUE"""),336.61) -> 336.61 | D77: =IFERROR(__xludf.DUMMYFUNCTION("""COMPUTED_VALUE"""),338.98) -> 338.98 | E77: =IFERROR(__xludf.DUMMYFUNCTION("""COMPUTED_VALUE"""),334.27) -> 334.27 | F77: =IFERROR(__xludf.DUMMYFUNCTION("""COMPUTED_VALUE"""),336.65) -> 336.65 | G77: =IFERROR(__xludf.DUMMYFUNCTION("""COMPUTED_VALUE"""),8039375.0) -> 8039375
B78: =IFERROR(__xludf.DUMMYFUNCTION("""COMPUTED_VALUE"""),46070.66666666667) -> 46070.667 | C78: =IFERROR(__xludf.DUMMYFUNCTION("""COMPUTED_VALUE"""),335.94) -> 335.94 | D78: =IFERROR(__xludf.DUMMYFUNCTION("""COMPUTED_VALUE"""),338.18) -> 338.18 | E78: =IFERROR(__xludf.DUMMYFUNCTION("""COMPUTED_VALUE"""),333.57) -> 333.57 | F78: =IFERROR(__xludf.DUMMYFUNCTION("""COMPUTED_VALUE"""),337.07) -> 337.07 | G78: =IFERROR(__xludf.DUMMYFUNCTION("""COMPUTED_VALUE"""),7112291.0) -> 7112291
B79: =IFERROR(__xludf.DUMMYFUNCTION("""COMPUTED_VALUE"""),46071.66666666667) -> 46071.667 | C79: =IFERROR(__xludf.DUMMYFUNCTION("""COMPUTED_VALUE"""),337.89) -> 337.89 | D79: =IFERROR(__xludf.DUMMYFUNCTION("""COMPUTED_VALUE"""),340.37) -> 340.37 | E79: =IFERROR(__xludf.DUMMYFUNCTION("""COMPUTED_VALUE"""),337.06) -> 337.06 | F79: =IFERROR(__xludf.DUMMYFUNCTION("""COMPUTED_VALUE"""),338.83) -> 338.83 | G79: =IFERROR(__xludf.DUMMYFUNCTION("""COMPUTED_VALUE"""),5718303.0) -> 5718303
B80: =IFERROR(__xludf.DUMMYFUNCTION("""COMPUTED_VALUE"""),46072.66666666667) -> 46072.667 | C80: =IFERROR(__xludf.DUMMYFUNCTION("""COMPUTED_VALUE"""),337.73) -> 337.73 | D80: =IFERROR(__xludf.DUMMYFUNCTION("""COMPUTED_VALUE"""),338.88) -> 338.88 | E80: =IFERROR(__xludf.DUMMYFUNCTION("""COMPUTED_VALUE"""),336.6) -> 336.6 | F80: =IFERROR(__xludf.DUMMYFUNCTION("""COMPUTED_VALUE"""),338.19) -> 338.19 | G80: =IFERROR(__xludf.DUMMYFUNCTION("""COMPUTED_VALUE"""),4401624.0) -> 4401624
B81: =IFERROR(__xludf.DUMMYFUNCTION("""COMPUTED_VALUE"""),46073.66666666667) -> 46073.667 | C81: =IFERROR(__xludf.DUMMYFUNCTION("""COMPUTED_VALUE"""),336.99) -> 336.99 | D81: =IFERROR(__xludf.DUMMYFUNCTION("""COMPUTED_VALUE"""),340.71) -> 340.71 | E81: =IFERROR(__xludf.DUMMYFUNCTION("""COMPUTED_VALUE"""),336.82) -> 336.82 | F81: =IFERROR(__xludf.DUMMYFUNCTION("""COMPUTED_VALUE"""),340.27) -> 340.27 | G81: =IFERROR(__xludf.DUMMYFUNCTION("""COMPUTED_VALUE"""),7051498.0) -> 7051498
B82: =IFERROR(__xludf.DUMMYFUNCTION("""COMPUTED_VALUE"""),46076.66666666667) -> 46076.667 | C82: =IFERROR(__xludf.DUMMYFUNCTION("""COMPUTED_VALUE"""),339.5) -> 339.5 | D82: =IFERROR(__xludf.DUMMYFUNCTION("""COMPUTED_VALUE"""),340.46) -> 340.46 | E82: =IFERROR(__xludf.DUMMYFUNCTION("""COMPUTED_VALUE"""),335.44) -> 335.44 | F82: =IFERROR(__xludf.DUMMYFUNCTION("""COMPUTED_VALUE"""),336.46) -> 336.46 | G82: =IFERROR(__xludf.DUMMYFUNCTION("""COMPUTED_VALUE"""),1.0762617E7) -> 10762617
B83: =IFERROR(__xludf.DUMMYFUNCTION("""COMPUTED_VALUE"""),46077.66666666667) -> 46077.667 | C83: =IFERROR(__xludf.DUMMYFUNCTION("""COMPUTED_VALUE"""),336.35) -> 336.35 | D83: =IFERROR(__xludf.DUMMYFUNCTION("""COMPUTED_VALUE"""),339.62) -> 339.62 | E83: =IFERROR(__xludf.DUMMYFUNCTION("""COMPUTED_VALUE"""),335.49) -> 335.49 | F83: =IFERROR(__xludf.DUMMYFUNCTION("""COMPUTED_VALUE"""),339.21) -> 339.21 | G83: =IFERROR(__xludf.DUMMYFUNCTION("""COMPUTED_VALUE"""),3633370.0) -> 3633370
B84: =IFERROR(__xludf.DUMMYFUNCTION("""COMPUTED_VALUE"""),46078.66666666667) -> 46078.667 | C84: =IFERROR(__xludf.DUMMYFUNCTION("""COMPUTED_VALUE"""),340.6) -> 340.6 | D84: =IFERROR(__xludf.DUMMYFUNCTION("""COMPUTED_VALUE"""),342.13) -> 342.13 | E84: =IFERROR(__xludf.DUMMYFUNCTION("""COMPUTED_VALUE"""),340.32) -> 340.32 | F84: =IFERROR(__xludf.DUMMYFUNCTION("""COMPUTED_VALUE"""),341.83) -> 341.83 | G84: =IFERROR(__xludf.DUMMYFUNCTION("""COMPUTED_VALUE"""),3962740.0) -> 3962740
B85: =IFERROR(__xludf.DUMMYFUNCTION("""COMPUTED_VALUE"""),46079.66666666667) -> 46079.667 | C85: =IFERROR(__xludf.DUMMYFUNCTION("""COMPUTED_VALUE"""),342.0) -> 342 | D85: =IFERROR(__xludf.DUMMYFUNCTION("""COMPUTED_VALUE"""),342.13) -> 342.13 | E85: =IFERROR(__xludf.DUMMYFUNCTION("""COMPUTED_VALUE"""),337.9) -> 337.9 | F85: =IFERROR(__xludf.DUMMYFUNCTION("""COMPUTED_VALUE"""),340.49) -> 340.49 | G85: =IFERROR(__xludf.DUMMYFUNCTION("""COMPUTED_VALUE"""),4967288.0) -> 4967288
B86: =IFERROR(__xludf.DUMMYFUNCTION("""COMPUTED_VALUE"""),46080.66666666667) -> 46080.667 | C86: =IFERROR(__xludf.DUMMYFUNCTION("""COMPUTED_VALUE"""),337.33) -> 337.33 | D86: =IFERROR(__xludf.DUMMYFUNCTION("""COMPUTED_VALUE"""),338.99) -> 338.99 | E86: =IFERROR(__xludf.DUMMYFUNCTION("""COMPUTED_VALUE"""),336.49) -> 336.49 | F86: =IFERROR(__xludf.DUMMYFUNCTION("""COMPUTED_VALUE"""),338.77) -> 338.77 | G86: =IFERROR(__xludf.DUMMYFUNCTION("""COMPUTED_VALUE"""),6033108.0) -> 6033108
B87: =IFERROR(__xludf.DUMMYFUNCTION("""COMPUTED_VALUE"""),46083.66666666667) -> 46083.667 | C87: =IFERROR(__xludf.DUMMYFUNCTION("""COMPUTED_VALUE"""),335.01) -> 335.01 | D87: =IFERROR(__xludf.DUMMYFUNCTION("""COMPUTED_VALUE"""),340.13) -> 340.13 | E87: =IFERROR(__xludf.DUMMYFUNCTION("""COMPUTED_VALUE"""),334.69) -> 334.69 | F87: =IFERROR(__xludf.DUMMYFUNCTION("""COMPUTED_VALUE"""),339.12) -> 339.12 | G87: =IFERROR(__xludf.DUMMYFUNCTION("""COMPUTED_VALUE"""),7211859.0) -> 7211859
B88: =IFERROR(__xludf.DUMMYFUNCTION("""COMPUTED_VALUE"""),46084.66666666667) -> 46084.667 | C88: =IFERROR(__xludf.DUMMYFUNCTION("""COMPUTED_VALUE"""),333.08) -> 333.08 | D88: =IFERROR(__xludf.DUMMYFUNCTION("""COMPUTED_VALUE"""),337.0) -> 337 | E88: =IFERROR(__xludf.DUMMYFUNCTION("""COMPUTED_VALUE"""),330.19) -> 330.19 | F88: =IFERROR(__xludf.DUMMYFUNCTION("""COMPUTED_VALUE"""),335.73) -> 335.73 | G88: =IFERROR(__xludf.DUMMYFUNCTION("""COMPUTED_VALUE"""),1.0735489E7) -> 10735489
B89: =IFERROR(__xludf.DUMMYFUNCTION("""COMPUTED_VALUE"""),46085.66666666667) -> 46085.667 | C89: =IFERROR(__xludf.DUMMYFUNCTION("""COMPUTED_VALUE"""),336.79) -> 336.79 | D89: =IFERROR(__xludf.DUMMYFUNCTION("""COMPUTED_VALUE"""),339.06) -> 339.06 | E89: =IFERROR(__xludf.DUMMYFUNCTION("""COMPUTED_VALUE"""),335.34) -> 335.34 | F89: =IFERROR(__xludf.DUMMYFUNCTION("""COMPUTED_VALUE"""),338.19) -> 338.19 | G89: =IFERROR(__xludf.DUMMYFUNCTION("""COMPUTED_VALUE"""),5448797.0) -> 5448797
B90: =IFERROR(__xludf.DUMMYFUNCTION("""COMPUTED_VALUE"""),46086.66666666667) -> 46086.667 | C90: =IFERROR(__xludf.DUMMYFUNCTION("""COMPUTED_VALUE"""),336.58) -> 336.58 | D90: =IFERROR(__xludf.DUMMYFUNCTION("""COMPUTED_VALUE"""),338.36) -> 338.36 | E90: =IFERROR(__xludf.DUMMYFUNCTION("""COMPUTED_VALUE"""),333.14) -> 333.14 | F90: =IFERROR(__xludf.DUMMYFUNCTION("""COMPUTED_VALUE"""),336.0) -> 336 | G90: =IFERROR(__xludf.DUMMYFUNCTION("""COMPUTED_VALUE"""),8658975.0) -> 8658975
B91: =IFERROR(__xludf.DUMMYFUNCTION("""COMPUTED_VALUE"""),46087.66666666667) -> 46087.667 | C91: =IFERROR(__xludf.DUMMYFUNCTION("""COMPUTED_VALUE"""),331.91) -> 331.91 | D91: =IFERROR(__xludf.DUMMYFUNCTION("""COMPUTED_VALUE"""),333.15) -> 333.15 | E91: =IFERROR(__xludf.DUMMYFUNCTION("""COMPUTED_VALUE"""),330.0) -> 330 | F91: =IFERROR(__xludf.DUMMYFUNCTION("""COMPUTED_VALUE"""),331.41) -> 331.41 | G91: =IFERROR(__xludf.DUMMYFUNCTION("""COMPUTED_VALUE"""),8621980.0) -> 8621980
B92: =IFERROR(__xludf.DUMMYFUNCTION("""COMPUTED_VALUE"""),46090.66666666667) -> 46090.667 | C92: =IFERROR(__xludf.DUMMYFUNCTION("""COMPUTED_VALUE"""),328.2) -> 328.2 | D92: =IFERROR(__xludf.DUMMYFUNCTION("""COMPUTED_VALUE"""),335.1) -> 335.1 | E92: =IFERROR(__xludf.DUMMYFUNCTION("""COMPUTED_VALUE"""),326.13) -> 326.13 | F92: =IFERROR(__xludf.DUMMYFUNCTION("""COMPUTED_VALUE"""),334.28) -> 334.28 | G92: =IFERROR(__xludf.DUMMYFUNCTION("""COMPUTED_VALUE"""),8379085.0) -> 8379085
B93: =IFERROR(__xludf.DUMMYFUNCTION("""COMPUTED_VALUE"""),46091.66666666667) -> 46091.667 | C93: =IFERROR(__xludf.DUMMYFUNCTION("""COMPUTED_VALUE"""),334.06) -> 334.06 | D93: =IFERROR(__xludf.DUMMYFUNCTION("""COMPUTED_VALUE"""),336.9) -> 336.9 | E93: =IFERROR(__xludf.DUMMYFUNCTION("""COMPUTED_VALUE"""),332.49) -> 332.49 | F93: =IFERROR(__xludf.DUMMYFUNCTION("""COMPUTED_VALUE"""),333.51) -> 333.51 | G93: =IFERROR(__xludf.DUMMYFUNCTION("""COMPUTED_VALUE"""),7761384.0) -> 7761384
B94: =IFERROR(__xludf.DUMMYFUNCTION("""COMPUTED_VALUE"""),46092.66666666667) -> 46092.667 | C94: =IFERROR(__xludf.DUMMYFUNCTION("""COMPUTED_VALUE"""),333.76) -> 333.76 | D94: =IFERROR(__xludf.DUMMYFUNCTION("""COMPUTED_VALUE"""),334.94) -> 334.94 | E94: =IFERROR(__xludf.DUMMYFUNCTION("""COMPUTED_VALUE"""),331.66) -> 331.66 | F94: =IFERROR(__xludf.DUMMYFUNCTION("""COMPUTED_VALUE"""),333.24) -> 333.24 | G94: =IFERROR(__xludf.DUMMYFUNCTION("""COMPUTED_VALUE"""),8631905.0) -> 8631905
B95: =IFERROR(__xludf.DUMMYFUNCTION("""COMPUTED_VALUE"""),46093.66666666667) -> 46093.667 | C95: =IFERROR(__xludf.DUMMYFUNCTION("""COMPUTED_VALUE"""),330.59) -> 330.59 | D95: =IFERROR(__xludf.DUMMYFUNCTION("""COMPUTED_VALUE"""),330.82) -> 330.82 | E95: =IFERROR(__xludf.DUMMYFUNCTION("""COMPUTED_VALUE"""),327.83) -> 327.83 | F95: =IFERROR(__xludf.DUMMYFUNCTION("""COMPUTED_VALUE"""),327.92) -> 327.92 | G95: =IFERROR(__xludf.DUMMYFUNCTION("""COMPUTED_VALUE"""),7011933.0) -> 7011933
B96: =IFERROR(__xludf.DUMMYFUNCTION("""COMPUTED_VALUE"""),46094.66666666667) -> 46094.667 | C96: =IFERROR(__xludf.DUMMYFUNCTION("""COMPUTED_VALUE"""),329.5) -> 329.5 | D96: =IFERROR(__xludf.DUMMYFUNCTION("""COMPUTED_VALUE"""),331.1) -> 331.1 | E96: =IFERROR(__xludf.DUMMYFUNCTION("""COMPUTED_VALUE"""),325.67) -> 325.67 | F96: =IFERROR(__xludf.DUMMYFUNCTION("""COMPUTED_VALUE"""),326.13) -> 326.13 | G96: =IFERROR(__xludf.DUMMYFUNCTION("""COMPUTED_VALUE"""),6294852.0) -> 6294852
B97: =IFERROR(__xludf.DUMMYFUNCTION("""COMPUTED_VALUE"""),46097.66666666667) -> 46097.667 | C97: =IFERROR(__xludf.DUMMYFUNCTION("""COMPUTED_VALUE"""),329.19) -> 329.19 | D97: =IFERROR(__xludf.DUMMYFUNCTION("""COMPUTED_VALUE"""),330.97) -> 330.97 | E97: =IFERROR(__xludf.DUMMYFUNCTION("""COMPUTED_VALUE"""),328.57) -> 328.57 | F97: =IFERROR(__xludf.DUMMYFUNCTION("""COMPUTED_VALUE"""),329.46) -> 329.46 | G97: =IFERROR(__xludf.DUMMYFUNCTION("""COMPUTED_VALUE"""),3766899.0) -> 3766899
B98: =IFERROR(__xludf.DUMMYFUNCTION("""COMPUTED_VALUE"""),46098.66666666667) -> 46098.667 | C98: =IFERROR(__xludf.DUMMYFUNCTION("""COMPUTED_VALUE"""),331.07) -> 331.07 | D98: =IFERROR(__xludf.DUMMYFUNCTION("""COMPUTED_VALUE"""),332.32) -> 332.32 | E98: =IFERROR(__xludf.DUMMYFUNCTION("""COMPUTED_VALUE"""),330.14) -> 330.14 | F98: =IFERROR(__xludf.DUMMYFUNCTION("""COMPUTED_VALUE"""),330.57) -> 330.57 | G98: =IFERROR(__xludf.DUMMYFUNCTION("""COMPUTED_VALUE"""),3181374.0) -> 3181374
B99: =IFERROR(__xludf.DUMMYFUNCTION("""COMPUTED_VALUE"""),46099.66666666667) -> 46099.667 | C99: =IFERROR(__xludf.DUMMYFUNCTION("""COMPUTED_VALUE"""),329.45) -> 329.45 | D99: =IFERROR(__xludf.DUMMYFUNCTION("""COMPUTED_VALUE"""),330.0) -> 330 | E99: =IFERROR(__xludf.DUMMYFUNCTION("""COMPUTED_VALUE"""),325.9) -> 325.9 | F99: =IFERROR(__xludf.DUMMYFUNCTION("""COMPUTED_VALUE"""),326.02) -> 326.02 | G99: =IFERROR(__xludf.DUMMYFUNCTION("""COMPUTED_VALUE"""),3919432.0) -> 3919432
B100: =IFERROR(__xludf.DUMMYFUNCTION("""COMPUTED_VALUE"""),46100.66666666667) -> 46100.667 | C100: =IFERROR(__xludf.DUMMYFUNCTION("""COMPUTED_VALUE"""),324.12) -> 324.12 | D100: =IFERROR(__xludf.DUMMYFUNCTION("""COMPUTED_VALUE"""),327.01) -> 327.01 | E100: =IFERROR(__xludf.DUMMYFUNCTION("""COMPUTED_VALUE"""),322.76) -> 322.76 | F100: =IFERROR(__xludf.DUMMYFUNCTION("""COMPUTED_VALUE"""),325.44) -> 325.44 | G100: =IFERROR(__xludf.DUMMYFUNCTION("""COMPUTED_VALUE"""),5183144.0) -> 5183144
B101: =IFERROR(__xludf.DUMMYFUNCTION("""COMPUTED_VALUE"""),46101.66666666667) -> 46101.667 | C101: =IFERROR(__xludf.DUMMYFUNCTION("""COMPUTED_VALUE"""),324.75) -> 324.75 | D101: =IFERROR(__xludf.DUMMYFUNCTION("""COMPUTED_VALUE"""),324.99) -> 324.99 | E101: =IFERROR(__xludf.DUMMYFUNCTION("""COMPUTED_VALUE"""),318.57) -> 318.57 | F101: =IFERROR(__xludf.DUMMYFUNCTION("""COMPUTED_VALUE"""),320.34) -> 320.34 | G101: =IFERROR(__xludf.DUMMYFUNCTION("""COMPUTED_VALUE"""),6532894.0) -> 6532894
B102: =IFERROR(__xludf.DUMMYFUNCTION("""COMPUTED_VALUE"""),46104.66666666667) -> 46104.667 | C102: =IFERROR(__xludf.DUMMYFUNCTION("""COMPUTED_VALUE"""),325.02) -> 325.02 | D102: =IFERROR(__xludf.DUMMYFUNCTION("""COMPUTED_VALUE"""),327.85) -> 327.85 | E102: =IFERROR(__xludf.DUMMYFUNCTION("""COMPUTED_VALUE"""),323.47) -> 323.47 | F102: =IFERROR(__xludf.DUMMYFUNCTION("""COMPUTED_VALUE"""),324.19) -> 324.19 | G102: =IFERROR(__xludf.DUMMYFUNCTION("""COMPUTED_VALUE"""),7888310.0) -> 7888310
B103: =IFERROR(__xludf.DUMMYFUNCTION("""COMPUTED_VALUE"""),46105.66666666667) -> 46105.667 | C103: =IFERROR(__xludf.DUMMYFUNCTION("""COMPUTED_VALUE"""),321.66) -> 321.66 | D103: =IFERROR(__xludf.DUMMYFUNCTION("""COMPUTED_VALUE"""),325.13) -> 325.13 | E103: =IFERROR(__xludf.DUMMYFUNCTION("""COMPUTED_VALUE"""),321.35) -> 321.35 | F103: =IFERROR(__xludf.DUMMYFUNCTION("""COMPUTED_VALUE"""),323.18) -> 323.18 | G103: =IFERROR(__xludf.DUMMYFUNCTION("""COMPUTED_VALUE"""),4382400.0) -> 4382400
B104: =IFERROR(__xludf.DUMMYFUNCTION("""COMPUTED_VALUE"""),46106.66666666667) -> 46106.667 | C104: =IFERROR(__xludf.DUMMYFUNCTION("""COMPUTED_VALUE"""),326.13) -> 326.13 | D104: =IFERROR(__xludf.DUMMYFUNCTION("""COMPUTED_VALUE"""),327.2) -> 327.2 | E104: =IFERROR(__xludf.DUMMYFUNCTION("""COMPUTED_VALUE"""),323.72) -> 323.72 | F104: =IFERROR(__xludf.DUMMYFUNCTION("""COMPUTED_VALUE"""),325.15) -> 325.15 | G104: =IFERROR(__xludf.DUMMYFUNCTION("""COMPUTED_VALUE"""),3625552.0) -> 3625552
B105: =IFERROR(__xludf.DUMMYFUNCTION("""COMPUTED_VALUE"""),46107.66666666667) -> 46107.667 | C105: =IFERROR(__xludf.DUMMYFUNCTION("""COMPUTED_VALUE"""),322.85) -> 322.85 | D105: =IFERROR(__xludf.DUMMYFUNCTION("""COMPUTED_VALUE"""),324.42) -> 324.42 | E105: =IFERROR(__xludf.DUMMYFUNCTION("""COMPUTED_VALUE"""),319.39) -> 319.39 | F105: =IFERROR(__xludf.DUMMYFUNCTION("""COMPUTED_VALUE"""),319.55) -> 319.55 | G105: =IFERROR(__xludf.DUMMYFUNCTION("""COMPUTED_VALUE"""),4794445.0) -> 4794445
B106: =IFERROR(__xludf.DUMMYFUNCTION("""COMPUTED_VALUE"""),46108.66666666667) -> 46108.667 | C106: =IFERROR(__xludf.DUMMYFUNCTION("""COMPUTED_VALUE"""),317.27) -> 317.27 | D106: =IFERROR(__xludf.DUMMYFUNCTION("""COMPUTED_VALUE"""),317.47) -> 317.47 | E106: =IFERROR(__xludf.DUMMYFUNCTION("""COMPUTED_VALUE"""),312.5) -> 312.5 | F106: =IFERROR(__xludf.DUMMYFUNCTION("""COMPUTED_VALUE"""),313.09) -> 313.09 | G106: =IFERROR(__xludf.DUMMYFUNCTION("""COMPUTED_VALUE"""),7027267.0) -> 7027267
B107: =IFERROR(__xludf.DUMMYFUNCTION("""COMPUTED_VALUE"""),46111.66666666667) -> 46111.667 | C107: =IFERROR(__xludf.DUMMYFUNCTION("""COMPUTED_VALUE"""),315.9) -> 315.9 | D107: =IFERROR(__xludf.DUMMYFUNCTION("""COMPUTED_VALUE"""),316.0) -> 316 | E107: =IFERROR(__xludf.DUMMYFUNCTION("""COMPUTED_VALUE"""),310.4) -> 310.4 | F107: =IFERROR(__xludf.DUMMYFUNCTION("""COMPUTED_VALUE"""),311.68) -> 311.68 | G107: =IFERROR(__xludf.DUMMYFUNCTION("""COMPUTED_VALUE"""),6510922.0) -> 6510922
B108: =IFERROR(__xludf.DUMMYFUNCTION("""COMPUTED_VALUE"""),46112.66666666667) -> 46112.667 | C108: =IFERROR(__xludf.DUMMYFUNCTION("""COMPUTED_VALUE"""),315.35) -> 315.35 | D108: =IFERROR(__xludf.DUMMYFUNCTION("""COMPUTED_VALUE"""),321.52) -> 321.52 | E108: =IFERROR(__xludf.DUMMYFUNCTION("""COMPUTED_VALUE"""),314.75) -> 314.75 | F108: =IFERROR(__xludf.DUMMYFUNCTION("""COMPUTED_VALUE"""),320.81) -> 320.81 | G108: =IFERROR(__xludf.DUMMYFUNCTION("""COMPUTED_VALUE"""),6764033.0) -> 6764033
B109: =IFERROR(__xludf.DUMMYFUNCTION("""COMPUTED_VALUE"""),46113.66666666667) -> 46113.667 | C109: =IFERROR(__xludf.DUMMYFUNCTION("""COMPUTED_VALUE"""),322.91) -> 322.91 | D109: =IFERROR(__xludf.DUMMYFUNCTION("""COMPUTED_VALUE"""),325.09) -> 325.09 | E109: =IFERROR(__xludf.DUMMYFUNCTION("""COMPUTED_VALUE"""),322.28) -> 322.28 | F109: =IFERROR(__xludf.DUMMYFUNCTION("""COMPUTED_VALUE"""),323.24) -> 323.24 | G109: =IFERROR(__xludf.DUMMYFUNCTION("""COMPUTED_VALUE"""),5540502.0) -> 5540502
B110: =IFERROR(__xludf.DUMMYFUNCTION("""COMPUTED_VALUE"""),46114.66666666667) -> 46114.667 | C110: =IFERROR(__xludf.DUMMYFUNCTION("""COMPUTED_VALUE"""),318.97) -> 318.97 | D110: =IFERROR(__xludf.DUMMYFUNCTION("""COMPUTED_VALUE"""),324.9) -> 324.9 | E110: =IFERROR(__xludf.DUMMYFUNCTION("""COMPUTED_VALUE"""),318.23) -> 318.23 | F110: =IFERROR(__xludf.DUMMYFUNCTION("""COMPUTED_VALUE"""),323.76) -> 323.76 | G110: =IFERROR(__xludf.DUMMYFUNCTION("""COMPUTED_VALUE"""),3653372.0) -> 3653372
B111: =IFERROR(__xludf.DUMMYFUNCTION("""COMPUTED_VALUE"""),46118.66666666667) -> 46118.667 | C111: =IFERROR(__xludf.DUMMYFUNCTION("""COMPUTED_VALUE"""),323.95) -> 323.95 | D111: =IFERROR(__xludf.DUMMYFUNCTION("""COMPUTED_VALUE"""),325.62) -> 325.62 | E111: =IFERROR(__xludf.DUMMYFUNCTION("""COMPUTED_VALUE"""),323.58) -> 323.58 | F111: =IFERROR(__xludf.DUMMYFUNCTION("""COMPUTED_VALUE"""),325.21) -> 325.21 | G111: =IFERROR(__xludf.DUMMYFUNCTION("""COMPUTED_VALUE"""),4401880.0) -> 4401880
B112: =IFERROR(__xludf.DUMMYFUNCTION("""COMPUTED_VALUE"""),46119.66666666667) -> 46119.667 | C112: =IFERROR(__xludf.DUMMYFUNCTION("""COMPUTED_VALUE"""),324.22) -> 324.22 | D112: =IFERROR(__xludf.DUMMYFUNCTION("""COMPUTED_VALUE"""),325.58) -> 325.58 | E112: =IFERROR(__xludf.DUMMYFUNCTION("""COMPUTED_VALUE"""),321.46) -> 321.46 | F112: =IFERROR(__xludf.DUMMYFUNCTION("""COMPUTED_VALUE"""),325.43) -> 325.43 | G112: =IFERROR(__xludf.DUMMYFUNCTION("""COMPUTED_VALUE"""),3567506.0) -> 3567506
B113: =IFERROR(__xludf.DUMMYFUNCTION("""COMPUTED_VALUE"""),46120.66666666667) -> 46120.667 | C113: =IFERROR(__xludf.DUMMYFUNCTION("""COMPUTED_VALUE"""),334.19) -> 334.19 | D113: =IFERROR(__xludf.DUMMYFUNCTION("""COMPUTED_VALUE"""),334.48) -> 334.48 | E113: =IFERROR(__xludf.DUMMYFUNCTION("""COMPUTED_VALUE"""),331.58) -> 331.58 | F113: =IFERROR(__xludf.DUMMYFUNCTION("""COMPUTED_VALUE"""),333.7) -> 333.7 | G113: =IFERROR(__xludf.DUMMYFUNCTION("""COMPUTED_VALUE"""),5384336.0) -> 5384336
B114: =IFERROR(__xludf.DUMMYFUNCTION("""COMPUTED_VALUE"""),46121.66666666667) -> 46121.667 | C114: =IFERROR(__xludf.DUMMYFUNCTION("""COMPUTED_VALUE"""),333.31) -> 333.31 | D114: =IFERROR(__xludf.DUMMYFUNCTION("""COMPUTED_VALUE"""),336.13) -> 336.13 | E114: =IFERROR(__xludf.DUMMYFUNCTION("""COMPUTED_VALUE"""),332.44) -> 332.44 | F114: =IFERROR(__xludf.DUMMYFUNCTION("""COMPUTED_VALUE"""),335.45) -> 335.45 | G114: =IFERROR(__xludf.DUMMYFUNCTION("""COMPUTED_VALUE"""),3436811.0) -> 3436811
...

Sheet 2330 台積電
B2: TPE:2330 | C2: << enter a symbol
C3: << optionally, enter an exchange (ex: NASDAQ, NYSE)
B5: =IFERROR(__xludf.DUMMYFUNCTION("GOOGLEFINANCE(B16,""name"")"),"Taiwan Semiconductor Manufacturng Co Ltd") -> Taiwan Semiconductor Manufacturng Co Ltd | O5: BUY
B7: Current Price | D7: Change | E7: % Change | J7: 持有股數 | K7: 持有成本 | L7: 平均股價 | N7: 類型
B8: =IFERROR(__xludf.DUMMYFUNCTION("GOOGLEFINANCE(B16,""price"")"),2355.0) -> 2355 | D8: =IFERROR(__xludf.DUMMYFUNCTION("IFERROR(GOOGLEFINANCE(B16,""change""),""-"")"),60.0) -> 60 | E8: =IFERROR(__xludf.DUMMYFUNCTION("IFERROR(GOOGLEFINANCE(B16,""changepct"")/100,""-"")"),0.026099999999999998) -> 0.0261 | J8: =SUM(K26:K100) -> 160 | K8: =SUM(N26:N100) -> 228561 | L8: =O43 -> 1428.5062 | N8: 電子/科技
B11: Market Cap | C11: P/E Ratio | D11: Beta
B12: =IFERROR(__xludf.DUMMYFUNCTION("IFERROR(GOOGLEFINANCE(B16,""marketcap""),""-"")"),1.867731125435E12) -> 1867731125435 | C12: =IFERROR(__xludf.DUMMYFUNCTION("IFERROR(GOOGLEFINANCE(B16,""pe""),""-"")"),31.19) -> 31.19 | D12: =IFERROR(__xludf.DUMMYFUNCTION("IFERROR(GOOGLEFINANCE(B16,""beta""),""-"")"),"-") -> -
G13: 6 Months
B16: =IF(ISBLANK(B3),"",B3&":")&B2 -> TPE:2330
J24: Transaction detail list
B25: =IFERROR(__xludf.DUMMYFUNCTION("GOOGLEFINANCE(B16, ""all"", EDATE(TODAY(), -LEFT(G13, FIND("" "", G13))), TODAY(), ""DAILY"")"),"Date") -> Date | C25: =IFERROR(__xludf.DUMMYFUNCTION("""COMPUTED_VALUE"""),"Open") -> Open | D25: =IFERROR(__xludf.DUMMYFUNCTION("""COMPUTED_VALUE"""),"High") -> High | E25: =IFERROR(__xludf.DUMMYFUNCTION("""COMPUTED_VALUE"""),"Low") -> Low | F25: =IFERROR(__xludf.DUMMYFUNCTION("""COMPUTED_VALUE"""),"Close") -> Close | G25: =IFERROR(__xludf.DUMMYFUNCTION("""COMPUTED_VALUE"""),"Volume") -> Volume | J25: Date | K25: Shares | L25: Prices | M25: Fee | N25: Cost | O25: Average Cost | P25: Note
B26: =IFERROR(__xludf.DUMMYFUNCTION("""COMPUTED_VALUE"""),45992.5625) -> 45992.562 | C26: =IFERROR(__xludf.DUMMYFUNCTION("""COMPUTED_VALUE"""),1445.0) -> 1445 | D26: =IFERROR(__xludf.DUMMYFUNCTION("""COMPUTED_VALUE"""),1445.0) -> 1445 | E26: =IFERROR(__xludf.DUMMYFUNCTION("""COMPUTED_VALUE"""),1410.0) -> 1410 | F26: =IFERROR(__xludf.DUMMYFUNCTION("""COMPUTED_VALUE"""),1410.0) -> 1410 | G26: =IFERROR(__xludf.DUMMYFUNCTION("""COMPUTED_VALUE"""),3.0559208E7) -> 30559208 | J26: 45846 | K26: 10 | L26: 1075 | M26: 4 | N26: =K26*L26+M26 -> 10754 | O26: =N26/K26 -> 1075.4
B27: =IFERROR(__xludf.DUMMYFUNCTION("""COMPUTED_VALUE"""),45993.5625) -> 45993.562 | C27: =IFERROR(__xludf.DUMMYFUNCTION("""COMPUTED_VALUE"""),1430.0) -> 1430 | D27: =IFERROR(__xludf.DUMMYFUNCTION("""COMPUTED_VALUE"""),1440.0) -> 1440 | E27: =IFERROR(__xludf.DUMMYFUNCTION("""COMPUTED_VALUE"""),1420.0) -> 1420 | F27: =IFERROR(__xludf.DUMMYFUNCTION("""COMPUTED_VALUE"""),1430.0) -> 1430 | G27: =IFERROR(__xludf.DUMMYFUNCTION("""COMPUTED_VALUE"""),2.3544477E7) -> 23544477 | J27: 45849 | K27: 10 | L27: 1095 | M27: 4 | N27: =K27*L27+M27 -> 10954 | O27: =SUM($N$26:N27)/SUM($K$26:K27) -> 1085.4
B28: =IFERROR(__xludf.DUMMYFUNCTION("""COMPUTED_VALUE"""),45994.5625) -> 45994.562 | C28: =IFERROR(__xludf.DUMMYFUNCTION("""COMPUTED_VALUE"""),1440.0) -> 1440 | D28: =IFERROR(__xludf.DUMMYFUNCTION("""COMPUTED_VALUE"""),1450.0) -> 1450 | E28: =IFERROR(__xludf.DUMMYFUNCTION("""COMPUTED_VALUE"""),1435.0) -> 1435 | F28: =IFERROR(__xludf.DUMMYFUNCTION("""COMPUTED_VALUE"""),1450.0) -> 1450 | G28: =IFERROR(__xludf.DUMMYFUNCTION("""COMPUTED_VALUE"""),2.030154E7) -> 20301540 | J28: 45856 | K28: 10 | L28: 1150 | M28: 4 | N28: =K28*L28+M28 -> 11504 | O28: =SUM($N$26:N28)/SUM($K$26:K28) -> 1107.0667
B29: =IFERROR(__xludf.DUMMYFUNCTION("""COMPUTED_VALUE"""),45995.5625) -> 45995.562 | C29: =IFERROR(__xludf.DUMMYFUNCTION("""COMPUTED_VALUE"""),1445.0) -> 1445 | D29: =IFERROR(__xludf.DUMMYFUNCTION("""COMPUTED_VALUE"""),1450.0) -> 1450 | E29: =IFERROR(__xludf.DUMMYFUNCTION("""COMPUTED_VALUE"""),1430.0) -> 1430 | F29: =IFERROR(__xludf.DUMMYFUNCTION("""COMPUTED_VALUE"""),1445.0) -> 1445 | G29: =IFERROR(__xludf.DUMMYFUNCTION("""COMPUTED_VALUE"""),2.0696944E7) -> 20696944 | J29: 45882 | K29: 5 | L29: 1190 | M29: 4 | N29: =K29*L29+M29 -> 5954 | O29: =SUM($N$26:N29)/SUM($K$26:K29) -> 1119.0286
B30: =IFERROR(__xludf.DUMMYFUNCTION("""COMPUTED_VALUE"""),45996.5625) -> 45996.562 | C30: =IFERROR(__xludf.DUMMYFUNCTION("""COMPUTED_VALUE"""),1445.0) -> 1445 | D30: =IFERROR(__xludf.DUMMYFUNCTION("""COMPUTED_VALUE"""),1460.0) -> 1460 | E30: =IFERROR(__xludf.DUMMYFUNCTION("""COMPUTED_VALUE"""),1440.0) -> 1440 | F30: =IFERROR(__xludf.DUMMYFUNCTION("""COMPUTED_VALUE"""),1460.0) -> 1460 | G30: =IFERROR(__xludf.DUMMYFUNCTION("""COMPUTED_VALUE"""),2.1072604E7) -> 21072604 | J30: 45889 | K30: 5 | L30: 1145 | M30: 4 | N30: =K30*L30+M30 -> 5729 | O30: =SUM($N$26:N30)/SUM($K$26:K30) -> 1122.375
B31: =IFERROR(__xludf.DUMMYFUNCTION("""COMPUTED_VALUE"""),45999.5625) -> 45999.562 | C31: =IFERROR(__xludf.DUMMYFUNCTION("""COMPUTED_VALUE"""),1465.0) -> 1465 | D31: =IFERROR(__xludf.DUMMYFUNCTION("""COMPUTED_VALUE"""),1495.0) -> 1495 | E31: =IFERROR(__xludf.DUMMYFUNCTION("""COMPUTED_VALUE"""),1460.0) -> 1460 | F31: =IFERROR(__xludf.DUMMYFUNCTION("""COMPUTED_VALUE"""),1495.0) -> 1495 | G31: =IFERROR(__xludf.DUMMYFUNCTION("""COMPUTED_VALUE"""),2.425726E7) -> 24257260 | J31: 45895 | K31: 10 | L31: 1170 | M31: 9 | N31: =K31*L31+M31 -> 11709 | O31: =SUM($N$26:N31)/SUM($K$26:K31) -> 1132.08
B32: =IFERROR(__xludf.DUMMYFUNCTION("""COMPUTED_VALUE"""),46000.5625) -> 46000.562 | C32: =IFERROR(__xludf.DUMMYFUNCTION("""COMPUTED_VALUE"""),1495.0) -> 1495 | D32: =IFERROR(__xludf.DUMMYFUNCTION("""COMPUTED_VALUE"""),1500.0) -> 1500 | E32: =IFERROR(__xludf.DUMMYFUNCTION("""COMPUTED_VALUE"""),1480.0) -> 1480 | F32: =IFERROR(__xludf.DUMMYFUNCTION("""COMPUTED_VALUE"""),1480.0) -> 1480 | G32: =IFERROR(__xludf.DUMMYFUNCTION("""COMPUTED_VALUE"""),2.4235825E7) -> 24235825 | J32: 45917 | K32: 10 | L32: 1270 | M32: 10 | N32: =K32*L32+M32 -> 12710 | O32: =SUM($N$26:N32)/SUM($K$26:K32) -> 1155.2333
B33: =IFERROR(__xludf.DUMMYFUNCTION("""COMPUTED_VALUE"""),46001.5625) -> 46001.562 | C33: =IFERROR(__xludf.DUMMYFUNCTION("""COMPUTED_VALUE"""),1490.0) -> 1490 | D33: =IFERROR(__xludf.DUMMYFUNCTION("""COMPUTED_VALUE"""),1505.0) -> 1505 | E33: =IFERROR(__xludf.DUMMYFUNCTION("""COMPUTED_VALUE"""),1485.0) -> 1485 | F33: =IFERROR(__xludf.DUMMYFUNCTION("""COMPUTED_VALUE"""),1505.0) -> 1505 | G33: =IFERROR(__xludf.DUMMYFUNCTION("""COMPUTED_VALUE"""),2.3319221E7) -> 23319221 | J33: 45918 | K33: 1 | L33: 1275 | M33: 1 | N33: =K33*L33+M33 -> 1276 | O33: =SUM($N$26:N33)/SUM($K$26:K33) -> 1157.2131
B34: =IFERROR(__xludf.DUMMYFUNCTION("""COMPUTED_VALUE"""),46002.5625) -> 46002.562 | C34: =IFERROR(__xludf.DUMMYFUNCTION("""COMPUTED_VALUE"""),1510.0) -> 1510 | D34: =IFERROR(__xludf.DUMMYFUNCTION("""COMPUTED_VALUE"""),1515.0) -> 1515 | E34: =IFERROR(__xludf.DUMMYFUNCTION("""COMPUTED_VALUE"""),1465.0) -> 1465 | F34: =IFERROR(__xludf.DUMMYFUNCTION("""COMPUTED_VALUE"""),1470.0) -> 1470 | G34: =IFERROR(__xludf.DUMMYFUNCTION("""COMPUTED_VALUE"""),2.8924982E7) -> 28924982 | J34: 45933 | K34: 10 | L34: 1390 | M34: 11 | N34: =K34*L34+M34 -> 13911 | O34: =SUM($N$26:N34)/SUM($K$26:K34) -> 1190.1549
B35: =IFERROR(__xludf.DUMMYFUNCTION("""COMPUTED_VALUE"""),46003.5625) -> 46003.562 | C35: =IFERROR(__xludf.DUMMYFUNCTION("""COMPUTED_VALUE"""),1475.0) -> 1475 | D35: =IFERROR(__xludf.DUMMYFUNCTION("""COMPUTED_VALUE"""),1485.0) -> 1485 | E35: =IFERROR(__xludf.DUMMYFUNCTION("""COMPUTED_VALUE"""),1470.0) -> 1470 | F35: =IFERROR(__xludf.DUMMYFUNCTION("""COMPUTED_VALUE"""),1480.0) -> 1480 | G35: =IFERROR(__xludf.DUMMYFUNCTION("""COMPUTED_VALUE"""),2.2107664E7) -> 22107664 | J35: 45943 | K35: 10 | L35: 1415 | M35: 11 | N35: =K35*L35+M35 -> 14161 | O35: =SUM($N$26:N35)/SUM($K$26:K35) -> 1218.0494
B36: =IFERROR(__xludf.DUMMYFUNCTION("""COMPUTED_VALUE"""),46006.5625) -> 46006.562 | C36: =IFERROR(__xludf.DUMMYFUNCTION("""COMPUTED_VALUE"""),1450.0) -> 1450 | D36: =IFERROR(__xludf.DUMMYFUNCTION("""COMPUTED_VALUE"""),1455.0) -> 1455 | E36: =IFERROR(__xludf.DUMMYFUNCTION("""COMPUTED_VALUE"""),1445.0) -> 1445 | F36: =IFERROR(__xludf.DUMMYFUNCTION("""COMPUTED_VALUE"""),1450.0) -> 1450 | G36: =IFERROR(__xludf.DUMMYFUNCTION("""COMPUTED_VALUE"""),2.5889058E7) -> 25889058 | J36: 45944 | K36: 9 | L36: 1450 | M36: 10 | N36: =K36*L36+M36 -> 13060 | O36: =SUM($N$26:N36)/SUM($K$26:K36) -> 1241.3556
B37: =IFERROR(__xludf.DUMMYFUNCTION("""COMPUTED_VALUE"""),46007.5625) -> 46007.562 | C37: =IFERROR(__xludf.DUMMYFUNCTION("""COMPUTED_VALUE"""),1435.0) -> 1435 | D37: =IFERROR(__xludf.DUMMYFUNCTION("""COMPUTED_VALUE"""),1445.0) -> 1445 | E37: =IFERROR(__xludf.DUMMYFUNCTION("""COMPUTED_VALUE"""),1425.0) -> 1425 | F37: =IFERROR(__xludf.DUMMYFUNCTION("""COMPUTED_VALUE"""),1435.0) -> 1435 | G37: =IFERROR(__xludf.DUMMYFUNCTION("""COMPUTED_VALUE"""),3.2168064E7) -> 32168064 | J37: 45959 | K37: 10 | L37: 1495 | M37: 11 | N37: =K37*L37+M37 -> 14961 | O37: =SUM($N$26:N37)/SUM($K$26:K37) -> 1266.83
B38: =IFERROR(__xludf.DUMMYFUNCTION("""COMPUTED_VALUE"""),46008.5625) -> 46008.562 | C38: =IFERROR(__xludf.DUMMYFUNCTION("""COMPUTED_VALUE"""),1435.0) -> 1435 | D38: =IFERROR(__xludf.DUMMYFUNCTION("""COMPUTED_VALUE"""),1445.0) -> 1445 | E38: =IFERROR(__xludf.DUMMYFUNCTION("""COMPUTED_VALUE"""),1425.0) -> 1425 | F38: =IFERROR(__xludf.DUMMYFUNCTION("""COMPUTED_VALUE"""),1430.0) -> 1430 | G38: =IFERROR(__xludf.DUMMYFUNCTION("""COMPUTED_VALUE"""),3.0535812E7) -> 30535812 | J38: 45966 | K38: 10 | L38: 1470 | M38: 11 | N38: =K38*L38+M38 -> 14711 | O38: =SUM($N$26:N38)/SUM($K$26:K38) -> 1285.4
B39: =IFERROR(__xludf.DUMMYFUNCTION("""COMPUTED_VALUE"""),46009.5625) -> 46009.562 | C39: =IFERROR(__xludf.DUMMYFUNCTION("""COMPUTED_VALUE"""),1420.0) -> 1420 | D39: =IFERROR(__xludf.DUMMYFUNCTION("""COMPUTED_VALUE"""),1435.0) -> 1435 | E39: =IFERROR(__xludf.DUMMYFUNCTION("""COMPUTED_VALUE"""),1415.0) -> 1415 | F39: =IFERROR(__xludf.DUMMYFUNCTION("""COMPUTED_VALUE"""),1430.0) -> 1430 | G39: =IFERROR(__xludf.DUMMYFUNCTION("""COMPUTED_VALUE"""),3.0534136E7) -> 30534136 | J39: 45982 | K39: 10 | L39: 1400 | M39: 11 | N39: =K39*L39+M39 -> 14011 | O39: =SUM($N$26:N39)/SUM($K$26:K39) -> 1295.0417
B40: =IFERROR(__xludf.DUMMYFUNCTION("""COMPUTED_VALUE"""),46010.5625) -> 46010.562 | C40: =IFERROR(__xludf.DUMMYFUNCTION("""COMPUTED_VALUE"""),1455.0) -> 1455 | D40: =IFERROR(__xludf.DUMMYFUNCTION("""COMPUTED_VALUE"""),1455.0) -> 1455 | E40: =IFERROR(__xludf.DUMMYFUNCTION("""COMPUTED_VALUE"""),1430.0) -> 1430 | F40: =IFERROR(__xludf.DUMMYFUNCTION("""COMPUTED_VALUE"""),1430.0) -> 1430 | G40: =IFERROR(__xludf.DUMMYFUNCTION("""COMPUTED_VALUE"""),3.876328E7) -> 38763280 | J40: 45995 | K40: 10 | L40: 1435 | M40: 11 | N40: =K40*L40+M40 -> 14361 | O40: =SUM($N$26:N40)/SUM($K$26:K40) -> 1305.8923
B41: =IFERROR(__xludf.DUMMYFUNCTION("""COMPUTED_VALUE"""),46013.5625) -> 46013.562 | C41: =IFERROR(__xludf.DUMMYFUNCTION("""COMPUTED_VALUE"""),1465.0) -> 1465 | D41: =IFERROR(__xludf.DUMMYFUNCTION("""COMPUTED_VALUE"""),1470.0) -> 1470 | E41: =IFERROR(__xludf.DUMMYFUNCTION("""COMPUTED_VALUE"""),1455.0) -> 1455 | F41: =IFERROR(__xludf.DUMMYFUNCTION("""COMPUTED_VALUE"""),1465.0) -> 1465 | G41: =IFERROR(__xludf.DUMMYFUNCTION("""COMPUTED_VALUE"""),2.2661665E7) -> 22661665 | J41: 46090 | K41: 10 | L41: 1800 | M41: 14 | N41: =K41*L41+M41 -> 18014 | O41: =SUM($N$26:N41)/SUM($K$26:K41) -> 1341.2857
B42: =IFERROR(__xludf.DUMMYFUNCTION("""COMPUTED_VALUE"""),46014.5625) -> 46014.562 | C42: =IFERROR(__xludf.DUMMYFUNCTION("""COMPUTED_VALUE"""),1475.0) -> 1475 | D42: =IFERROR(__xludf.DUMMYFUNCTION("""COMPUTED_VALUE"""),1490.0) -> 1490 | E42: =IFERROR(__xludf.DUMMYFUNCTION("""COMPUTED_VALUE"""),1470.0) -> 1470 | F42: =IFERROR(__xludf.DUMMYFUNCTION("""COMPUTED_VALUE"""),1490.0) -> 1490 | G42: =IFERROR(__xludf.DUMMYFUNCTION("""COMPUTED_VALUE"""),2.0739075E7) -> 20739075 | J42: 46101 | K42: 10 | L42: 1855 | M42: 14 | N42: =K42*L42+M42 -> 18564 | O42: =SUM($N$26:N42)/SUM($K$26:K42) -> 1375.6267
B43: =IFERROR(__xludf.DUMMYFUNCTION("""COMPUTED_VALUE"""),46015.5625) -> 46015.562 | C43: =IFERROR(__xludf.DUMMYFUNCTION("""COMPUTED_VALUE"""),1495.0) -> 1495 | D43: =IFERROR(__xludf.DUMMYFUNCTION("""COMPUTED_VALUE"""),1500.0) -> 1500 | E43: =IFERROR(__xludf.DUMMYFUNCTION("""COMPUTED_VALUE"""),1485.0) -> 1485 | F43: =IFERROR(__xludf.DUMMYFUNCTION("""COMPUTED_VALUE"""),1495.0) -> 1495 | G43: =IFERROR(__xludf.DUMMYFUNCTION("""COMPUTED_VALUE"""),1.2987261E7) -> 12987261 | J43: 46161 | K43: 10 | L43: 2220 | M43: 17 | N43: =K43*L43+M43 -> 22217 | O43: =SUM($N$26:N43)/SUM($K$26:K43) -> 1428.5062
B44: =IFERROR(__xludf.DUMMYFUNCTION("""COMPUTED_VALUE"""),46017.5625) -> 46017.562 | C44: =IFERROR(__xludf.DUMMYFUNCTION("""COMPUTED_VALUE"""),1505.0) -> 1505 | D44: =IFERROR(__xludf.DUMMYFUNCTION("""COMPUTED_VALUE"""),1510.0) -> 1510 | E44: =IFERROR(__xludf.DUMMYFUNCTION("""COMPUTED_VALUE"""),1495.0) -> 1495 | F44: =IFERROR(__xludf.DUMMYFUNCTION("""COMPUTED_VALUE"""),1510.0) -> 1510 | G44: =IFERROR(__xludf.DUMMYFUNCTION("""COMPUTED_VALUE"""),1.8823612E7) -> 18823612 | N44: =K44*L44+M44 -> 0 | O44: =SUM($N$26:N44)/SUM($K$26:K44) -> 1428.5062
B45: =IFERROR(__xludf.DUMMYFUNCTION("""COMPUTED_VALUE"""),46020.5625) -> 46020.562 | C45: =IFERROR(__xludf.DUMMYFUNCTION("""COMPUTED_VALUE"""),1515.0) -> 1515 | D45: =IFERROR(__xludf.DUMMYFUNCTION("""COMPUTED_VALUE"""),1530.0) -> 1530 | E45: =IFERROR(__xludf.DUMMYFUNCTION("""COMPUTED_VALUE"""),1510.0) -> 1510 | F45: =IFERROR(__xludf.DUMMYFUNCTION("""COMPUTED_VALUE"""),1530.0) -> 1530 | G45: =IFERROR(__xludf.DUMMYFUNCTION("""COMPUTED_VALUE"""),2.1124648E7) -> 21124648 | N45: =K45*L45+M45 -> 0 | O45: =SUM($N$26:N45)/SUM($K$26:K45) -> 1428.5062
B46: =IFERROR(__xludf.DUMMYFUNCTION("""COMPUTED_VALUE"""),46021.5625) -> 46021.562 | C46: =IFERROR(__xludf.DUMMYFUNCTION("""COMPUTED_VALUE"""),1515.0) -> 1515 | D46: =IFERROR(__xludf.DUMMYFUNCTION("""COMPUTED_VALUE"""),1530.0) -> 1530 | E46: =IFERROR(__xludf.DUMMYFUNCTION("""COMPUTED_VALUE"""),1510.0) -> 1510 | F46: =IFERROR(__xludf.DUMMYFUNCTION("""COMPUTED_VALUE"""),1520.0) -> 1520 | G46: =IFERROR(__xludf.DUMMYFUNCTION("""COMPUTED_VALUE"""),2.03254E7) -> 20325400 | N46: =K46*L46+M46 -> 0 | O46: =SUM($N$26:N46)/SUM($K$26:K46) -> 1428.5062
B47: =IFERROR(__xludf.DUMMYFUNCTION("""COMPUTED_VALUE"""),46022.5625) -> 46022.562 | C47: =IFERROR(__xludf.DUMMYFUNCTION("""COMPUTED_VALUE"""),1520.0) -> 1520 | D47: =IFERROR(__xludf.DUMMYFUNCTION("""COMPUTED_VALUE"""),1550.0) -> 1550 | E47: =IFERROR(__xludf.DUMMYFUNCTION("""COMPUTED_VALUE"""),1515.0) -> 1515 | F47: =IFERROR(__xludf.DUMMYFUNCTION("""COMPUTED_VALUE"""),1550.0) -> 1550 | G47: =IFERROR(__xludf.DUMMYFUNCTION("""COMPUTED_VALUE"""),2.9695967E7) -> 29695967 | N47: =K47*L47+M47 -> 0 | O47: =SUM($N$26:N47)/SUM($K$26:K47) -> 1428.5062
B48: =IFERROR(__xludf.DUMMYFUNCTION("""COMPUTED_VALUE"""),46024.5625) -> 46024.562 | C48: =IFERROR(__xludf.DUMMYFUNCTION("""COMPUTED_VALUE"""),1555.0) -> 1555 | D48: =IFERROR(__xludf.DUMMYFUNCTION("""COMPUTED_VALUE"""),1585.0) -> 1585 | E48: =IFERROR(__xludf.DUMMYFUNCTION("""COMPUTED_VALUE"""),1545.0) -> 1545 | F48: =IFERROR(__xludf.DUMMYFUNCTION("""COMPUTED_VALUE"""),1585.0) -> 1585 | G48: =IFERROR(__xludf.DUMMYFUNCTION("""COMPUTED_VALUE"""),3.7512761E7) -> 37512761 | J48: =TODAY() -> 46172 | L48: =B8 -> 2355 | N48: =K48*L48+M48 -> 0 | O48: =SUM($N$26:N48)/SUM($K$26:K48) -> 1428.5062
B49: =IFERROR(__xludf.DUMMYFUNCTION("""COMPUTED_VALUE"""),46027.5625) -> 46027.562 | C49: =IFERROR(__xludf.DUMMYFUNCTION("""COMPUTED_VALUE"""),1630.0) -> 1630 | D49: =IFERROR(__xludf.DUMMYFUNCTION("""COMPUTED_VALUE"""),1695.0) -> 1695 | E49: =IFERROR(__xludf.DUMMYFUNCTION("""COMPUTED_VALUE"""),1625.0) -> 1625 | F49: =IFERROR(__xludf.DUMMYFUNCTION("""COMPUTED_VALUE"""),1670.0) -> 1670 | G49: =IFERROR(__xludf.DUMMYFUNCTION("""COMPUTED_VALUE"""),6.687182E7) -> 66871820
B50: =IFERROR(__xludf.DUMMYFUNCTION("""COMPUTED_VALUE"""),46028.5625) -> 46028.562 | C50: =IFERROR(__xludf.DUMMYFUNCTION("""COMPUTED_VALUE"""),1645.0) -> 1645 | D50: =IFERROR(__xludf.DUMMYFUNCTION("""COMPUTED_VALUE"""),1705.0) -> 1705 | E50: =IFERROR(__xludf.DUMMYFUNCTION("""COMPUTED_VALUE"""),1645.0) -> 1645 | F50: =IFERROR(__xludf.DUMMYFUNCTION("""COMPUTED_VALUE"""),1705.0) -> 1705 | G50: =IFERROR(__xludf.DUMMYFUNCTION("""COMPUTED_VALUE"""),4.6751692E7) -> 46751692
B51: =IFERROR(__xludf.DUMMYFUNCTION("""COMPUTED_VALUE"""),46029.5625) -> 46029.562 | C51: =IFERROR(__xludf.DUMMYFUNCTION("""COMPUTED_VALUE"""),1665.0) -> 1665 | D51: =IFERROR(__xludf.DUMMYFUNCTION("""COMPUTED_VALUE"""),1685.0) -> 1685 | E51: =IFERROR(__xludf.DUMMYFUNCTION("""COMPUTED_VALUE"""),1665.0) -> 1665 | F51: =IFERROR(__xludf.DUMMYFUNCTION("""COMPUTED_VALUE"""),1675.0) -> 1675 | G51: =IFERROR(__xludf.DUMMYFUNCTION("""COMPUTED_VALUE"""),4.9857449E7) -> 49857449
B52: =IFERROR(__xludf.DUMMYFUNCTION("""COMPUTED_VALUE"""),46030.5625) -> 46030.562 | C52: =IFERROR(__xludf.DUMMYFUNCTION("""COMPUTED_VALUE"""),1660.0) -> 1660 | D52: =IFERROR(__xludf.DUMMYFUNCTION("""COMPUTED_VALUE"""),1700.0) -> 1700 | E52: =IFERROR(__xludf.DUMMYFUNCTION("""COMPUTED_VALUE"""),1655.0) -> 1655 | F52: =IFERROR(__xludf.DUMMYFUNCTION("""COMPUTED_VALUE"""),1685.0) -> 1685 | G52: =IFERROR(__xludf.DUMMYFUNCTION("""COMPUTED_VALUE"""),2.9215618E7) -> 29215618
B53: =IFERROR(__xludf.DUMMYFUNCTION("""COMPUTED_VALUE"""),46031.5625) -> 46031.562 | C53: =IFERROR(__xludf.DUMMYFUNCTION("""COMPUTED_VALUE"""),1665.0) -> 1665 | D53: =IFERROR(__xludf.DUMMYFUNCTION("""COMPUTED_VALUE"""),1700.0) -> 1700 | E53: =IFERROR(__xludf.DUMMYFUNCTION("""COMPUTED_VALUE"""),1655.0) -> 1655 | F53: =IFERROR(__xludf.DUMMYFUNCTION("""COMPUTED_VALUE"""),1680.0) -> 1680 | G53: =IFERROR(__xludf.DUMMYFUNCTION("""COMPUTED_VALUE"""),3.7387656E7) -> 37387656
B54: =IFERROR(__xludf.DUMMYFUNCTION("""COMPUTED_VALUE"""),46034.5625) -> 46034.562 | C54: =IFERROR(__xludf.DUMMYFUNCTION("""COMPUTED_VALUE"""),1700.0) -> 1700 | D54: =IFERROR(__xludf.DUMMYFUNCTION("""COMPUTED_VALUE"""),1705.0) -> 1705 | E54: =IFERROR(__xludf.DUMMYFUNCTION("""COMPUTED_VALUE"""),1690.0) -> 1690 | F54: =IFERROR(__xludf.DUMMYFUNCTION("""COMPUTED_VALUE"""),1690.0) -> 1690 | G54: =IFERROR(__xludf.DUMMYFUNCTION("""COMPUTED_VALUE"""),2.9987449E7) -> 29987449
B55: =IFERROR(__xludf.DUMMYFUNCTION("""COMPUTED_VALUE"""),46035.5625) -> 46035.562 | C55: =IFERROR(__xludf.DUMMYFUNCTION("""COMPUTED_VALUE"""),1720.0) -> 1720 | D55: =IFERROR(__xludf.DUMMYFUNCTION("""COMPUTED_VALUE"""),1720.0) -> 1720 | E55: =IFERROR(__xludf.DUMMYFUNCTION("""COMPUTED_VALUE"""),1700.0) -> 1700 | F55: =IFERROR(__xludf.DUMMYFUNCTION("""COMPUTED_VALUE"""),1710.0) -> 1710 | G55: =IFERROR(__xludf.DUMMYFUNCTION("""COMPUTED_VALUE"""),3.01718E7) -> 30171800
B56: =IFERROR(__xludf.DUMMYFUNCTION("""COMPUTED_VALUE"""),46036.5625) -> 46036.562 | C56: =IFERROR(__xludf.DUMMYFUNCTION("""COMPUTED_VALUE"""),1705.0) -> 1705 | D56: =IFERROR(__xludf.DUMMYFUNCTION("""COMPUTED_VALUE"""),1715.0) -> 1715 | E56: =IFERROR(__xludf.DUMMYFUNCTION("""COMPUTED_VALUE"""),1700.0) -> 1700 | F56: =IFERROR(__xludf.DUMMYFUNCTION("""COMPUTED_VALUE"""),1710.0) -> 1710 | G56: =IFERROR(__xludf.DUMMYFUNCTION("""COMPUTED_VALUE"""),2.9100816E7) -> 29100816
B57: =IFERROR(__xludf.DUMMYFUNCTION("""COMPUTED_VALUE"""),46037.5625) -> 46037.562 | C57: =IFERROR(__xludf.DUMMYFUNCTION("""COMPUTED_VALUE"""),1685.0) -> 1685 | D57: =IFERROR(__xludf.DUMMYFUNCTION("""COMPUTED_VALUE"""),1700.0) -> 1700 | E57: =IFERROR(__xludf.DUMMYFUNCTION("""COMPUTED_VALUE"""),1680.0) -> 1680 | F57: =IFERROR(__xludf.DUMMYFUNCTION("""COMPUTED_VALUE"""),1690.0) -> 1690 | G57: =IFERROR(__xludf.DUMMYFUNCTION("""COMPUTED_VALUE"""),3.6391886E7) -> 36391886
B58: =IFERROR(__xludf.DUMMYFUNCTION("""COMPUTED_VALUE"""),46038.5625) -> 46038.562 | C58: =IFERROR(__xludf.DUMMYFUNCTION("""COMPUTED_VALUE"""),1735.0) -> 1735 | D58: =IFERROR(__xludf.DUMMYFUNCTION("""COMPUTED_VALUE"""),1750.0) -> 1750 | E58: =IFERROR(__xludf.DUMMYFUNCTION("""COMPUTED_VALUE"""),1710.0) -> 1710 | F58: =IFERROR(__xludf.DUMMYFUNCTION("""COMPUTED_VALUE"""),1740.0) -> 1740 | G58: =IFERROR(__xludf.DUMMYFUNCTION("""COMPUTED_VALUE"""),5.3551629E7) -> 53551629
B59: =IFERROR(__xludf.DUMMYFUNCTION("""COMPUTED_VALUE"""),46041.5625) -> 46041.562 | C59: =IFERROR(__xludf.DUMMYFUNCTION("""COMPUTED_VALUE"""),1725.0) -> 1725 | D59: =IFERROR(__xludf.DUMMYFUNCTION("""COMPUTED_VALUE"""),1780.0) -> 1780 | E59: =IFERROR(__xludf.DUMMYFUNCTION("""COMPUTED_VALUE"""),1725.0) -> 1725 | F59: =IFERROR(__xludf.DUMMYFUNCTION("""COMPUTED_VALUE"""),1760.0) -> 1760 | G59: =IFERROR(__xludf.DUMMYFUNCTION("""COMPUTED_VALUE"""),2.9580038E7) -> 29580038
B60: =IFERROR(__xludf.DUMMYFUNCTION("""COMPUTED_VALUE"""),46042.5625) -> 46042.562 | C60: =IFERROR(__xludf.DUMMYFUNCTION("""COMPUTED_VALUE"""),1740.0) -> 1740 | D60: =IFERROR(__xludf.DUMMYFUNCTION("""COMPUTED_VALUE"""),1775.0) -> 1775 | E60: =IFERROR(__xludf.DUMMYFUNCTION("""COMPUTED_VALUE"""),1740.0) -> 1740 | F60: =IFERROR(__xludf.DUMMYFUNCTION("""COMPUTED_VALUE"""),1775.0) -> 1775 | G60: =IFERROR(__xludf.DUMMYFUNCTION("""COMPUTED_VALUE"""),2.9401234E7) -> 29401234
B61: =IFERROR(__xludf.DUMMYFUNCTION("""COMPUTED_VALUE"""),46043.5625) -> 46043.562 | C61: =IFERROR(__xludf.DUMMYFUNCTION("""COMPUTED_VALUE"""),1745.0) -> 1745 | D61: =IFERROR(__xludf.DUMMYFUNCTION("""COMPUTED_VALUE"""),1765.0) -> 1765 | E61: =IFERROR(__xludf.DUMMYFUNCTION("""COMPUTED_VALUE"""),1740.0) -> 1740 | F61: =IFERROR(__xludf.DUMMYFUNCTION("""COMPUTED_VALUE"""),1740.0) -> 1740 | G61: =IFERROR(__xludf.DUMMYFUNCTION("""COMPUTED_VALUE"""),4.5192749E7) -> 45192749
B62: =IFERROR(__xludf.DUMMYFUNCTION("""COMPUTED_VALUE"""),46044.5625) -> 46044.562 | C62: =IFERROR(__xludf.DUMMYFUNCTION("""COMPUTED_VALUE"""),1765.0) -> 1765 | D62: =IFERROR(__xludf.DUMMYFUNCTION("""COMPUTED_VALUE"""),1770.0) -> 1770 | E62: =IFERROR(__xludf.DUMMYFUNCTION("""COMPUTED_VALUE"""),1750.0) -> 1750 | F62: =IFERROR(__xludf.DUMMYFUNCTION("""COMPUTED_VALUE"""),1760.0) -> 1760 | G62: =IFERROR(__xludf.DUMMYFUNCTION("""COMPUTED_VALUE"""),3.2069478E7) -> 32069478
B63: =IFERROR(__xludf.DUMMYFUNCTION("""COMPUTED_VALUE"""),46045.5625) -> 46045.562 | C63: =IFERROR(__xludf.DUMMYFUNCTION("""COMPUTED_VALUE"""),1770.0) -> 1770 | D63: =IFERROR(__xludf.DUMMYFUNCTION("""COMPUTED_VALUE"""),1775.0) -> 1775 | E63: =IFERROR(__xludf.DUMMYFUNCTION("""COMPUTED_VALUE"""),1750.0) -> 1750 | F63: =IFERROR(__xludf.DUMMYFUNCTION("""COMPUTED_VALUE"""),1770.0) -> 1770 | G63: =IFERROR(__xludf.DUMMYFUNCTION("""COMPUTED_VALUE"""),2.7601167E7) -> 27601167
B64: =IFERROR(__xludf.DUMMYFUNCTION("""COMPUTED_VALUE"""),46048.5625) -> 46048.562 | C64: =IFERROR(__xludf.DUMMYFUNCTION("""COMPUTED_VALUE"""),1765.0) -> 1765 | D64: =IFERROR(__xludf.DUMMYFUNCTION("""COMPUTED_VALUE"""),1785.0) -> 1785 | E64: =IFERROR(__xludf.DUMMYFUNCTION("""COMPUTED_VALUE"""),1755.0) -> 1755 | F64: =IFERROR(__xludf.DUMMYFUNCTION("""COMPUTED_VALUE"""),1755.0) -> 1755 | G64: =IFERROR(__xludf.DUMMYFUNCTION("""COMPUTED_VALUE"""),2.2960198E7) -> 22960198
B65: =IFERROR(__xludf.DUMMYFUNCTION("""COMPUTED_VALUE"""),46049.5625) -> 46049.562 | C65: =IFERROR(__xludf.DUMMYFUNCTION("""COMPUTED_VALUE"""),1760.0) -> 1760 | D65: =IFERROR(__xludf.DUMMYFUNCTION("""COMPUTED_VALUE"""),1785.0) -> 1785 | E65: =IFERROR(__xludf.DUMMYFUNCTION("""COMPUTED_VALUE"""),1755.0) -> 1755 | F65: =IFERROR(__xludf.DUMMYFUNCTION("""COMPUTED_VALUE"""),1780.0) -> 1780 | G65: =IFERROR(__xludf.DUMMYFUNCTION("""COMPUTED_VALUE"""),2.89852E7) -> 28985200
B66: =IFERROR(__xludf.DUMMYFUNCTION("""COMPUTED_VALUE"""),46050.5625) -> 46050.562 | C66: =IFERROR(__xludf.DUMMYFUNCTION("""COMPUTED_VALUE"""),1790.0) -> 1790 | D66: =IFERROR(__xludf.DUMMYFUNCTION("""COMPUTED_VALUE"""),1820.0) -> 1820 | E66: =IFERROR(__xludf.DUMMYFUNCTION("""COMPUTED_VALUE"""),1790.0) -> 1790 | F66: =IFERROR(__xludf.DUMMYFUNCTION("""COMPUTED_VALUE"""),1820.0) -> 1820 | G66: =IFERROR(__xludf.DUMMYFUNCTION("""COMPUTED_VALUE"""),2.9301156E7) -> 29301156
B67: =IFERROR(__xludf.DUMMYFUNCTION("""COMPUTED_VALUE"""),46051.5625) -> 46051.562 | C67: =IFERROR(__xludf.DUMMYFUNCTION("""COMPUTED_VALUE"""),1830.0) -> 1830 | D67: =IFERROR(__xludf.DUMMYFUNCTION("""COMPUTED_VALUE"""),1835.0) -> 1835 | E67: =IFERROR(__xludf.DUMMYFUNCTION("""COMPUTED_VALUE"""),1800.0) -> 1800 | F67: =IFERROR(__xludf.DUMMYFUNCTION("""COMPUTED_VALUE"""),1805.0) -> 1805 | G67: =IFERROR(__xludf.DUMMYFUNCTION("""COMPUTED_VALUE"""),3.2224002E7) -> 32224002
B68: =IFERROR(__xludf.DUMMYFUNCTION("""COMPUTED_VALUE"""),46052.5625) -> 46052.562 | C68: =IFERROR(__xludf.DUMMYFUNCTION("""COMPUTED_VALUE"""),1790.0) -> 1790 | D68: =IFERROR(__xludf.DUMMYFUNCTION("""COMPUTED_VALUE"""),1800.0) -> 1800 | E68: =IFERROR(__xludf.DUMMYFUNCTION("""COMPUTED_VALUE"""),1775.0) -> 1775 | F68: =IFERROR(__xludf.DUMMYFUNCTION("""COMPUTED_VALUE"""),1775.0) -> 1775 | G68: =IFERROR(__xludf.DUMMYFUNCTION("""COMPUTED_VALUE"""),4.0825139E7) -> 40825139
B69: =IFERROR(__xludf.DUMMYFUNCTION("""COMPUTED_VALUE"""),46055.5625) -> 46055.562 | C69: =IFERROR(__xludf.DUMMYFUNCTION("""COMPUTED_VALUE"""),1750.0) -> 1750 | D69: =IFERROR(__xludf.DUMMYFUNCTION("""COMPUTED_VALUE"""),1765.0) -> 1765 | E69: =IFERROR(__xludf.DUMMYFUNCTION("""COMPUTED_VALUE"""),1745.0) -> 1745 | F69: =IFERROR(__xludf.DUMMYFUNCTION("""COMPUTED_VALUE"""),1765.0) -> 1765 | G69: =IFERROR(__xludf.DUMMYFUNCTION("""COMPUTED_VALUE"""),2.8251381E7) -> 28251381
B70: =IFERROR(__xludf.DUMMYFUNCTION("""COMPUTED_VALUE"""),46056.5625) -> 46056.562 | C70: =IFERROR(__xludf.DUMMYFUNCTION("""COMPUTED_VALUE"""),1810.0) -> 1810 | D70: =IFERROR(__xludf.DUMMYFUNCTION("""COMPUTED_VALUE"""),1810.0) -> 1810 | E70: =IFERROR(__xludf.DUMMYFUNCTION("""COMPUTED_VALUE"""),1785.0) -> 1785 | F70: =IFERROR(__xludf.DUMMYFUNCTION("""COMPUTED_VALUE"""),1800.0) -> 1800 | G70: =IFERROR(__xludf.DUMMYFUNCTION("""COMPUTED_VALUE"""),2.6744162E7) -> 26744162
B71: =IFERROR(__xludf.DUMMYFUNCTION("""COMPUTED_VALUE"""),46057.5625) -> 46057.562 | C71: =IFERROR(__xludf.DUMMYFUNCTION("""COMPUTED_VALUE"""),1785.0) -> 1785 | D71: =IFERROR(__xludf.DUMMYFUNCTION("""COMPUTED_VALUE"""),1805.0) -> 1805 | E71: =IFERROR(__xludf.DUMMYFUNCTION("""COMPUTED_VALUE"""),1775.0) -> 1775 | F71: =IFERROR(__xludf.DUMMYFUNCTION("""COMPUTED_VALUE"""),1785.0) -> 1785 | G71: =IFERROR(__xludf.DUMMYFUNCTION("""COMPUTED_VALUE"""),2.6952301E7) -> 26952301
B72: =IFERROR(__xludf.DUMMYFUNCTION("""COMPUTED_VALUE"""),46058.5625) -> 46058.562 | C72: =IFERROR(__xludf.DUMMYFUNCTION("""COMPUTED_VALUE"""),1765.0) -> 1765 | D72: =IFERROR(__xludf.DUMMYFUNCTION("""COMPUTED_VALUE"""),1780.0) -> 1780 | E72: =IFERROR(__xludf.DUMMYFUNCTION("""COMPUTED_VALUE"""),1760.0) -> 1760 | F72: =IFERROR(__xludf.DUMMYFUNCTION("""COMPUTED_VALUE"""),1765.0) -> 1765 | G72: =IFERROR(__xludf.DUMMYFUNCTION("""COMPUTED_VALUE"""),2.6299986E7) -> 26299986
B73: =IFERROR(__xludf.DUMMYFUNCTION("""COMPUTED_VALUE"""),46059.5625) -> 46059.562 | C73: =IFERROR(__xludf.DUMMYFUNCTION("""COMPUTED_VALUE"""),1745.0) -> 1745 | D73: =IFERROR(__xludf.DUMMYFUNCTION("""COMPUTED_VALUE"""),1780.0) -> 1780 | E73: =IFERROR(__xludf.DUMMYFUNCTION("""COMPUTED_VALUE"""),1740.0) -> 1740 | F73: =IFERROR(__xludf.DUMMYFUNCTION("""COMPUTED_VALUE"""),1780.0) -> 1780 | G73: =IFERROR(__xludf.DUMMYFUNCTION("""COMPUTED_VALUE"""),3.3263592E7) -> 33263592
B74: =IFERROR(__xludf.DUMMYFUNCTION("""COMPUTED_VALUE"""),46062.5625) -> 46062.562 | C74: =IFERROR(__xludf.DUMMYFUNCTION("""COMPUTED_VALUE"""),1830.0) -> 1830 | D74: =IFERROR(__xludf.DUMMYFUNCTION("""COMPUTED_VALUE"""),1835.0) -> 1835 | E74: =IFERROR(__xludf.DUMMYFUNCTION("""COMPUTED_VALUE"""),1815.0) -> 1815 | F74: =IFERROR(__xludf.DUMMYFUNCTION("""COMPUTED_VALUE"""),1815.0) -> 1815 | G74: =IFERROR(__xludf.DUMMYFUNCTION("""COMPUTED_VALUE"""),3.6529289E7) -> 36529289
B75: =IFERROR(__xludf.DUMMYFUNCTION("""COMPUTED_VALUE"""),46063.5625) -> 46063.562 | C75: =IFERROR(__xludf.DUMMYFUNCTION("""COMPUTED_VALUE"""),1845.0) -> 1845 | D75: =IFERROR(__xludf.DUMMYFUNCTION("""COMPUTED_VALUE"""),1880.0) -> 1880 | E75: =IFERROR(__xludf.DUMMYFUNCTION("""COMPUTED_VALUE"""),1840.0) -> 1840 | F75: =IFERROR(__xludf.DUMMYFUNCTION("""COMPUTED_VALUE"""),1880.0) -> 1880 | G75: =IFERROR(__xludf.DUMMYFUNCTION("""COMPUTED_VALUE"""),4.1859169E7) -> 41859169
B76: =IFERROR(__xludf.DUMMYFUNCTION("""COMPUTED_VALUE"""),46064.5625) -> 46064.562 | C76: =IFERROR(__xludf.DUMMYFUNCTION("""COMPUTED_VALUE"""),1880.0) -> 1880 | D76: =IFERROR(__xludf.DUMMYFUNCTION("""COMPUTED_VALUE"""),1925.0) -> 1925 | E76: =IFERROR(__xludf.DUMMYFUNCTION("""COMPUTED_VALUE"""),1875.0) -> 1875 | F76: =IFERROR(__xludf.DUMMYFUNCTION("""COMPUTED_VALUE"""),1915.0) -> 1915 | G76: =IFERROR(__xludf.DUMMYFUNCTION("""COMPUTED_VALUE"""),4.048831E7) -> 40488310
B77: =IFERROR(__xludf.DUMMYFUNCTION("""COMPUTED_VALUE"""),46076.5625) -> 46076.562 | C77: =IFERROR(__xludf.DUMMYFUNCTION("""COMPUTED_VALUE"""),1900.0) -> 1900 | D77: =IFERROR(__xludf.DUMMYFUNCTION("""COMPUTED_VALUE"""),1935.0) -> 1935 | E77: =IFERROR(__xludf.DUMMYFUNCTION("""COMPUTED_VALUE"""),1900.0) -> 1900 | F77: =IFERROR(__xludf.DUMMYFUNCTION("""COMPUTED_VALUE"""),1900.0) -> 1900 | G77: =IFERROR(__xludf.DUMMYFUNCTION("""COMPUTED_VALUE"""),6.9816209E7) -> 69816209
B78: =IFERROR(__xludf.DUMMYFUNCTION("""COMPUTED_VALUE"""),46077.5625) -> 46077.562 | C78: =IFERROR(__xludf.DUMMYFUNCTION("""COMPUTED_VALUE"""),1915.0) -> 1915 | D78: =IFERROR(__xludf.DUMMYFUNCTION("""COMPUTED_VALUE"""),1975.0) -> 1975 | E78: =IFERROR(__xludf.DUMMYFUNCTION("""COMPUTED_VALUE"""),1915.0) -> 1915 | F78: =IFERROR(__xludf.DUMMYFUNCTION("""COMPUTED_VALUE"""),1965.0) -> 1965 | G78: =IFERROR(__xludf.DUMMYFUNCTION("""COMPUTED_VALUE"""),4.0961679E7) -> 40961679
B79: =IFERROR(__xludf.DUMMYFUNCTION("""COMPUTED_VALUE"""),46078.5625) -> 46078.562 | C79: =IFERROR(__xludf.DUMMYFUNCTION("""COMPUTED_VALUE"""),1995.0) -> 1995 | D79: =IFERROR(__xludf.DUMMYFUNCTION("""COMPUTED_VALUE"""),2025.0) -> 2025 | E79: =IFERROR(__xludf.DUMMYFUNCTION("""COMPUTED_VALUE"""),1995.0) -> 1995 | F79: =IFERROR(__xludf.DUMMYFUNCTION("""COMPUTED_VALUE"""),2015.0) -> 2015 | G79: =IFERROR(__xludf.DUMMYFUNCTION("""COMPUTED_VALUE"""),4.0832607E7) -> 40832607
B80: =IFERROR(__xludf.DUMMYFUNCTION("""COMPUTED_VALUE"""),46079.5625) -> 46079.562 | C80: =IFERROR(__xludf.DUMMYFUNCTION("""COMPUTED_VALUE"""),2000.0) -> 2000 | D80: =IFERROR(__xludf.DUMMYFUNCTION("""COMPUTED_VALUE"""),2010.0) -> 2010 | E80: =IFERROR(__xludf.DUMMYFUNCTION("""COMPUTED_VALUE"""),1995.0) -> 1995 | F80: =IFERROR(__xludf.DUMMYFUNCTION("""COMPUTED_VALUE"""),1995.0) -> 1995 | G80: =IFERROR(__xludf.DUMMYFUNCTION("""COMPUTED_VALUE"""),5.8561388E7) -> 58561388
B81: =IFERROR(__xludf.DUMMYFUNCTION("""COMPUTED_VALUE"""),46083.5625) -> 46083.562 | C81: =IFERROR(__xludf.DUMMYFUNCTION("""COMPUTED_VALUE"""),1940.0) -> 1940 | D81: =IFERROR(__xludf.DUMMYFUNCTION("""COMPUTED_VALUE"""),1995.0) -> 1995 | E81: =IFERROR(__xludf.DUMMYFUNCTION("""COMPUTED_VALUE"""),1940.0) -> 1940 | F81: =IFERROR(__xludf.DUMMYFUNCTION("""COMPUTED_VALUE"""),1975.0) -> 1975 | G81: =IFERROR(__xludf.DUMMYFUNCTION("""COMPUTED_VALUE"""),4.8884884E7) -> 48884884
B82: =IFERROR(__xludf.DUMMYFUNCTION("""COMPUTED_VALUE"""),46084.5625) -> 46084.562 | C82: =IFERROR(__xludf.DUMMYFUNCTION("""COMPUTED_VALUE"""),1970.0) -> 1970 | D82: =IFERROR(__xludf.DUMMYFUNCTION("""COMPUTED_VALUE"""),1980.0) -> 1980 | E82: =IFERROR(__xludf.DUMMYFUNCTION("""COMPUTED_VALUE"""),1935.0) -> 1935 | F82: =IFERROR(__xludf.DUMMYFUNCTION("""COMPUTED_VALUE"""),1935.0) -> 1935 | G82: =IFERROR(__xludf.DUMMYFUNCTION("""COMPUTED_VALUE"""),4.3090471E7) -> 43090471
B83: =IFERROR(__xludf.DUMMYFUNCTION("""COMPUTED_VALUE"""),46085.5625) -> 46085.562 | C83: =IFERROR(__xludf.DUMMYFUNCTION("""COMPUTED_VALUE"""),1895.0) -> 1895 | D83: =IFERROR(__xludf.DUMMYFUNCTION("""COMPUTED_VALUE"""),1910.0) -> 1910 | E83: =IFERROR(__xludf.DUMMYFUNCTION("""COMPUTED_VALUE"""),1865.0) -> 1865 | F83: =IFERROR(__xludf.DUMMYFUNCTION("""COMPUTED_VALUE"""),1865.0) -> 1865 | G83: =IFERROR(__xludf.DUMMYFUNCTION("""COMPUTED_VALUE"""),6.8160943E7) -> 68160943
B84: =IFERROR(__xludf.DUMMYFUNCTION("""COMPUTED_VALUE"""),46086.5625) -> 46086.562 | C84: =IFERROR(__xludf.DUMMYFUNCTION("""COMPUTED_VALUE"""),1940.0) -> 1940 | D84: =IFERROR(__xludf.DUMMYFUNCTION("""COMPUTED_VALUE"""),1960.0) -> 1960 | E84: =IFERROR(__xludf.DUMMYFUNCTION("""COMPUTED_VALUE"""),1895.0) -> 1895 | F84: =IFERROR(__xludf.DUMMYFUNCTION("""COMPUTED_VALUE"""),1900.0) -> 1900 | G84: =IFERROR(__xludf.DUMMYFUNCTION("""COMPUTED_VALUE"""),4.8120463E7) -> 48120463
B85: =IFERROR(__xludf.DUMMYFUNCTION("""COMPUTED_VALUE"""),46087.5625) -> 46087.562 | C85: =IFERROR(__xludf.DUMMYFUNCTION("""COMPUTED_VALUE"""),1880.0) -> 1880 | D85: =IFERROR(__xludf.DUMMYFUNCTION("""COMPUTED_VALUE"""),1900.0) -> 1900 | E85: =IFERROR(__xludf.DUMMYFUNCTION("""COMPUTED_VALUE"""),1880.0) -> 1880 | F85: =IFERROR(__xludf.DUMMYFUNCTION("""COMPUTED_VALUE"""),1890.0) -> 1890 | G85: =IFERROR(__xludf.DUMMYFUNCTION("""COMPUTED_VALUE"""),3.0082724E7) -> 30082724
B86: =IFERROR(__xludf.DUMMYFUNCTION("""COMPUTED_VALUE"""),46090.5625) -> 46090.562 | C86: =IFERROR(__xludf.DUMMYFUNCTION("""COMPUTED_VALUE"""),1775.0) -> 1775 | D86: =IFERROR(__xludf.DUMMYFUNCTION("""COMPUTED_VALUE"""),1810.0) -> 1810 | E86: =IFERROR(__xludf.DUMMYFUNCTION("""COMPUTED_VALUE"""),1770.0) -> 1770 | F86: =IFERROR(__xludf.DUMMYFUNCTION("""COMPUTED_VALUE"""),1810.0) -> 1810 | G86: =IFERROR(__xludf.DUMMYFUNCTION("""COMPUTED_VALUE"""),7.6459172E7) -> 76459172
B87: =IFERROR(__xludf.DUMMYFUNCTION("""COMPUTED_VALUE"""),46091.5625) -> 46091.562 | C87: =IFERROR(__xludf.DUMMYFUNCTION("""COMPUTED_VALUE"""),1870.0) -> 1870 | D87: =IFERROR(__xludf.DUMMYFUNCTION("""COMPUTED_VALUE"""),1890.0) -> 1890 | E87: =IFERROR(__xludf.DUMMYFUNCTION("""COMPUTED_VALUE"""),1830.0) -> 1830 | F87: =IFERROR(__xludf.DUMMYFUNCTION("""COMPUTED_VALUE"""),1850.0) -> 1850 | G87: =IFERROR(__xludf.DUMMYFUNCTION("""COMPUTED_VALUE"""),4.1375691E7) -> 41375691
B88: =IFERROR(__xludf.DUMMYFUNCTION("""COMPUTED_VALUE"""),46092.5625) -> 46092.562 | C88: =IFERROR(__xludf.DUMMYFUNCTION("""COMPUTED_VALUE"""),1885.0) -> 1885 | D88: =IFERROR(__xludf.DUMMYFUNCTION("""COMPUTED_VALUE"""),1950.0) -> 1950 | E88: =IFERROR(__xludf.DUMMYFUNCTION("""COMPUTED_VALUE"""),1875.0) -> 1875 | F88: =IFERROR(__xludf.DUMMYFUNCTION("""COMPUTED_VALUE"""),1940.0) -> 1940 | G88: =IFERROR(__xludf.DUMMYFUNCTION("""COMPUTED_VALUE"""),3.6167313E7) -> 36167313
B89: =IFERROR(__xludf.DUMMYFUNCTION("""COMPUTED_VALUE"""),46093.5625) -> 46093.562 | C89: =IFERROR(__xludf.DUMMYFUNCTION("""COMPUTED_VALUE"""),1900.0) -> 1900 | D89: =IFERROR(__xludf.DUMMYFUNCTION("""COMPUTED_VALUE"""),1915.0) -> 1915 | E89: =IFERROR(__xludf.DUMMYFUNCTION("""COMPUTED_VALUE"""),1885.0) -> 1885 | F89: =IFERROR(__xludf.DUMMYFUNCTION("""COMPUTED_VALUE"""),1885.0) -> 1885 | G89: =IFERROR(__xludf.DUMMYFUNCTION("""COMPUTED_VALUE"""),3.4040589E7) -> 34040589
B90: =IFERROR(__xludf.DUMMYFUNCTION("""COMPUTED_VALUE"""),46094.5625) -> 46094.562 | C90: =IFERROR(__xludf.DUMMYFUNCTION("""COMPUTED_VALUE"""),1840.0) -> 1840 | D90: =IFERROR(__xludf.DUMMYFUNCTION("""COMPUTED_VALUE"""),1885.0) -> 1885 | E90: =IFERROR(__xludf.DUMMYFUNCTION("""COMPUTED_VALUE"""),1840.0) -> 1840 | F90: =IFERROR(__xludf.DUMMYFUNCTION("""COMPUTED_VALUE"""),1865.0) -> 1865 | G90: =IFERROR(__xludf.DUMMYFUNCTION("""COMPUTED_VALUE"""),3.1214304E7) -> 31214304
B91: =IFERROR(__xludf.DUMMYFUNCTION("""COMPUTED_VALUE"""),46097.5625) -> 46097.562 | C91: =IFERROR(__xludf.DUMMYFUNCTION("""COMPUTED_VALUE"""),1875.0) -> 1875 | D91: =IFERROR(__xludf.DUMMYFUNCTION("""COMPUTED_VALUE"""),1880.0) -> 1880 | E91: =IFERROR(__xludf.DUMMYFUNCTION("""COMPUTED_VALUE"""),1845.0) -> 1845 | F91: =IFERROR(__xludf.DUMMYFUNCTION("""COMPUTED_VALUE"""),1845.0) -> 1845 | G91: =IFERROR(__xludf.DUMMYFUNCTION("""COMPUTED_VALUE"""),3.1249086E7) -> 31249086
B92: =IFERROR(__xludf.DUMMYFUNCTION("""COMPUTED_VALUE"""),46098.5625) -> 46098.562 | C92: =IFERROR(__xludf.DUMMYFUNCTION("""COMPUTED_VALUE"""),1875.0) -> 1875 | D92: =IFERROR(__xludf.DUMMYFUNCTION("""COMPUTED_VALUE"""),1880.0) -> 1880 | E92: =IFERROR(__xludf.DUMMYFUNCTION("""COMPUTED_VALUE"""),1860.0) -> 1860 | F92: =IFERROR(__xludf.DUMMYFUNCTION("""COMPUTED_VALUE"""),1870.0) -> 1870 | G92: =IFERROR(__xludf.DUMMYFUNCTION("""COMPUTED_VALUE"""),2.3812211E7) -> 23812211
B93: =IFERROR(__xludf.DUMMYFUNCTION("""COMPUTED_VALUE"""),46099.5625) -> 46099.562 | C93: =IFERROR(__xludf.DUMMYFUNCTION("""COMPUTED_VALUE"""),1900.0) -> 1900 | D93: =IFERROR(__xludf.DUMMYFUNCTION("""COMPUTED_VALUE"""),1910.0) -> 1910 | E93: =IFERROR(__xludf.DUMMYFUNCTION("""COMPUTED_VALUE"""),1890.0) -> 1890 | F93: =IFERROR(__xludf.DUMMYFUNCTION("""COMPUTED_VALUE"""),1905.0) -> 1905 | G93: =IFERROR(__xludf.DUMMYFUNCTION("""COMPUTED_VALUE"""),2.3068156E7) -> 23068156
B94: =IFERROR(__xludf.DUMMYFUNCTION("""COMPUTED_VALUE"""),46100.5625) -> 46100.562 | C94: =IFERROR(__xludf.DUMMYFUNCTION("""COMPUTED_VALUE"""),1875.0) -> 1875 | D94: =IFERROR(__xludf.DUMMYFUNCTION("""COMPUTED_VALUE"""),1880.0) -> 1880 | E94: =IFERROR(__xludf.DUMMYFUNCTION("""COMPUTED_VALUE"""),1850.0) -> 1850 | F94: =IFERROR(__xludf.DUMMYFUNCTION("""COMPUTED_VALUE"""),1850.0) -> 1850 | G94: =IFERROR(__xludf.DUMMYFUNCTION("""COMPUTED_VALUE"""),3.1040569E7) -> 31040569
B95: =IFERROR(__xludf.DUMMYFUNCTION("""COMPUTED_VALUE"""),46101.5625) -> 46101.562 | C95: =IFERROR(__xludf.DUMMYFUNCTION("""COMPUTED_VALUE"""),1860.0) -> 1860 | D95: =IFERROR(__xludf.DUMMYFUNCTION("""COMPUTED_VALUE"""),1870.0) -> 1870 | E95: =IFERROR(__xludf.DUMMYFUNCTION("""COMPUTED_VALUE"""),1840.0) -> 1840 | F95: =IFERROR(__xludf.DUMMYFUNCTION("""COMPUTED_VALUE"""),1840.0) -> 1840 | G95: =IFERROR(__xludf.DUMMYFUNCTION("""COMPUTED_VALUE"""),4.6312322E7) -> 46312322
B96: =IFERROR(__xludf.DUMMYFUNCTION("""COMPUTED_VALUE"""),46104.5625) -> 46104.562 | C96: =IFERROR(__xludf.DUMMYFUNCTION("""COMPUTED_VALUE"""),1790.0) -> 1790 | D96: =IFERROR(__xludf.DUMMYFUNCTION("""COMPUTED_VALUE"""),1815.0) -> 1815 | E96: =IFERROR(__xludf.DUMMYFUNCTION("""COMPUTED_VALUE"""),1785.0) -> 1785 | F96: =IFERROR(__xludf.DUMMYFUNCTION("""COMPUTED_VALUE"""),1810.0) -> 1810 | G96: =IFERROR(__xludf.DUMMYFUNCTION("""COMPUTED_VALUE"""),3.4902948E7) -> 34902948
B97: =IFERROR(__xludf.DUMMYFUNCTION("""COMPUTED_VALUE"""),46105.5625) -> 46105.562 | C97: =IFERROR(__xludf.DUMMYFUNCTION("""COMPUTED_VALUE"""),1850.0) -> 1850 | D97: =IFERROR(__xludf.DUMMYFUNCTION("""COMPUTED_VALUE"""),1850.0) -> 1850 | E97: =IFERROR(__xludf.DUMMYFUNCTION("""COMPUTED_VALUE"""),1800.0) -> 1800 | F97: =IFERROR(__xludf.DUMMYFUNCTION("""COMPUTED_VALUE"""),1810.0) -> 1810 | G97: =IFERROR(__xludf.DUMMYFUNCTION("""COMPUTED_VALUE"""),2.7001025E7) -> 27001025
B98: =IFERROR(__xludf.DUMMYFUNCTION("""COMPUTED_VALUE"""),46106.5625) -> 46106.562 | C98: =IFERROR(__xludf.DUMMYFUNCTION("""COMPUTED_VALUE"""),1865.0) -> 1865 | D98: =IFERROR(__xludf.DUMMYFUNCTION("""COMPUTED_VALUE"""),1875.0) -> 1875 | E98: =IFERROR(__xludf.DUMMYFUNCTION("""COMPUTED_VALUE"""),1845.0) -> 1845 | F98: =IFERROR(__xludf.DUMMYFUNCTION("""COMPUTED_VALUE"""),1845.0) -> 1845 | G98: =IFERROR(__xludf.DUMMYFUNCTION("""COMPUTED_VALUE"""),4.096404E7) -> 40964040
B99: =IFERROR(__xludf.DUMMYFUNCTION("""COMPUTED_VALUE"""),46107.5625) -> 46107.562 | C99: =IFERROR(__xludf.DUMMYFUNCTION("""COMPUTED_VALUE"""),1850.0) -> 1850 | D99: =IFERROR(__xludf.DUMMYFUNCTION("""COMPUTED_VALUE"""),1865.0) -> 1865 | E99: =IFERROR(__xludf.DUMMYFUNCTION("""COMPUTED_VALUE"""),1840.0) -> 1840 | F99: =IFERROR(__xludf.DUMMYFUNCTION("""COMPUTED_VALUE"""),1840.0) -> 1840 | G99: =IFERROR(__xludf.DUMMYFUNCTION("""COMPUTED_VALUE"""),2.095847E7) -> 20958470
B100: =IFERROR(__xludf.DUMMYFUNCTION("""COMPUTED_VALUE"""),46108.5625) -> 46108.562 | C100: =IFERROR(__xludf.DUMMYFUNCTION("""COMPUTED_VALUE"""),1805.0) -> 1805 | D100: =IFERROR(__xludf.DUMMYFUNCTION("""COMPUTED_VALUE"""),1825.0) -> 1825 | E100: =IFERROR(__xludf.DUMMYFUNCTION("""COMPUTED_VALUE"""),1800.0) -> 1800 | F100: =IFERROR(__xludf.DUMMYFUNCTION("""COMPUTED_VALUE"""),1820.0) -> 1820 | G100: =IFERROR(__xludf.DUMMYFUNCTION("""COMPUTED_VALUE"""),2.897414E7) -> 28974140
B101: =IFERROR(__xludf.DUMMYFUNCTION("""COMPUTED_VALUE"""),46111.5625) -> 46111.562 | C101: =IFERROR(__xludf.DUMMYFUNCTION("""COMPUTED_VALUE"""),1780.0) -> 1780 | D101: =IFERROR(__xludf.DUMMYFUNCTION("""COMPUTED_VALUE"""),1800.0) -> 1800 | E101: =IFERROR(__xludf.DUMMYFUNCTION("""COMPUTED_VALUE"""),1780.0) -> 1780 | F101: =IFERROR(__xludf.DUMMYFUNCTION("""COMPUTED_VALUE"""),1780.0) -> 1780 | G101: =IFERROR(__xludf.DUMMYFUNCTION("""COMPUTED_VALUE"""),3.98897E7) -> 39889700
B102: =IFERROR(__xludf.DUMMYFUNCTION("""COMPUTED_VALUE"""),46112.5625) -> 46112.562 | C102: =IFERROR(__xludf.DUMMYFUNCTION("""COMPUTED_VALUE"""),1775.0) -> 1775 | D102: =IFERROR(__xludf.DUMMYFUNCTION("""COMPUTED_VALUE"""),1790.0) -> 1790 | E102: =IFERROR(__xludf.DUMMYFUNCTION("""COMPUTED_VALUE"""),1760.0) -> 1760 | F102: =IFERROR(__xludf.DUMMYFUNCTION("""COMPUTED_VALUE"""),1760.0) -> 1760 | G102: =IFERROR(__xludf.DUMMYFUNCTION("""COMPUTED_VALUE"""),4.9221091E7) -> 49221091
B103: =IFERROR(__xludf.DUMMYFUNCTION("""COMPUTED_VALUE"""),46113.5625) -> 46113.562 | C103: =IFERROR(__xludf.DUMMYFUNCTION("""COMPUTED_VALUE"""),1840.0) -> 1840 | D103: =IFERROR(__xludf.DUMMYFUNCTION("""COMPUTED_VALUE"""),1855.0) -> 1855 | E103: =IFERROR(__xludf.DUMMYFUNCTION("""COMPUTED_VALUE"""),1830.0) -> 1830 | F103: =IFERROR(__xludf.DUMMYFUNCTION("""COMPUTED_VALUE"""),1855.0) -> 1855 | G103: =IFERROR(__xludf.DUMMYFUNCTION("""COMPUTED_VALUE"""),3.5537379E7) -> 35537379
B104: =IFERROR(__xludf.DUMMYFUNCTION("""COMPUTED_VALUE"""),46114.5625) -> 46114.562 | C104: =IFERROR(__xludf.DUMMYFUNCTION("""COMPUTED_VALUE"""),1865.0) -> 1865 | D104: =IFERROR(__xludf.DUMMYFUNCTION("""COMPUTED_VALUE"""),1865.0) -> 1865 | E104: =IFERROR(__xludf.DUMMYFUNCTION("""COMPUTED_VALUE"""),1805.0) -> 1805 | F104: =IFERROR(__xludf.DUMMYFUNCTION("""COMPUTED_VALUE"""),1810.0) -> 1810 | G104: =IFERROR(__xludf.DUMMYFUNCTION("""COMPUTED_VALUE"""),2.5132417E7) -> 25132417
B105: =IFERROR(__xludf.DUMMYFUNCTION("""COMPUTED_VALUE"""),46119.5625) -> 46119.562 | C105: =IFERROR(__xludf.DUMMYFUNCTION("""COMPUTED_VALUE"""),1850.0) -> 1850 | D105: =IFERROR(__xludf.DUMMYFUNCTION("""COMPUTED_VALUE"""),1860.0) -> 1860 | E105: =IFERROR(__xludf.DUMMYFUNCTION("""COMPUTED_VALUE"""),1835.0) -> 1835 | F105: =IFERROR(__xludf.DUMMYFUNCTION("""COMPUTED_VALUE"""),1860.0) -> 1860 | G105: =IFERROR(__xludf.DUMMYFUNCTION("""COMPUTED_VALUE"""),1.7953562E7) -> 17953562
B106: =IFERROR(__xludf.DUMMYFUNCTION("""COMPUTED_VALUE"""),46120.5625) -> 46120.562 | C106: =IFERROR(__xludf.DUMMYFUNCTION("""COMPUTED_VALUE"""),1935.0) -> 1935 | D106: =IFERROR(__xludf.DUMMYFUNCTION("""COMPUTED_VALUE"""),1950.0) -> 1950 | E106: =IFERROR(__xludf.DUMMYFUNCTION("""COMPUTED_VALUE"""),1925.0) -> 1925 | F106: =IFERROR(__xludf.DUMMYFUNCTION("""COMPUTED_VALUE"""),1950.0) -> 1950 | G106: =IFERROR(__xludf.DUMMYFUNCTION("""COMPUTED_VALUE"""),4.6515921E7) -> 46515921
B107: =IFERROR(__xludf.DUMMYFUNCTION("""COMPUTED_VALUE"""),46121.5625) -> 46121.562 | C107: =IFERROR(__xludf.DUMMYFUNCTION("""COMPUTED_VALUE"""),1945.0) -> 1945 | D107: =IFERROR(__xludf.DUMMYFUNCTION("""COMPUTED_VALUE"""),1955.0) -> 1955 | E107: =IFERROR(__xludf.DUMMYFUNCTION("""COMPUTED_VALUE"""),1930.0) -> 1930 | F107: =IFERROR(__xludf.DUMMYFUNCTION("""COMPUTED_VALUE"""),1955.0) -> 1955 | G107: =IFERROR(__xludf.DUMMYFUNCTION("""COMPUTED_VALUE"""),3.1835073E7) -> 31835073
B108: =IFERROR(__xludf.DUMMYFUNCTION("""COMPUTED_VALUE"""),46122.5625) -> 46122.562 | C108: =IFERROR(__xludf.DUMMYFUNCTION("""COMPUTED_VALUE"""),1975.0) -> 1975 | D108: =IFERROR(__xludf.DUMMYFUNCTION("""COMPUTED_VALUE"""),2000.0) -> 2000 | E108: =IFERROR(__xludf.DUMMYFUNCTION("""COMPUTED_VALUE"""),1970.0) -> 1970 | F108: =IFERROR(__xludf.DUMMYFUNCTION("""COMPUTED_VALUE"""),2000.0) -> 2000 | G108: =IFERROR(__xludf.DUMMYFUNCTION("""COMPUTED_VALUE"""),2.8637625E7) -> 28637625
B109: =IFERROR(__xludf.DUMMYFUNCTION("""COMPUTED_VALUE"""),46125.5625) -> 46125.562 | C109: =IFERROR(__xludf.DUMMYFUNCTION("""COMPUTED_VALUE"""),1985.0) -> 1985 | D109: =IFERROR(__xludf.DUMMYFUNCTION("""COMPUTED_VALUE"""),1995.0) -> 1995 | E109: =IFERROR(__xludf.DUMMYFUNCTION("""COMPUTED_VALUE"""),1975.0) -> 1975 | F109: =IFERROR(__xludf.DUMMYFUNCTION("""COMPUTED_VALUE"""),1990.0) -> 1990 | G109: =IFERROR(__xludf.DUMMYFUNCTION("""COMPUTED_VALUE"""),2.8968757E7) -> 28968757
B110: =IFERROR(__xludf.DUMMYFUNCTION("""COMPUTED_VALUE"""),46126.5625) -> 46126.562 | C110: =IFERROR(__xludf.DUMMYFUNCTION("""COMPUTED_VALUE"""),2015.0) -> 2015 | D110: =IFERROR(__xludf.DUMMYFUNCTION("""COMPUTED_VALUE"""),2055.0) -> 2055 | E110: =IFERROR(__xludf.DUMMYFUNCTION("""COMPUTED_VALUE"""),2010.0) -> 2010 | F110: =IFERROR(__xludf.DUMMYFUNCTION("""COMPUTED_VALUE"""),2055.0) -> 2055 | G110: =IFERROR(__xludf.DUMMYFUNCTION("""COMPUTED_VALUE"""),3.9113405E7) -> 39113405
B111: =IFERROR(__xludf.DUMMYFUNCTION("""COMPUTED_VALUE"""),46127.5625) -> 46127.562 | C111: =IFERROR(__xludf.DUMMYFUNCTION("""COMPUTED_VALUE"""),2065.0) -> 2065 | D111: =IFERROR(__xludf.DUMMYFUNCTION("""COMPUTED_VALUE"""),2100.0) -> 2100 | E111: =IFERROR(__xludf.DUMMYFUNCTION("""COMPUTED_VALUE"""),2060.0) -> 2060 | F111: =IFERROR(__xludf.DUMMYFUNCTION("""COMPUTED_VALUE"""),2080.0) -> 2080 | G111: =IFERROR(__xludf.DUMMYFUNCTION("""COMPUTED_VALUE"""),4.0343568E7) -> 40343568
B112: =IFERROR(__xludf.DUMMYFUNCTION("""COMPUTED_VALUE"""),46128.5625) -> 46128.562 | C112: =IFERROR(__xludf.DUMMYFUNCTION("""COMPUTED_VALUE"""),2080.0) -> 2080 | D112: =IFERROR(__xludf.DUMMYFUNCTION("""COMPUTED_VALUE"""),2090.0) -> 2090 | E112: =IFERROR(__xludf.DUMMYFUNCTION("""COMPUTED_VALUE"""),2055.0) -> 2055 | F112: =IFERROR(__xludf.DUMMYFUNCTION("""COMPUTED_VALUE"""),2085.0) -> 2085 | G112: =IFERROR(__xludf.DUMMYFUNCTION("""COMPUTED_VALUE"""),3.2038524E7) -> 32038524
B113: =IFERROR(__xludf.DUMMYFUNCTION("""COMPUTED_VALUE"""),46129.5625) -> 46129.562 | C113: =IFERROR(__xludf.DUMMYFUNCTION("""COMPUTED_VALUE"""),2055.0) -> 2055 | D113: =IFERROR(__xludf.DUMMYFUNCTION("""COMPUTED_VALUE"""),2060.0) -> 2060 | E113: =IFERROR(__xludf.DUMMYFUNCTION("""COMPUTED_VALUE"""),2030.0) -> 2030 | F113: =IFERROR(__xludf.DUMMYFUNCTION("""COMPUTED_VALUE"""),2030.0) -> 2030 | G113: =IFERROR(__xludf.DUMMYFUNCTION("""COMPUTED_VALUE"""),3.9260244E7) -> 39260244
B114: =IFERROR(__xludf.DUMMYFUNCTION("""COMPUTED_VALUE"""),46132.5625) -> 46132.562 | C114: =IFERROR(__xludf.DUMMYFUNCTION("""COMPUTED_VALUE"""),2030.0) -> 2030 | D114: =IFERROR(__xludf.DUMMYFUNCTION("""COMPUTED_VALUE"""),2055.0) -> 2055 | E114: =IFERROR(__xludf.DUMMYFUNCTION("""COMPUTED_VALUE"""),2025.0) -> 2025 | F114: =IFERROR(__xludf.DUMMYFUNCTION("""COMPUTED_VALUE"""),2025.0) -> 2025 | G114: =IFERROR(__xludf.DUMMYFUNCTION("""COMPUTED_VALUE"""),2.5407621E7) -> 25407621
...

Sheet 00692 富邦公司治理
B2: TPE:00692 | C2: << enter a symbol
C3: << optionally, enter an exchange (ex: NASDAQ, NYSE)
B5: =IFERROR(__xludf.DUMMYFUNCTION("GOOGLEFINANCE(B16,""name"")"),"FUBON TWSE CORPORATE GOVERNANCE 100 ETF") -> FUBON TWSE CORPORATE GOVERNANCE 100 ETF | O5: BUY
B7: Current Price | D7: Change | E7: % Change | J7: 持有股數 | K7: 持有成本 | L7: 平均股價 | N7: 類型
B8: =IFERROR(__xludf.DUMMYFUNCTION("GOOGLEFINANCE(B16,""price"")"),90.45) -> 90.45 | D8: =IFERROR(__xludf.DUMMYFUNCTION("IFERROR(GOOGLEFINANCE(B16,""change""),""-"")"),3.2) -> 3.2 | E8: =IFERROR(__xludf.DUMMYFUNCTION("IFERROR(GOOGLEFINANCE(B16,""changepct"")/100,""-"")"),0.036699999999999997) -> 0.0367 | J8: =SUM(K26:K100) -> 7500 | K8: =SUM(N26:N100) -> 258743 | L8: =K8/J8 -> 34.499067 | N8: 指數ETF
B11: Market Cap | C11: P/E Ratio | D11: Beta
B12: =IFERROR(__xludf.DUMMYFUNCTION("IFERROR(GOOGLEFINANCE(B16,""marketcap""),""-"")"),"-") -> - | C12: =IFERROR(__xludf.DUMMYFUNCTION("IFERROR(GOOGLEFINANCE(B16,""pe""),""-"")"),"-") -> - | D12: =IFERROR(__xludf.DUMMYFUNCTION("IFERROR(GOOGLEFINANCE(B16,""beta""),""-"")"),"-") -> -
G13: 36 Months
B16: =IF(ISBLANK(B3),"",B3&":")&B2 -> TPE:00692
J24: Transaction detail list
B25: =IFERROR(__xludf.DUMMYFUNCTION("GOOGLEFINANCE(B16, ""all"", EDATE(TODAY(), -LEFT(G13, FIND("" "", G13))), TODAY(), ""DAILY"")"),"Date") -> Date | C25: =IFERROR(__xludf.DUMMYFUNCTION("""COMPUTED_VALUE"""),"Open") -> Open | D25: =IFERROR(__xludf.DUMMYFUNCTION("""COMPUTED_VALUE"""),"High") -> High | E25: =IFERROR(__xludf.DUMMYFUNCTION("""COMPUTED_VALUE"""),"Low") -> Low | F25: =IFERROR(__xludf.DUMMYFUNCTION("""COMPUTED_VALUE"""),"Close") -> Close | G25: =IFERROR(__xludf.DUMMYFUNCTION("""COMPUTED_VALUE"""),"Volume") -> Volume | J25: Date | K25: Shares | L25: Prices | M25: Fee | N25: Cost | O25: Average Cost | P25: Note
B26: =IFERROR(__xludf.DUMMYFUNCTION("""COMPUTED_VALUE"""),45076.5625) -> 45076.562 | C26: =IFERROR(__xludf.DUMMYFUNCTION("""COMPUTED_VALUE"""),31.56) -> 31.56 | D26: =IFERROR(__xludf.DUMMYFUNCTION("""COMPUTED_VALUE"""),31.64) -> 31.64 | E26: =IFERROR(__xludf.DUMMYFUNCTION("""COMPUTED_VALUE"""),31.47) -> 31.47 | F26: =IFERROR(__xludf.DUMMYFUNCTION("""COMPUTED_VALUE"""),31.56) -> 31.56 | G26: =IFERROR(__xludf.DUMMYFUNCTION("""COMPUTED_VALUE"""),2208747.0) -> 2208747 | J26: 43879 | K26: 1000 | L26: 23.45 | M26: 20 | N26: =K26*L26+M26 -> 23470 | O26: =N26/K26 -> 23.47
B27: =IFERROR(__xludf.DUMMYFUNCTION("""COMPUTED_VALUE"""),45077.5625) -> 45077.562 | C27: =IFERROR(__xludf.DUMMYFUNCTION("""COMPUTED_VALUE"""),31.56) -> 31.56 | D27: =IFERROR(__xludf.DUMMYFUNCTION("""COMPUTED_VALUE"""),31.56) -> 31.56 | E27: =IFERROR(__xludf.DUMMYFUNCTION("""COMPUTED_VALUE"""),31.26) -> 31.26 | F27: =IFERROR(__xludf.DUMMYFUNCTION("""COMPUTED_VALUE"""),31.46) -> 31.46 | G27: =IFERROR(__xludf.DUMMYFUNCTION("""COMPUTED_VALUE"""),1203835.0) -> 1203835 | J27: 44046 | K27: 1000 | L27: 26.18 | M27: 20 | N27: =K27*L27+M27 -> 26200 | O27: =SUM($N$26:N27)/SUM($K$26:K27) -> 24.835
B28: =IFERROR(__xludf.DUMMYFUNCTION("""COMPUTED_VALUE"""),45078.5625) -> 45078.562 | C28: =IFERROR(__xludf.DUMMYFUNCTION("""COMPUTED_VALUE"""),31.32) -> 31.32 | D28: =IFERROR(__xludf.DUMMYFUNCTION("""COMPUTED_VALUE"""),31.35) -> 31.35 | E28: =IFERROR(__xludf.DUMMYFUNCTION("""COMPUTED_VALUE"""),31.2) -> 31.2 | F28: =IFERROR(__xludf.DUMMYFUNCTION("""COMPUTED_VALUE"""),31.28) -> 31.28 | G28: =IFERROR(__xludf.DUMMYFUNCTION("""COMPUTED_VALUE"""),1665850.0) -> 1665850 | J28: 44845 | K28: 500 | L28: 25.47 | M28: 20 | N28: =K28*L28+M28 -> 12755 | O28: =SUM($N$26:N28)/SUM($K$26:K28) -> 24.97
B29: =IFERROR(__xludf.DUMMYFUNCTION("""COMPUTED_VALUE"""),45079.5625) -> 45079.562 | C29: =IFERROR(__xludf.DUMMYFUNCTION("""COMPUTED_VALUE"""),31.3) -> 31.3 | D29: =IFERROR(__xludf.DUMMYFUNCTION("""COMPUTED_VALUE"""),31.72) -> 31.72 | E29: =IFERROR(__xludf.DUMMYFUNCTION("""COMPUTED_VALUE"""),31.3) -> 31.3 | F29: =IFERROR(__xludf.DUMMYFUNCTION("""COMPUTED_VALUE"""),31.66) -> 31.66 | G29: =IFERROR(__xludf.DUMMYFUNCTION("""COMPUTED_VALUE"""),2381586.0) -> 2381586 | J29: 45133 | K29: 500 | L29: 32.57 | M29: 20 | N29: =K29*L29+M29 -> 16305 | O29: =SUM($N$26:N29)/SUM($K$26:K29) -> 26.243333
B30: =IFERROR(__xludf.DUMMYFUNCTION("""COMPUTED_VALUE"""),45082.5625) -> 45082.562 | C30: =IFERROR(__xludf.DUMMYFUNCTION("""COMPUTED_VALUE"""),31.68) -> 31.68 | D30: =IFERROR(__xludf.DUMMYFUNCTION("""COMPUTED_VALUE"""),31.7) -> 31.7 | E30: =IFERROR(__xludf.DUMMYFUNCTION("""COMPUTED_VALUE"""),31.58) -> 31.58 | F30: =IFERROR(__xludf.DUMMYFUNCTION("""COMPUTED_VALUE"""),31.59) -> 31.59 | G30: =IFERROR(__xludf.DUMMYFUNCTION("""COMPUTED_VALUE"""),1782328.0) -> 1782328 | J30: 45142 | K30: 500 | L30: 31.91 | M30: 12 | N30: =K30*L30+M30 -> 15967 | O30: =SUM($N$26:N30)/SUM($K$26:K30) -> 27.056286
B31: =IFERROR(__xludf.DUMMYFUNCTION("""COMPUTED_VALUE"""),45083.5625) -> 45083.562 | C31: =IFERROR(__xludf.DUMMYFUNCTION("""COMPUTED_VALUE"""),31.59) -> 31.59 | D31: =IFERROR(__xludf.DUMMYFUNCTION("""COMPUTED_VALUE"""),31.86) -> 31.86 | E31: =IFERROR(__xludf.DUMMYFUNCTION("""COMPUTED_VALUE"""),31.58) -> 31.58 | F31: =IFERROR(__xludf.DUMMYFUNCTION("""COMPUTED_VALUE"""),31.8) -> 31.8 | G31: =IFERROR(__xludf.DUMMYFUNCTION("""COMPUTED_VALUE"""),3119797.0) -> 3119797 | J31: 45159 | K31: 500 | L31: 31.09 | M31: 12 | N31: =K31*L31+M31 -> 15557 | O31: =SUM($N$26:N31)/SUM($K$26:K31) -> 27.5635
B32: =IFERROR(__xludf.DUMMYFUNCTION("""COMPUTED_VALUE"""),45084.5625) -> 45084.562 | C32: =IFERROR(__xludf.DUMMYFUNCTION("""COMPUTED_VALUE"""),31.84) -> 31.84 | D32: =IFERROR(__xludf.DUMMYFUNCTION("""COMPUTED_VALUE"""),32.05) -> 32.05 | E32: =IFERROR(__xludf.DUMMYFUNCTION("""COMPUTED_VALUE"""),31.82) -> 31.82 | F32: =IFERROR(__xludf.DUMMYFUNCTION("""COMPUTED_VALUE"""),32.05) -> 32.05 | G32: =IFERROR(__xludf.DUMMYFUNCTION("""COMPUTED_VALUE"""),2741304.0) -> 2741304 | J32: 45499 | K32: 500 | L32: 42.05 | M32: 16 | N32: =K32*L32+M32 -> 21041 | O32: =SUM($N$26:N32)/SUM($K$26:K32) -> 29.176667
B33: =IFERROR(__xludf.DUMMYFUNCTION("""COMPUTED_VALUE"""),45085.5625) -> 45085.562 | C33: =IFERROR(__xludf.DUMMYFUNCTION("""COMPUTED_VALUE"""),32.03) -> 32.03 | D33: =IFERROR(__xludf.DUMMYFUNCTION("""COMPUTED_VALUE"""),32.03) -> 32.03 | E33: =IFERROR(__xludf.DUMMYFUNCTION("""COMPUTED_VALUE"""),31.63) -> 31.63 | F33: =IFERROR(__xludf.DUMMYFUNCTION("""COMPUTED_VALUE"""),31.72) -> 31.72 | G33: =IFERROR(__xludf.DUMMYFUNCTION("""COMPUTED_VALUE"""),2941389.0) -> 2941389 | J33: 45506 | K33: 500 | L33: 42.02 | M33: 20 | N33: =K33*L33+M33 -> 21030 | O33: =SUM($N$26:N33)/SUM($K$26:K33) -> 30.465
B34: =IFERROR(__xludf.DUMMYFUNCTION("""COMPUTED_VALUE"""),45086.5625) -> 45086.562 | C34: =IFERROR(__xludf.DUMMYFUNCTION("""COMPUTED_VALUE"""),31.82) -> 31.82 | D34: =IFERROR(__xludf.DUMMYFUNCTION("""COMPUTED_VALUE"""),32.0) -> 32 | E34: =IFERROR(__xludf.DUMMYFUNCTION("""COMPUTED_VALUE"""),31.8) -> 31.8 | F34: =IFERROR(__xludf.DUMMYFUNCTION("""COMPUTED_VALUE"""),31.98) -> 31.98 | G34: =IFERROR(__xludf.DUMMYFUNCTION("""COMPUTED_VALUE"""),1629907.0) -> 1629907 | J34: 45509 | K34: 500 | L34: 39 | M34: 15 | N34: =K34*L34+M34 -> 19515 | O34: =SUM($N$26:N34)/SUM($K$26:K34) -> 31.243636
B35: =IFERROR(__xludf.DUMMYFUNCTION("""COMPUTED_VALUE"""),45089.5625) -> 45089.562 | C35: =IFERROR(__xludf.DUMMYFUNCTION("""COMPUTED_VALUE"""),32.02) -> 32.02 | D35: =IFERROR(__xludf.DUMMYFUNCTION("""COMPUTED_VALUE"""),32.24) -> 32.24 | E35: =IFERROR(__xludf.DUMMYFUNCTION("""COMPUTED_VALUE"""),32.02) -> 32.02 | F35: =IFERROR(__xludf.DUMMYFUNCTION("""COMPUTED_VALUE"""),32.17) -> 32.17 | G35: =IFERROR(__xludf.DUMMYFUNCTION("""COMPUTED_VALUE"""),1576598.0) -> 1576598 | J35: 45539 | K35: 500 | L35: 40.43 | M35: 16 | N35: =K35*L35+M35 -> 20231 | O35: =SUM($N$26:N35)/SUM($K$26:K35) -> 32.011833
B36: =IFERROR(__xludf.DUMMYFUNCTION("""COMPUTED_VALUE"""),45090.5625) -> 45090.562 | C36: =IFERROR(__xludf.DUMMYFUNCTION("""COMPUTED_VALUE"""),32.41) -> 32.41 | D36: =IFERROR(__xludf.DUMMYFUNCTION("""COMPUTED_VALUE"""),32.79) -> 32.79 | E36: =IFERROR(__xludf.DUMMYFUNCTION("""COMPUTED_VALUE"""),32.41) -> 32.41 | F36: =IFERROR(__xludf.DUMMYFUNCTION("""COMPUTED_VALUE"""),32.74) -> 32.74 | G36: =IFERROR(__xludf.DUMMYFUNCTION("""COMPUTED_VALUE"""),9618461.0) -> 9618461 | J36: 45597 | K36: 1000 | L36: 44.32 | M36: 35 | N36: =K36*L36+M36 -> 44355 | O36: =SUM($N$26:N36)/SUM($K$26:K36) -> 33.775143
B37: =IFERROR(__xludf.DUMMYFUNCTION("""COMPUTED_VALUE"""),45091.5625) -> 45091.562 | C37: =IFERROR(__xludf.DUMMYFUNCTION("""COMPUTED_VALUE"""),32.71) -> 32.71 | D37: =IFERROR(__xludf.DUMMYFUNCTION("""COMPUTED_VALUE"""),32.78) -> 32.78 | E37: =IFERROR(__xludf.DUMMYFUNCTION("""COMPUTED_VALUE"""),32.66) -> 32.66 | F37: =IFERROR(__xludf.DUMMYFUNCTION("""COMPUTED_VALUE"""),32.76) -> 32.76 | G37: =IFERROR(__xludf.DUMMYFUNCTION("""COMPUTED_VALUE"""),1877387.0) -> 1877387 | J37: 45691 | K37: 500 | L37: 44.6 | M37: 17 | N37: =K37*L37+M37 -> 22317 | O37: =SUM($N$26:N37)/SUM($K$26:K37) -> 34.499067
B38: =IFERROR(__xludf.DUMMYFUNCTION("""COMPUTED_VALUE"""),45092.5625) -> 45092.562 | C38: =IFERROR(__xludf.DUMMYFUNCTION("""COMPUTED_VALUE"""),32.76) -> 32.76 | D38: =IFERROR(__xludf.DUMMYFUNCTION("""COMPUTED_VALUE"""),33.0) -> 33 | E38: =IFERROR(__xludf.DUMMYFUNCTION("""COMPUTED_VALUE"""),32.76) -> 32.76 | F38: =IFERROR(__xludf.DUMMYFUNCTION("""COMPUTED_VALUE"""),32.92) -> 32.92 | G38: =IFERROR(__xludf.DUMMYFUNCTION("""COMPUTED_VALUE"""),2224959.0) -> 2224959 | N38: =K38*L38+M38 -> 0 | O38: =SUM($N$26:N38)/SUM($K$26:K38) -> 34.499067
B39: =IFERROR(__xludf.DUMMYFUNCTION("""COMPUTED_VALUE"""),45093.5625) -> 45093.562 | C39: =IFERROR(__xludf.DUMMYFUNCTION("""COMPUTED_VALUE"""),32.92) -> 32.92 | D39: =IFERROR(__xludf.DUMMYFUNCTION("""COMPUTED_VALUE"""),32.94) -> 32.94 | E39: =IFERROR(__xludf.DUMMYFUNCTION("""COMPUTED_VALUE"""),32.78) -> 32.78 | F39: =IFERROR(__xludf.DUMMYFUNCTION("""COMPUTED_VALUE"""),32.89) -> 32.89 | G39: =IFERROR(__xludf.DUMMYFUNCTION("""COMPUTED_VALUE"""),3125048.0) -> 3125048 | N39: =K39*L39+M39 -> 0 | O39: =SUM($N$26:N39)/SUM($K$26:K39) -> 34.499067
B40: =IFERROR(__xludf.DUMMYFUNCTION("""COMPUTED_VALUE"""),45096.5625) -> 45096.562 | C40: =IFERROR(__xludf.DUMMYFUNCTION("""COMPUTED_VALUE"""),32.84) -> 32.84 | D40: =IFERROR(__xludf.DUMMYFUNCTION("""COMPUTED_VALUE"""),32.89) -> 32.89 | E40: =IFERROR(__xludf.DUMMYFUNCTION("""COMPUTED_VALUE"""),32.7) -> 32.7 | F40: =IFERROR(__xludf.DUMMYFUNCTION("""COMPUTED_VALUE"""),32.85) -> 32.85 | G40: =IFERROR(__xludf.DUMMYFUNCTION("""COMPUTED_VALUE"""),2242288.0) -> 2242288 | N40: =K40*L40+M40 -> 0 | O40: =SUM($N$26:N40)/SUM($K$26:K40) -> 34.499067
B41: =IFERROR(__xludf.DUMMYFUNCTION("""COMPUTED_VALUE"""),45097.5625) -> 45097.562 | C41: =IFERROR(__xludf.DUMMYFUNCTION("""COMPUTED_VALUE"""),32.84) -> 32.84 | D41: =IFERROR(__xludf.DUMMYFUNCTION("""COMPUTED_VALUE"""),32.84) -> 32.84 | E41: =IFERROR(__xludf.DUMMYFUNCTION("""COMPUTED_VALUE"""),32.6) -> 32.6 | F41: =IFERROR(__xludf.DUMMYFUNCTION("""COMPUTED_VALUE"""),32.71) -> 32.71 | G41: =IFERROR(__xludf.DUMMYFUNCTION("""COMPUTED_VALUE"""),1494425.0) -> 1494425 | J41: =TODAY() -> 46172 | L41: =B8 -> 90.45 | N41: =K41*L41+M41 -> 0 | O41: =SUM($N$26:N41)/SUM($K$26:K41) -> 34.499067
B42: =IFERROR(__xludf.DUMMYFUNCTION("""COMPUTED_VALUE"""),45098.5625) -> 45098.562 | C42: =IFERROR(__xludf.DUMMYFUNCTION("""COMPUTED_VALUE"""),32.64) -> 32.64 | D42: =IFERROR(__xludf.DUMMYFUNCTION("""COMPUTED_VALUE"""),32.82) -> 32.82 | E42: =IFERROR(__xludf.DUMMYFUNCTION("""COMPUTED_VALUE"""),32.58) -> 32.58 | F42: =IFERROR(__xludf.DUMMYFUNCTION("""COMPUTED_VALUE"""),32.75) -> 32.75 | G42: =IFERROR(__xludf.DUMMYFUNCTION("""COMPUTED_VALUE"""),3248823.0) -> 3248823
B43: =IFERROR(__xludf.DUMMYFUNCTION("""COMPUTED_VALUE"""),45103.5625) -> 45103.562 | C43: =IFERROR(__xludf.DUMMYFUNCTION("""COMPUTED_VALUE"""),32.5) -> 32.5 | D43: =IFERROR(__xludf.DUMMYFUNCTION("""COMPUTED_VALUE"""),32.65) -> 32.65 | E43: =IFERROR(__xludf.DUMMYFUNCTION("""COMPUTED_VALUE"""),32.45) -> 32.45 | F43: =IFERROR(__xludf.DUMMYFUNCTION("""COMPUTED_VALUE"""),32.56) -> 32.56 | G43: =IFERROR(__xludf.DUMMYFUNCTION("""COMPUTED_VALUE"""),2750073.0) -> 2750073
B44: =IFERROR(__xludf.DUMMYFUNCTION("""COMPUTED_VALUE"""),45104.5625) -> 45104.562 | C44: =IFERROR(__xludf.DUMMYFUNCTION("""COMPUTED_VALUE"""),32.47) -> 32.47 | D44: =IFERROR(__xludf.DUMMYFUNCTION("""COMPUTED_VALUE"""),32.5) -> 32.5 | E44: =IFERROR(__xludf.DUMMYFUNCTION("""COMPUTED_VALUE"""),32.31) -> 32.31 | F44: =IFERROR(__xludf.DUMMYFUNCTION("""COMPUTED_VALUE"""),32.34) -> 32.34 | G44: =IFERROR(__xludf.DUMMYFUNCTION("""COMPUTED_VALUE"""),2113436.0) -> 2113436
B45: =IFERROR(__xludf.DUMMYFUNCTION("""COMPUTED_VALUE"""),45105.5625) -> 45105.562 | C45: =IFERROR(__xludf.DUMMYFUNCTION("""COMPUTED_VALUE"""),32.38) -> 32.38 | D45: =IFERROR(__xludf.DUMMYFUNCTION("""COMPUTED_VALUE"""),32.47) -> 32.47 | E45: =IFERROR(__xludf.DUMMYFUNCTION("""COMPUTED_VALUE"""),32.3) -> 32.3 | F45: =IFERROR(__xludf.DUMMYFUNCTION("""COMPUTED_VALUE"""),32.36) -> 32.36 | G45: =IFERROR(__xludf.DUMMYFUNCTION("""COMPUTED_VALUE"""),2899639.0) -> 2899639
B46: =IFERROR(__xludf.DUMMYFUNCTION("""COMPUTED_VALUE"""),45106.5625) -> 45106.562 | C46: =IFERROR(__xludf.DUMMYFUNCTION("""COMPUTED_VALUE"""),32.55) -> 32.55 | D46: =IFERROR(__xludf.DUMMYFUNCTION("""COMPUTED_VALUE"""),32.68) -> 32.68 | E46: =IFERROR(__xludf.DUMMYFUNCTION("""COMPUTED_VALUE"""),32.32) -> 32.32 | F46: =IFERROR(__xludf.DUMMYFUNCTION("""COMPUTED_VALUE"""),32.37) -> 32.37 | G46: =IFERROR(__xludf.DUMMYFUNCTION("""COMPUTED_VALUE"""),3728493.0) -> 3728493
B47: =IFERROR(__xludf.DUMMYFUNCTION("""COMPUTED_VALUE"""),45107.5625) -> 45107.562 | C47: =IFERROR(__xludf.DUMMYFUNCTION("""COMPUTED_VALUE"""),32.37) -> 32.37 | D47: =IFERROR(__xludf.DUMMYFUNCTION("""COMPUTED_VALUE"""),32.46) -> 32.46 | E47: =IFERROR(__xludf.DUMMYFUNCTION("""COMPUTED_VALUE"""),32.25) -> 32.25 | F47: =IFERROR(__xludf.DUMMYFUNCTION("""COMPUTED_VALUE"""),32.46) -> 32.46 | G47: =IFERROR(__xludf.DUMMYFUNCTION("""COMPUTED_VALUE"""),2158609.0) -> 2158609
B48: =IFERROR(__xludf.DUMMYFUNCTION("""COMPUTED_VALUE"""),45110.5625) -> 45110.562 | C48: =IFERROR(__xludf.DUMMYFUNCTION("""COMPUTED_VALUE"""),32.52) -> 32.52 | D48: =IFERROR(__xludf.DUMMYFUNCTION("""COMPUTED_VALUE"""),32.89) -> 32.89 | E48: =IFERROR(__xludf.DUMMYFUNCTION("""COMPUTED_VALUE"""),32.52) -> 32.52 | F48: =IFERROR(__xludf.DUMMYFUNCTION("""COMPUTED_VALUE"""),32.85) -> 32.85 | G48: =IFERROR(__xludf.DUMMYFUNCTION("""COMPUTED_VALUE"""),2239965.0) -> 2239965
B49: =IFERROR(__xludf.DUMMYFUNCTION("""COMPUTED_VALUE"""),45111.5625) -> 45111.562 | C49: =IFERROR(__xludf.DUMMYFUNCTION("""COMPUTED_VALUE"""),32.9) -> 32.9 | D49: =IFERROR(__xludf.DUMMYFUNCTION("""COMPUTED_VALUE"""),32.97) -> 32.97 | E49: =IFERROR(__xludf.DUMMYFUNCTION("""COMPUTED_VALUE"""),32.8) -> 32.8 | F49: =IFERROR(__xludf.DUMMYFUNCTION("""COMPUTED_VALUE"""),32.97) -> 32.97 | G49: =IFERROR(__xludf.DUMMYFUNCTION("""COMPUTED_VALUE"""),2576274.0) -> 2576274
B50: =IFERROR(__xludf.DUMMYFUNCTION("""COMPUTED_VALUE"""),45112.5625) -> 45112.562 | C50: =IFERROR(__xludf.DUMMYFUNCTION("""COMPUTED_VALUE"""),32.97) -> 32.97 | D50: =IFERROR(__xludf.DUMMYFUNCTION("""COMPUTED_VALUE"""),32.97) -> 32.97 | E50: =IFERROR(__xludf.DUMMYFUNCTION("""COMPUTED_VALUE"""),32.74) -> 32.74 | F50: =IFERROR(__xludf.DUMMYFUNCTION("""COMPUTED_VALUE"""),32.82) -> 32.82 | G50: =IFERROR(__xludf.DUMMYFUNCTION("""COMPUTED_VALUE"""),1897359.0) -> 1897359
B51: =IFERROR(__xludf.DUMMYFUNCTION("""COMPUTED_VALUE"""),45113.5625) -> 45113.562 | C51: =IFERROR(__xludf.DUMMYFUNCTION("""COMPUTED_VALUE"""),32.53) -> 32.53 | D51: =IFERROR(__xludf.DUMMYFUNCTION("""COMPUTED_VALUE"""),32.57) -> 32.57 | E51: =IFERROR(__xludf.DUMMYFUNCTION("""COMPUTED_VALUE"""),32.19) -> 32.19 | F51: =IFERROR(__xludf.DUMMYFUNCTION("""COMPUTED_VALUE"""),32.29) -> 32.29 | G51: =IFERROR(__xludf.DUMMYFUNCTION("""COMPUTED_VALUE"""),5305953.0) -> 5305953
B52: =IFERROR(__xludf.DUMMYFUNCTION("""COMPUTED_VALUE"""),45114.5625) -> 45114.562 | C52: =IFERROR(__xludf.DUMMYFUNCTION("""COMPUTED_VALUE"""),32.02) -> 32.02 | D52: =IFERROR(__xludf.DUMMYFUNCTION("""COMPUTED_VALUE"""),32.29) -> 32.29 | E52: =IFERROR(__xludf.DUMMYFUNCTION("""COMPUTED_VALUE"""),32.0) -> 32 | F52: =IFERROR(__xludf.DUMMYFUNCTION("""COMPUTED_VALUE"""),32.12) -> 32.12 | G52: =IFERROR(__xludf.DUMMYFUNCTION("""COMPUTED_VALUE"""),2736816.0) -> 2736816
